Workbook

Sheet Read Me
A1: HOW TO USE THIS FILE
A3: WEEKLY
A4: 1. Paste the week's sales into Weekly Sales columns A–F (Week ending, Branch CPT/JHB/DBN, Item code, Article, spare, m² sold). Keep adding weeks below each other. Columns H–J fill themselves – never paste over them. Lines marked 'Not on stock sheet' are ignored (transport, cowhides, items with no stock line).
A5: 2. Add any stock moved between branches to Transfers.
A6: 3. New order sent to a supplier: add one line per item on Orders (PO number, order date, supplier, code, due month, branch, m², cost/m²).
A7: 4. Supplier invoice / delivery arrives: add one line per item on Stock Received (date, invoice no., the SAME PO number as on Orders, supplier, code, m², cost/m², branch). It adds to that branch's stock and closes the PO line. Never type received m² on the Orders tab – that column is a formula. A line closes once 90% or more has arrived (change on Settings); over-deliveries close it too.
A8: 5. Change "Stock as at" on the Settings tab to the date of the latest sales, then look at Dashboard → Reorder List, or filter Master Stock on STATUS.
A10: WHEN A NEW STOCK COUNT COMES IN
A11: Replace the m² on CPT Count / JHB Count / DBN Count, update the count dates on Settings, and clear Weekly Sales, Transfers and Stock Received.
A13: HOW THE NUMBERS WORK
A14: Available (per branch) = count m² + stock received − weekly sales for that branch + transfers in − transfers out.
A15: Avg selling m²/month = 6-month Sales History ÷ 6. Until that is loaded, it uses the average on the current CPT stock sheet.
... A28: COLOURS: blue text = typed input · black = formula · green = lookup from another tab · yellow fill = please check / fill in.

Sheet Dashboard
A1: AGS Stock Dashboard – leather hides & sides, all branches
A2: ="Stock as at "&TEXT(Settings!$B$13,"d mmmm yyyy")&" · everything on this page updates from Master Stock." -> Stock as at 9 October 2026 · everything on this page updates from Master Stock.
A4: STOCK AVAILABLE (m²) | G4: ON ORDER (m²) | L4: LINES BY STATUS
B5: CPT | C5: JHB | D5: DBN | E5: TOTAL | G5: Month | H5: For CPT | I5: For JHB | J5: Total | L5: Status | M5: Lines
A6: Hides | B6: =SUMIFS('Master Stock'!$E$5:$E$206,'Master Stock'!$C$5:$C$206,"Hide") -> 48961.5 | C6: =SUMIFS('Master Stock'!$F$5:$F$206,'Master Stock'!$C$5:$C$206,"Hide") -> 16197.83 | D6: =SUMIFS('Master Stock'!$G$5:$G$206,'Master Stock'!$C$5:$C$206,"Hide") -> 3132.66 | E6: =SUMIFS('Master Stock'!$H$5:$H$206,'Master Stock'!$C$5:$C$206,"Hide") -> 68291.99 | G6: ='Master Stock'!J4 -> 46296 | H6: =SUMIFS(Orders!$L:$L,Orders!$F:$F,">="&$G6,Orders!$F:$F,"<"&EDATE($G6,1),Orders!$G:$G,"CPT") -> 5680 | I6: =SUMIFS(Orders!$L:$L,Orders!$F:$F,">="&$G6,Orders!$F:$F,"<"&EDATE($G6,1),Orders!$G:$G,"JHB") -> 2200 | J6: =H6+I6 -> 7880 | L6: OUT - REORDER | M6: =COUNTIF('Master Stock'!$V$5:$V$206,L6) -> 0
A7: Sides | B7: =SUMIFS('Master Stock'!$E$5:$E$206,'Master Stock'!$C$5:$C$206,"Side") -> 14814 | C7: =SUMIFS('Master Stock'!$F$5:$F$206,'Master Stock'!$C$5:$C$206,"Side") -> 2107.75 | D7: =SUMIFS('Master Stock'!$G$5:$G$206,'Master Stock'!$C$5:$C$206,"Side") -> 981.61 | E7: =SUMIFS('Master Stock'!$H$5:$H$206,'Master Stock'!$C$5:$C$206,"Side") -> 17903.36 | G7: ='Master Stock'!K4 -> 46327 | H7: =SUMIFS(Orders!$L:$L,Orders!$F:$F,">="&$G7,Orders!$F:$F,"<"&EDATE($G7,1),Orders!$G:$G,"CPT") -> 17100 | I7: =SUMIFS(Orders!$L:$L,Orders!$F:$F,">="&$G7,Orders!$F:$F,"<"&EDATE($G7,1),Orders!$G:$G,"JHB") -> 8100 | J7: =H7+I7 -> 25200 | L7: REORDER | M7: =COUNTIF('Master Stock'!$V$5:$V$206,L7) -> 4
A8: Total | B8: =SUM(B6:B7) -> 63775.5 | C8: =SUM(C6:C7) -> 18305.58 | D8: =SUM(D6:D7) -> 4114.27 | E8: =SUM(E6:E7) -> 86195.35 | G8: ='Master Stock'!L4 -> 46357 | H8: =SUMIFS(Orders!$L:$L,Orders!$F:$F,">="&$G8,Orders!$F:$F,"<"&EDATE($G8,1),Orders!$G:$G,"CPT") -> 13300 | I8: =SUMIFS(Orders!$L:$L,Orders!$F:$F,">="&$G8,Orders!$F:$F,"<"&EDATE($G8,1),Orders!$G:$G,"JHB") -> 0 | J8: =H8+I8 -> 13300 | L8: OUT - ON ORDER | M8: =COUNTIF('Master Stock'!$V$5:$V$206,L8) -> 5
A9: Sold since count | E9: =SUM('Master Stock'!$I$5:$I$206) -> 5419.84 | G9: Later | J9: =SUM('Master Stock'!$M$5:$M$206) -> 0 | L9: LOW - ON ORDER | M9: =COUNTIF('Master Stock'!$V$5:$V$206,L9) -> 35
G10: Total | J10: =SUM('Master Stock'!$N$5:$N$206) -> 46380 | L10: OK | M10: =COUNTIF('Master Stock'!$V$5:$V$206,L10) -> 93
A11: Weekly sales not on stock sheet (m²) | E11: =SUMIFS('Weekly Sales'!$F:$F,'Weekly Sales'!$J:$J,"Not on stock sheet") -> 186.6 | G11: Value excl VAT | J11: =SUM(Orders!M5:M133) -> 12751784 | L11: SLOW MOVER | M11: =COUNTIF('Master Stock'!$V$5:$V$206,L11) -> 12
L12: NO BUFFER SET | M12: =COUNTIF('Master Stock'!$V$5:$V$206,L12) -> 10
L13: END OF RANGE | M13: =COUNTIF('Master Stock'!$V$5:$V$206,L13) -> 43
A16: REORDER LIST – biggest shortfall against buffer first (after counting stock on order)
A17: # | B17: Code | C17: Article | D17: Type | E17: Available m² | F17: On order m² | G17: Buffer m² | H17: Avg selling m²/month | I17: Short of buffer m² | J17: Months of cover | K17: Status
A18: 1 | B18: =IF($M18="","",INDEX('Master Stock'!$A$5:$A$206,$M18)) -> CAS004 | C18: =IF($M18="","",INDEX('Master Stock'!$B$5:$B$206,$M18)) -> CASTROL GREY | D18: =IF($M18="","",INDEX('Master Stock'!$C$5:$C$206,$M18)) -> Hide | E18: =IF($M18="","",INDEX('Master Stock'!$H$5:$H$206,$M18)) -> 156 | F18: =IF($M18="","",INDEX('Master Stock'!$N$5:$N$206,$M18)) -> 0 | G18: =IF($M18="","",INDEX('Master Stock'!$T$5:$T$206,$M18)) -> 200 | H18: =IF($M18="","",INDEX('Master Stock'!$Q$5:$Q$206,$M18)) -> 10 | I18: =IF($M18="","",INDEX('Master Stock'!$U$5:$U$206,$M18)) -> 44 | J18: =IF($M18="","",INDEX('Master Stock'!$S$5:$S$206,$M18)) -> 15.6 | K18: =IF($M18="","",INDEX('Master Stock'!$V$5:$V$206,$M18)) -> REORDER | M18: =IF(LARGE('Master Stock'!$X$5:$X$206,A18)>0,MATCH(LARGE('Master Stock'!$X$5:$X$206,A18),'Master Stock'!$X$5:$X$206,0),"") -> 29
A19: 2 | B19: =IF($M19="","",INDEX('Master Stock'!$A$5:$A$206,$M19)) -> TEX031 | C19: =IF($M19="","",INDEX('Master Stock'!$B$5:$B$206,$M19)) -> TEXAS COBALT | D19: =IF($M19="","",INDEX('Master Stock'!$C$5:$C$206,$M19)) -> Side | E19: =IF($M19="","",INDEX('Master Stock'!$H$5:$H$206,$M19)) -> 184.58 | F19: =IF($M19="","",INDEX('Master Stock'!$N$5:$N$206,$M19)) -> 0 | G19: =IF($M19="","",INDEX('Master Stock'!$T$5:$T$206,$M19)) -> 200 | H19: =IF($M19="","",INDEX('Master Stock'!$Q$5:$Q$206,$M19)) -> 35 | I19: =IF($M19="","",INDEX('Master Stock'!$U$5:$U$206,$M19)) -> 15.42 | J19: =IF($M19="","",INDEX('Master Stock'!$S$5:$S$206,$M19)) -> 5.2737143 | K19: =IF($M19="","",INDEX('Master Stock'!$V$5:$V$206,$M19)) -> REORDER | M19: =IF(LARGE('Master Stock'!$X$5:$X$206,A19)>0,MATCH(LARGE('Master Stock'!$X$5:$X$206,A19),'Master Stock'!$X$5:$X$206,0),"") -> 166
A20: 3 | B20: =IF($M20="","",INDEX('Master Stock'!$A$5:$A$206,$M20)) -> TEX029 | C20: =IF($M20="","",INDEX('Master Stock'!$B$5:$B$206,$M20)) -> TEXAS VIOLET | D20: =IF($M20="","",INDEX('Master Stock'!$C$5:$C$206,$M20)) -> Side | E20: =IF($M20="","",INDEX('Master Stock'!$H$5:$H$206,$M20)) -> 189.58 | F20: =IF($M20="","",INDEX('Master Stock'!$N$5:$N$206,$M20)) -> 0 | G20: =IF($M20="","",INDEX('Master Stock'!$T$5:$T$206,$M20)) -> 200 | H20: =IF($M20="","",INDEX('Master Stock'!$Q$5:$Q$206,$M20)) -> 30 | I20: =IF($M20="","",INDEX('Master Stock'!$U$5:$U$206,$M20)) -> 10.42 | J20: =IF($M20="","",INDEX('Master Stock'!$S$5:$S$206,$M20)) -> 6.3193333 | K20: =IF($M20="","",INDEX('Master Stock'!$V$5:$V$206,$M20)) -> REORDER | M20: =IF(LARGE('Master Stock'!$X$5:$X$206,A20)>0,MATCH(LARGE('Master Stock'!$X$5:$X$206,A20),'Master Stock'!$X$5:$X$206,0),"") -> 174
A21: 4 | B21: =IF($M21="","",INDEX('Master Stock'!$A$5:$A$206,$M21)) -> SOR002 | C21: =IF($M21="","",INDEX('Master Stock'!$B$5:$B$206,$M21)) -> SORRENTO GREY | D21: =IF($M21="","",INDEX('Master Stock'!$C$5:$C$206,$M21)) -> Hide | E21: =IF($M21="","",INDEX('Master Stock'!$H$5:$H$206,$M21)) -> 97.01 | F21: =IF($M21="","",INDEX('Master Stock'!$N$5:$N$206,$M21)) -> 0 | G21: =IF($M21="","",INDEX('Master Stock'!$T$5:$T$206,$M21)) -> 100 | H21: =IF($M21="","",INDEX('Master Stock'!$Q$5:$Q$206,$M21)) -> 0 | I21: =IF($M21="","",INDEX('Master Stock'!$U$5:$U$206,$M21)) -> 2.99 | J21: =IF($M21="","",INDEX('Master Stock'!$S$5:$S$206,$M21)) | K21: =IF($M21="","",INDEX('Master Stock'!$V$5:$V$206,$M21)) -> REORDER | M21: =IF(LARGE('Master Stock'!$X$5:$X$206,A21)>0,MATCH(LARGE('Master Stock'!$X$5:$X$206,A21),'Master Stock'!$X$5:$X$206,0),"") -> 107
A22: 5 | B22: =IF($M22="","",INDEX('Master Stock'!$A$5:$A$206,$M22)) | C22: =IF($M22="","",INDEX('Master Stock'!$B$5:$B$206,$M22)) | D22: =IF($M22="","",INDEX('Master Stock'!$C$5:$C$206,$M22)) | E22: =IF($M22="","",INDEX('Master Stock'!$H$5:$H$206,$M22)) | F22: =IF($M22="","",INDEX('Master Stock'!$N$5:$N$206,$M22)) | G22: =IF($M22="","",INDEX('Master Stock'!$T$5:$T$206,$M22)) | H22: =IF($M22="","",INDEX('Master Stock'!$Q$5:$Q$206,$M22)) | I22: =IF($M22="","",INDEX('Master Stock'!$U$5:$U$206,$M22)) | J22: =IF($M22="","",INDEX('Master Stock'!$S$5:$S$206,$M22)) | K22: =IF($M22="","",INDEX('Master Stock'!$V$5:$V$206,$M22)) | M22: =IF(LARGE('Master Stock'!$X$5:$X$206,A22)>0,MATCH(LARGE('Master Stock'!$X$5:$X$206,A22),'Master Stock'!$X$5:$X$206,0),"")
A23: 6 | B23: =IF($M23="","",INDEX('Master Stock'!$A$5:$A$206,$M23)) | C23: =IF($M23="","",INDEX('Master Stock'!$B$5:$B$206,$M23)) | D23: =IF($M23="","",INDEX('Master Stock'!$C$5:$C$206,$M23)) | E23: =IF($M23="","",INDEX('Master Stock'!$H$5:$H$206,$M23)) | F23: =IF($M23="","",INDEX('Master Stock'!$N$5:$N$206,$M23)) | G23: =IF($M23="","",INDEX('Master Stock'!$T$5:$T$206,$M23)) | H23: =IF($M23="","",INDEX('Master Stock'!$Q$5:$Q$206,$M23)) | I23: =IF($M23="","",INDEX('Master Stock'!$U$5:$U$206,$M23)) | J23: =IF($M23="","",INDEX('Master Stock'!$S$5:$S$206,$M23)) | K23: =IF($M23="","",INDEX('Master Stock'!$V$5:$V$206,$M23)) | M23: =IF(LARGE('Master Stock'!$X$5:$X$206,A23)>0,MATCH(LARGE('Master Stock'!$X$5:$X$206,A23),'Master Stock'!$X$5:$X$206,0),"")
A24: 7 | B24: =IF($M24="","",INDEX('Master Stock'!$A$5:$A$206,$M24)) | C24: =IF($M24="","",INDEX('Master Stock'!$B$5:$B$206,$M24)) | D24: =IF($M24="","",INDEX('Master Stock'!$C$5:$C$206,$M24)) | E24: =IF($M24="","",INDEX('Master Stock'!$H$5:$H$206,$M24)) | F24: =IF($M24="","",INDEX('Master Stock'!$N$5:$N$206,$M24)) | G24: =IF($M24="","",INDEX('Master Stock'!$T$5:$T$206,$M24)) | H24: =IF($M24="","",INDEX('Master Stock'!$Q$5:$Q$206,$M24)) | I24: =IF($M24="","",INDEX('Master Stock'!$U$5:$U$206,$M24)) | J24: =IF($M24="","",INDEX('Master Stock'!$S$5:$S$206,$M24)) | K24: =IF($M24="","",INDEX('Master Stock'!$V$5:$V$206,$M24)) | M24: =IF(LARGE('Master Stock'!$X$5:$X$206,A24)>0,MATCH(LARGE('Master Stock'!$X$5:$X$206,A24),'Master Stock'!$X$5:$X$206,0),"")
A25: 8 | B25: =IF($M25="","",INDEX('Master Stock'!$A$5:$A$206,$M25)) | C25: =IF($M25="","",INDEX('Master Stock'!$B$5:$B$206,$M25)) | D25: =IF($M25="","",INDEX('Master Stock'!$C$5:$C$206,$M25)) | E25: =IF($M25="","",INDEX('Master Stock'!$H$5:$H$206,$M25)) | F25: =IF($M25="","",INDEX('Master Stock'!$N$5:$N$206,$M25)) | G25: =IF($M25="","",INDEX('Master Stock'!$T$5:$T$206,$M25)) | H25: =IF($M25="","",INDEX('Master Stock'!$Q$5:$Q$206,$M25)) | I25: =IF($M25="","",INDEX('Master Stock'!$U$5:$U$206,$M25)) | J25: =IF($M25="","",INDEX('Master Stock'!$S$5:$S$206,$M25)) | K25: =IF($M25="","",INDEX('Master Stock'!$V$5:$V$206,$M25)) | M25: =IF(LARGE('Master Stock'!$X$5:$X$206,A25)>0,MATCH(LARGE('Master Stock'!$X$5:$X$206,A25),'Master Stock'!$X$5:$X$206,0),"")
A26: 9 | B26: =IF($M26="","",INDEX('Master Stock'!$A$5:$A$206,$M26)) | C26: =IF($M26="","",INDEX('Master Stock'!$B$5:$B$206,$M26)) | D26: =IF($M26="","",INDEX('Master Stock'!$C$5:$C$206,$M26)) | E26: =IF($M26="","",INDEX('Master Stock'!$H$5:$H$206,$M26)) | F26: =IF($M26="","",INDEX('Master Stock'!$N$5:$N$206,$M26)) | G26: =IF($M26="","",INDEX('Master Stock'!$T$5:$T$206,$M26)) | H26: =IF($M26="","",INDEX('Master Stock'!$Q$5:$Q$206,$M26)) | I26: =IF($M26="","",INDEX('Master Stock'!$U$5:$U$206,$M26)) | J26: =IF($M26="","",INDEX('Master Stock'!$S$5:$S$206,$M26)) | K26: =IF($M26="","",INDEX('Master Stock'!$V$5:$V$206,$M26)) | M26: =IF(LARGE('Master Stock'!$X$5:$X$206,A26)>0,MATCH(LARGE('Master Stock'!$X$5:$X$206,A26),'Master Stock'!$X$5:$X$206,0),"")
A27: 10 | B27: =IF($M27="","",INDEX('Master Stock'!$A$5:$A$206,$M27)) | C27: =IF($M27="","",INDEX('Master Stock'!$B$5:$B$206,$M27)) | D27: =IF($M27="","",INDEX('Master Stock'!$C$5:$C$206,$M27)) | E27: =IF($M27="","",INDEX('Master Stock'!$H$5:$H$206,$M27)) | F27: =IF($M27="","",INDEX('Master Stock'!$N$5:$N$206,$M27)) | G27: =IF($M27="","",INDEX('Master Stock'!$T$5:$T$206,$M27)) | H27: =IF($M27="","",INDEX('Master Stock'!$Q$5:$Q$206,$M27)) | I27: =IF($M27="","",INDEX('Master Stock'!$U$5:$U$206,$M27)) | J27: =IF($M27="","",INDEX('Master Stock'!$S$5:$S$206,$M27)) | K27: =IF($M27="","",INDEX('Master Stock'!$V$5:$V$206,$M27)) | M27: =IF(LARGE('Master Stock'!$X$5:$X$206,A27)>0,MATCH(LARGE('Master Stock'!$X$5:$X$206,A27),'Master Stock'!$X$5:$X$206,0),"")
A28: 11 | B28: =IF($M28="","",INDEX('Master Stock'!$A$5:$A$206,$M28)) | C28: =IF($M28="","",INDEX('Master Stock'!$B$5:$B$206,$M28)) | D28: =IF($M28="","",INDEX('Master Stock'!$C$5:$C$206,$M28)) | E28: =IF($M28="","",INDEX('Master Stock'!$H$5:$H$206,$M28)) | F28: =IF($M28="","",INDEX('Master Stock'!$N$5:$N$206,$M28)) | G28: =IF($M28="","",INDEX('Master Stock'!$T$5:$T$206,$M28)) | H28: =IF($M28="","",INDEX('Master Stock'!$Q$5:$Q$206,$M28)) | I28: =IF($M28="","",INDEX('Master Stock'!$U$5:$U$206,$M28)) | J28: =IF($M28="","",INDEX('Master Stock'!$S$5:$S$206,$M28)) | K28: =IF($M28="","",INDEX('Master Stock'!$V$5:$V$206,$M28)) | M28: =IF(LARGE('Master Stock'!$X$5:$X$206,A28)>0,MATCH(LARGE('Master Stock'!$X$5:$X$206,A28),'Master Stock'!$X$5:$X$206,0),"")
A29: 12 | B29: =IF($M29="","",INDEX('Master Stock'!$A$5:$A$206,$M29)) | C29: =IF($M29="","",INDEX('Master Stock'!$B$5:$B$206,$M29)) | D29: =IF($M29="","",INDEX('Master Stock'!$C$5:$C$206,$M29)) | E29: =IF($M29="","",INDEX('Master Stock'!$H$5:$H$206,$M29)) | F29: =IF($M29="","",INDEX('Master Stock'!$N$5:$N$206,$M29)) | G29: =IF($M29="","",INDEX('Master Stock'!$T$5:$T$206,$M29)) | H29: =IF($M29="","",INDEX('Master Stock'!$Q$5:$Q$206,$M29)) | I29: =IF($M29="","",INDEX('Master Stock'!$U$5:$U$206,$M29)) | J29: =IF($M29="","",INDEX('Master Stock'!$S$5:$S$206,$M29)) | K29: =IF($M29="","",INDEX('Master Stock'!$V$5:$V$206,$M29)) | M29: =IF(LARGE('Master Stock'!$X$5:$X$206,A29)>0,MATCH(LARGE('Master Stock'!$X$5:$X$206,A29),'Master Stock'!$X$5:$X$206,0),"")
... A57: 40 | B57: =IF($M57="","",INDEX('Master Stock'!$A$5:$A$206,$M57)) | C57: =IF($M57="","",INDEX('Master Stock'!$B$5:$B$206,$M57)) | D57: =IF($M57="","",INDEX('Master Stock'!$C$5:$C$206,$M57)) | E57: =IF($M57="","",INDEX('Master Stock'!$H$5:$H$206,$M57)) | F57: =IF($M57="","",INDEX('Master Stock'!$N$5:$N$206,$M57)) | G57: =IF($M57="","",INDEX('Master Stock'!$T$5:$T$206,$M57)) | H57: =IF($M57="","",INDEX('Master Stock'!$Q$5:$Q$206,$M57)) | I57: =IF($M57="","",INDEX('Master Stock'!$U$5:$U$206,$M57)) | J57: =IF($M57="","",INDEX('Master Stock'!$S$5:$S$206,$M57)) | K57: =IF($M57="","",INDEX('Master Stock'!$V$5:$V$206,$M57)) | M57: =IF(LARGE('Master Stock'!$X$5:$X$206,A57)>0,MATCH(LARGE('Master Stock'!$X$5:$X$206,A57),'Master Stock'!$X$5:$X$206,0),"")

Sheet Master Stock
A1: AGS Universal Stock Sheet – all branches (leather hides & sides)
A2: ="Stock as at "&TEXT(Settings!$B$13,"d mmmm yyyy")&" · CPT count 8 Oct, JHB & DBN count 30 Sep, plus stock received, less weekly sales, ± transfers. Blue = input, black = formula." -> Stock as at 9 October 2026 · CPT count 8 Oct, JHB & DBN count 30 Sep, plus stock received, less weekly sales, ± transfers. Blue = input, black = formula.
A4: Code | B4: Article | C4: Type | D4: Range | E4: CPT m² | F4: JHB m² | G4: DBN m² | H4: TOTAL AVAILABLE m² | I4: Sold since count m² | J4: 46296 | K4: 46327 | L4: 46357 | M4: On order later | N4: Total on order m² | O4: Available + on order | P4: Avg/month (current sheet) | Q4: Avg selling m²/month | R4: Avg source | S4: Months of cover | T4: Buffer m² | U4: Short of buffer m² | V4: STATUS | W4: Notes | X4: rank (helper)
A5: GAZ001 | B5: GAZELLE OXBLOOD | C5: Hide | D5: Active | E5: =SUMIFS('CPT Count'!$D:$D,'CPT Count'!$A:$A,$A5)-SUMIFS('Weekly Sales'!$F:$F,'Weekly Sales'!$H:$H,$A5,'Weekly Sales'!$I:$I,"CPT")+SUMIFS(Transfers!$F:$F,Transfers!$C:$C,$A5,Transfers!$J:$J,"CPT")-SUMIFS(Transfers!$F:$F,Transfers!$C:$C,$A5,Transfers!$I:$I,"CPT",Transfers!$H:$H,"<>Y")+SUMIFS('Stock Received'!$I:$I,'Stock Received'!$E:$E,$A5,'Stock Received'!$L:$L,"CPT") -> 722.41 | F5: =SUMIFS('JHB Count'!$E:$E,'JHB Count'!$F:$F,$A5)-SUMIFS('Weekly Sales'!$F:$F,'Weekly Sales'!$H:$H,$A5,'Weekly Sales'!$I:$I,"JHB")+SUMIFS(Transfers!$F:$F,Transfers!$C:$C,$A5,Transfers!$J:$J,"JHB")-SUMIFS(Transfers!$F:$F,Transfers!$C:$C,$A5,Transfers!$I:$I,"JHB",Transfers!$H:$H,"<>Y")+SUMIFS('Stock Received'!$I:$I,'Stock Received'!$E:$E,$A5,'Stock Received'!$L:$L,"JHB") -> 44 | G5: =SUMIFS('DBN Count'!$D:$D,'DBN Count'!$E:$E,$A5)-SUMIFS('Weekly Sales'!$F:$F,'Weekly Sales'!$H:$H,$A5,'Weekly Sales'!$I:$I,"DBN")+SUMIFS(Transfers!$F:$F,Transfers!$C:$C,$A5,Transfers!$J:$J,"DBN")-SUMIFS(Transfers!$F:$F,Transfers!$C:$C,$A5,Transfers!$I:$I,"DBN",Transfers!$H:$H,"<>Y")+SUMIFS('Stock Received'!$I:$I,'Stock Received'!$E:$E,$A5,'Stock Received'!$L:$L,"DBN") -> 20.15 | H5: =E5+F5+G5 -> 786.56 | I5: =SUMIFS('Weekly Sales'!$F:$F,'Weekly Sales'!$H:$H,$A5) -> 8.16 | J5: =SUMIFS(Orders!$L:$L,Orders!$D:$D,$A5,Orders!$F:$F,">="&J$4,Orders!$F:$F,"<"&EDATE(J$4,1)) -> 0 | K5: =SUMIFS(Orders!$L:$L,Orders!$D:$D,$A5,Orders!$F:$F,">="&K$4,Orders!$F:$F,"<"&EDATE(K$4,1)) -> 0 | L5: =SUMIFS(Orders!$L:$L,Orders!$D:$D,$A5,Orders!$F:$F,">="&L$4,Orders!$F:$F,"<"&EDATE(L$4,1)) -> 0 | M5: =N5-J5-K5-L5 -> 0 | N5: =SUMIFS(Orders!$L:$L,Orders!$D:$D,$A5) -> 0 | O5: =H5+N5 -> 786.56 | P5: 100 | Q5: =IF(SUMIFS('Sales History'!$E:$E,'Sales History'!$G:$G,$A5)>0,SUMIFS('Sales History'!$E:$E,'Sales History'!$G:$G,$A5)/Settings!$B$4,N(P5)) -> 100 | R5: =IF(SUMIFS('Sales History'!$E:$E,'Sales History'!$G:$G,$A5)>0,"6-month history",IF(N(P5)>0,"Current sheet","No sales data")) -> Current sheet | S5: =IF(Q5>0,H5/Q5,"") -> 7.8656 | T5: 300 | U5: =IF(T5="","",MAX(0,T5-O5)) -> 0 | V5: =IF(D5="End of range","END OF RANGE",IF(T5="","NO BUFFER SET",IF(H5<=0,IF(O5<T5,"OUT - REORDER","OUT - ON ORDER"),IF(O5<T5,"REORDER",IF(H5<T5,"LOW - ON ORDER",IF(AND(S5<>"",N(S5)>Settings!$B$5),"SLOW MOVER","OK")))))) -> OK | X5: =IF(OR(D5="End of range",U5=""),0,IF(N(U5)>0,U5+ROW()/1000000,0)) -> 0
A6: GAZ010 | B6: GAZELLE MOCCA | C6: Hide | D6: Active | E6: =SUMIFS('CPT Count'!$D:$D,'CPT Count'!$A:$A,$A6)-SUMIFS('Weekly Sales'!$F:$F,'Weekly Sales'!$H:$H,$A6,'Weekly Sales'!$I:$I,"CPT")+SUMIFS(Transfers!$F:$F,Transfers!$C:$C,$A6,Transfers!$J:$J,"CPT")-SUMIFS(Transfers!$F:$F,Transfers!$C:$C,$A6,Transfers!$I:$I,"CPT",Transfers!$H:$H,"<>Y")+SUMIFS('Stock Received'!$I:$I,'Stock Received'!$E:$E,$A6,'Stock Received'!$L:$L,"CPT") -> 558.18 | F6: =SUMIFS('JHB Count'!$E:$E,'JHB Count'!$F:$F,$A6)-SUMIFS('Weekly Sales'!$F:$F,'Weekly Sales'!$H:$H,$A6,'Weekly Sales'!$I:$I,"JHB")+SUMIFS(Transfers!$F:$F,Transfers!$C:$C,$A6,Transfers!$J:$J,"JHB")-SUMIFS(Transfers!$F:$F,Transfers!$C:$C,$A6,Transfers!$I:$I,"JHB",Transfers!$H:$H,"<>Y")+SUMIFS('Stock Received'!$I:$I,'Stock Received'!$E:$E,$A6,'Stock Received'!$L:$L,"JHB") -> 64 | G6: =SUMIFS('DBN Count'!$D:$D,'DBN Count'!$E:$E,$A6)-SUMIFS('Weekly Sales'!$F:$F,'Weekly Sales'!$H:$H,$A6,'Weekly Sales'!$I:$I,"DBN")+SUMIFS(Transfers!$F:$F,Transfers!$C:$C,$A6,Transfers!$J:$J,"DBN")-SUMIFS(Transfers!$F:$F,Transfers!$C:$C,$A6,Transfers!$I:$I,"DBN",Transfers!$H:$H,"<>Y")+SUMIFS('Stock Received'!$I:$I,'Stock Received'!$E:$E,$A6,'Stock Received'!$L:$L,"DBN") -> 24.59 | H6: =E6+F6+G6 -> 646.77 | I6: =SUMIFS('Weekly Sales'!$F:$F,'Weekly Sales'!$H:$H,$A6) -> 48.01 | J6: =SUMIFS(Orders!$L:$L,Orders!$D:$D,$A6,Orders!$F:$F,">="&J$4,Orders!$F:$F,"<"&EDATE(J$4,1)) -> 0 | K6: =SUMIFS(Orders!$L:$L,Orders!$D:$D,$A6,Orders!$F:$F,">="&K$4,Orders!$F:$F,"<"&EDATE(K$4,1)) -> 0 | L6: =SUMIFS(Orders!$L:$L,Orders!$D:$D,$A6,Orders!$F:$F,">="&L$4,Orders!$F:$F,"<"&EDATE(L$4,1)) -> 0 | M6: =N6-J6-K6-L6 -> 0 | N6: =SUMIFS(Orders!$L:$L,Orders!$D:$D,$A6) -> 0 | O6: =H6+N6 -> 646.77 | P6: 110 | Q6: =IF(SUMIFS('Sales History'!$E:$E,'Sales History'!$G:$G,$A6)>0,SUMIFS('Sales History'!$E:$E,'Sales History'!$G:$G,$A6)/Settings!$B$4,N(P6)) -> 110 | R6: =IF(SUMIFS('Sales History'!$E:$E,'Sales History'!$G:$G,$A6)>0,"6-month history",IF(N(P6)>0,"Current sheet","No sales data")) -> Current sheet | S6: =IF(Q6>0,H6/Q6,"") -> 5.8797273 | T6: 300 | U6: =IF(T6="","",MAX(0,T6-O6)) -> 0 | V6: =IF(D6="End of range","END OF RANGE",IF(T6="","NO BUFFER SET",IF(H6<=0,IF(O6<T6,"OUT - REORDER","OUT - ON ORDER"),IF(O6<T6,"REORDER",IF(H6<T6,"LOW - ON ORDER",IF(AND(S6<>"",N(S6)>Settings!$B$5),"SLOW MOVER","OK")))))) -> OK | X6: =IF(OR(D6="End of range",U6=""),0,IF(N(U6)>0,U6+ROW()/1000000,0)) -> 0
A7: GAZ006 | B7: GAZELLE BLACK | C7: Hide | D7: Active | E7: =SUMIFS('CPT Count'!$D:$D,'CPT Count'!$A:$A,$A7)-SUMIFS('Weekly Sales'!$F:$F,'Weekly Sales'!$H:$H,$A7,'Weekly Sales'!$I:$I,"CPT")+SUMIFS(Transfers!$F:$F,Transfers!$C:$C,$A7,Transfers!$J:$J,"CPT")-SUMIFS(Transfers!$F:$F,Transfers!$C:$C,$A7,Transfers!$I:$I,"CPT",Transfers!$H:$H,"<>Y")+SUMIFS('Stock Received'!$I:$I,'Stock Received'!$E:$E,$A7,'Stock Received'!$L:$L,"CPT") -> 1174.19 | F7: =SUMIFS('JHB Count'!$E:$E,'JHB Count'!$F:$F,$A7)-SUMIFS('Weekly Sales'!$F:$F,'Weekly Sales'!$H:$H,$A7,'Weekly Sales'!$I:$I,"JHB")+SUMIFS(Transfers!$F:$F,Transfers!$C:$C,$A7,Transfers!$J:$J,"JHB")-SUMIFS(Transfers!$F:$F,Transfers!$C:$C,$A7,Transfers!$I:$I,"JHB",Transfers!$H:$H,"<>Y")+SUMIFS('Stock Received'!$I:$I,'Stock Received'!$E:$E,$A7,'Stock Received'!$L:$L,"JHB") -> 107.05 | G7: =SUMIFS('DBN Count'!$D:$D,'DBN Count'!$E:$E,$A7)-SUMIFS('Weekly Sales'!$F:$F,'Weekly Sales'!$H:$H,$A7,'Weekly Sales'!$I:$I,"DBN")+SUMIFS(Transfers!$F:$F,Transfers!$C:$C,$A7,Transfers!$J:$J,"DBN")-SUMIFS(Transfers!$F:$F,Transfers!$C:$C,$A7,Transfers!$I:$I,"DBN",Transfers!$H:$H,"<>Y")+SUMIFS('Stock Received'!$I:$I,'Stock Received'!$E:$E,$A7,'Stock Received'!$L:$L,"DBN") -> 137.85 | H7: =E7+F7+G7 -> 1419.09 | I7: =SUMIFS('Weekly Sales'!$F:$F,'Weekly Sales'!$H:$H,$A7) -> 33.43 | J7: =SUMIFS(Orders!$L:$L,Orders!$D:$D,$A7,Orders!$F:$F,">="&J$4,Orders!$F:$F,"<"&EDATE(J$4,1)) -> 0 | K7: =SUMIFS(Orders!$L:$L,Orders!$D:$D,$A7,Orders!$F:$F,">="&K$4,Orders!$F:$F,"<"&EDATE(K$4,1)) -> 0 | L7: =SUMIFS(Orders!$L:$L,Orders!$D:$D,$A7,Orders!$F:$F,">="&L$4,Orders!$F:$F,"<"&EDATE(L$4,1)) -> 500 | M7: =N7-J7-K7-L7 -> 0 | N7: =SUMIFS(Orders!$L:$L,Orders!$D:$D,$A7) -> 500 | O7: =H7+N7 -> 1919.09 | P7: 375 | Q7: =IF(SUMIFS('Sales History'!$E:$E,'Sales History'!$G:$G,$A7)>0,SUMIFS('Sales History'!$E:$E,'Sales History'!$G:$G,$A7)/Settings!$B$4,N(P7)) -> 375 | R7: =IF(SUMIFS('Sales History'!$E:$E,'Sales History'!$G:$G,$A7)>0,"6-month history",IF(N(P7)>0,"Current sheet","No sales data")) -> Current sheet | S7: =IF(Q7>0,H7/Q7,"") -> 3.78424 | T7: 500 | U7: =IF(T7="","",MAX(0,T7-O7)) -> 0 | V7: =IF(D7="End of range","END OF RANGE",IF(T7="","NO BUFFER SET",IF(H7<=0,IF(O7<T7,"OUT - REORDER","OUT - ON ORDER"),IF(O7<T7,"REORDER",IF(H7<T7,"LOW - ON ORDER",IF(AND(S7<>"",N(S7)>Settings!$B$5),"SLOW MOVER","OK")))))) -> OK | X7: =IF(OR(D7="End of range",U7=""),0,IF(N(U7)>0,U7+ROW()/1000000,0)) -> 0
A8: GAZ007 | B8: GAZELLE RED | C8: Hide | D8: Active | E8: =SUMIFS('CPT Count'!$D:$D,'CPT Count'!$A:$A,$A8)-SUMIFS('Weekly Sales'!$F:$F,'Weekly Sales'!$H:$H,$A8,'Weekly Sales'!$I:$I,"CPT")+SUMIFS(Transfers!$F:$F,Transfers!$C:$C,$A8,Transfers!$J:$J,"CPT")-SUMIFS(Transfers!$F:$F,Transfers!$C:$C,$A8,Transfers!$I:$I,"CPT",Transfers!$H:$H,"<>Y")+SUMIFS('Stock Received'!$I:$I,'Stock Received'!$E:$E,$A8,'Stock Received'!$L:$L,"CPT") -> 351 | F8: =SUMIFS('JHB Count'!$E:$E,'JHB Count'!$F:$F,$A8)-SUMIFS('Weekly Sales'!$F:$F,'Weekly Sales'!$H:$H,$A8,'Weekly Sales'!$I:$I,"JHB")+SUMIFS(Transfers!$F:$F,Transfers!$C:$C,$A8,Transfers!$J:$J,"JHB")-SUMIFS(Transfers!$F:$F,Transfers!$C:$C,$A8,Transfers!$I:$I,"JHB",Transfers!$H:$H,"<>Y")+SUMIFS('Stock Received'!$I:$I,'Stock Received'!$E:$E,$A8,'Stock Received'!$L:$L,"JHB") -> 60 | G8: =SUMIFS('DBN Count'!$D:$D,'DBN Count'!$E:$E,$A8)-SUMIFS('Weekly Sales'!$F:$F,'Weekly Sales'!$H:$H,$A8,'Weekly Sales'!$I:$I,"DBN")+SUMIFS(Transfers!$F:$F,Transfers!$C:$C,$A8,Transfers!$J:$J,"DBN")-SUMIFS(Transfers!$F:$F,Transfers!$C:$C,$A8,Transfers!$I:$I,"DBN",Transfers!$H:$H,"<>Y")+SUMIFS('Stock Received'!$I:$I,'Stock Received'!$E:$E,$A8,'Stock Received'!$L:$L,"DBN") -> 21.47 | H8: =E8+F8+G8 -> 432.47 | I8: =SUMIFS('Weekly Sales'!$F:$F,'Weekly Sales'!$H:$H,$A8) -> 0 | J8: =SUMIFS(Orders!$L:$L,Orders!$D:$D,$A8,Orders!$F:$F,">="&J$4,Orders!$F:$F,"<"&EDATE(J$4,1)) -> 0 | K8: =SUMIFS(Orders!$L:$L,Orders!$D:$D,$A8,Orders!$F:$F,">="&K$4,Orders!$F:$F,"<"&EDATE(K$4,1)) -> 0 | L8: =SUMIFS(Orders!$L:$L,Orders!$D:$D,$A8,Orders!$F:$F,">="&L$4,Orders!$F:$F,"<"&EDATE(L$4,1)) -> 0 | M8: =N8-J8-K8-L8 -> 0 | N8: =SUMIFS(Orders!$L:$L,Orders!$D:$D,$A8) -> 0 | O8: =H8+N8 -> 432.47 | P8: 50 | Q8: =IF(SUMIFS('Sales History'!$E:$E,'Sales History'!$G:$G,$A8)>0,SUMIFS('Sales History'!$E:$E,'Sales History'!$G:$G,$A8)/Settings!$B$4,N(P8)) -> 50 | R8: =IF(SUMIFS('Sales History'!$E:$E,'Sales History'!$G:$G,$A8)>0,"6-month history",IF(N(P8)>0,"Current sheet","No sales data")) -> Current sheet | S8: =IF(Q8>0,H8/Q8,"") -> 8.6494 | T8: 300 | U8: =IF(T8="","",MAX(0,T8-O8)) -> 0 | V8: =IF(D8="End of range","END OF RANGE",IF(T8="","NO BUFFER SET",IF(H8<=0,IF(O8<T8,"OUT - REORDER","OUT - ON ORDER"),IF(O8<T8,"REORDER",IF(H8<T8,"LOW - ON ORDER",IF(AND(S8<>"",N(S8)>Settings!$B$5),"SLOW MOVER","OK")))))) -> OK | X8: =IF(OR(D8="End of range",U8=""),0,IF(N(U8)>0,U8+ROW()/1000000,0)) -> 0
A9: GAZ005 | B9: GAZELLE NAVY | C9: Hide | D9: Active | E9: =SUMIFS('CPT Count'!$D:$D,'CPT Count'!$A:$A,$A9)-SUMIFS('Weekly Sales'!$F:$F,'Weekly Sales'!$H:$H,$A9,'Weekly Sales'!$I:$I,"CPT")+SUMIFS(Transfers!$F:$F,Transfers!$C:$C,$A9,Transfers!$J:$J,"CPT")-SUMIFS(Transfers!$F:$F,Transfers!$C:$C,$A9,Transfers!$I:$I,"CPT",Transfers!$H:$H,"<>Y")+SUMIFS('Stock Received'!$I:$I,'Stock Received'!$E:$E,$A9,'Stock Received'!$L:$L,"CPT") -> 595.35 | F9: =SUMIFS('JHB Count'!$E:$E,'JHB Count'!$F:$F,$A9)-SUMIFS('Weekly Sales'!$F:$F,'Weekly Sales'!$H:$H,$A9,'Weekly Sales'!$I:$I,"JHB")+SUMIFS(Transfers!$F:$F,Transfers!$C:$C,$A9,Transfers!$J:$J,"JHB")-SUMIFS(Transfers!$F:$F,Transfers!$C:$C,$A9,Transfers!$I:$I,"JHB",Transfers!$H:$H,"<>Y")+SUMIFS('Stock Received'!$I:$I,'Stock Received'!$E:$E,$A9,'Stock Received'!$L:$L,"JHB") -> 36 | G9: =SUMIFS('DBN Count'!$D:$D,'DBN Count'!$E:$E,$A9)-SUMIFS('Weekly Sales'!$F:$F,'Weekly Sales'!$H:$H,$A9,'Weekly Sales'!$I:$I,"DBN")+SUMIFS(Transfers!$F:$F,Transfers!$C:$C,$A9,Transfers!$J:$J,"DBN")-SUMIFS(Transfers!$F:$F,Transfers!$C:$C,$A9,Transfers!$I:$I,"DBN",Transfers!$H:$H,"<>Y")+SUMIFS('Stock Received'!$I:$I,'Stock Received'!$E:$E,$A9,'Stock Received'!$L:$L,"DBN") -> 23.29 | H9: =E9+F9+G9 -> 654.64 | I9: =SUMIFS('Weekly Sales'!$F:$F,'Weekly Sales'!$H:$H,$A9) -> 3.65 | J9: =SUMIFS(Orders!$L:$L,Orders!$D:$D,$A9,Orders!$F:$F,">="&J$4,Orders!$F:$F,"<"&EDATE(J$4,1)) -> 0 | K9: =SUMIFS(Orders!$L:$L,Orders!$D:$D,$A9,Orders!$F:$F,">="&K$4,Orders!$F:$F,"<"&EDATE(K$4,1)) -> 0 | L9: =SUMIFS(Orders!$L:$L,Orders!$D:$D,$A9,Orders!$F:$F,">="&L$4,Orders!$F:$F,"<"&EDATE(L$4,1)) -> 0 | M9: =N9-J9-K9-L9 -> 0 | N9: =SUMIFS(Orders!$L:$L,Orders!$D:$D,$A9) -> 0 | O9: =H9+N9 -> 654.64 | P9: 110 | Q9: =IF(SUMIFS('Sales History'!$E:$E,'Sales History'!$G:$G,$A9)>0,SUMIFS('Sales History'!$E:$E,'Sales History'!$G:$G,$A9)/Settings!$B$4,N(P9)) -> 110 | R9: =IF(SUMIFS('Sales History'!$E:$E,'Sales History'!$G:$G,$A9)>0,"6-month history",IF(N(P9)>0,"Current sheet","No sales data")) -> Current sheet | S9: =IF(Q9>0,H9/Q9,"") -> 5.9512727 | T9: 300 | U9: =IF(T9="","",MAX(0,T9-O9)) -> 0 | V9: =IF(D9="End of range","END OF RANGE",IF(T9="","NO BUFFER SET",IF(H9<=0,IF(O9<T9,"OUT - REORDER","OUT - ON ORDER"),IF(O9<T9,"REORDER",IF(H9<T9,"LOW - ON ORDER",IF(AND(S9<>"",N(S9)>Settings!$B$5),"SLOW MOVER","OK")))))) -> OK | X9: =IF(OR(D9="End of range",U9=""),0,IF(N(U9)>0,U9+ROW()/1000000,0)) -> 0
A10: GAZ008 | B10: GAZELLE WHITE | C10: Hide | D10: Active | E10: =SUMIFS('CPT Count'!$D:$D,'CPT Count'!$A:$A,$A10)-SUMIFS('Weekly Sales'!$F:$F,'Weekly Sales'!$H:$H,$A10,'Weekly Sales'!$I:$I,"CPT")+SUMIFS(Transfers!$F:$F,Transfers!$C:$C,$A10,Transfers!$J:$J,"CPT")-SUMIFS(Transfers!$F:$F,Transfers!$C:$C,$A10,Transfers!$I:$I,"CPT",Transfers!$H:$H,"<>Y")+SUMIFS('Stock Received'!$I:$I,'Stock Received'!$E:$E,$A10,'Stock Received'!$L:$L,"CPT") -> 740 | F10: =SUMIFS('JHB Count'!$E:$E,'JHB Count'!$F:$F,$A10)-SUMIFS('Weekly Sales'!$F:$F,'Weekly Sales'!$H:$H,$A10,'Weekly Sales'!$I:$I,"JHB")+SUMIFS(Transfers!$F:$F,Transfers!$C:$C,$A10,Transfers!$J:$J,"JHB")-SUMIFS(Transfers!$F:$F,Transfers!$C:$C,$A10,Transfers!$I:$I,"JHB",Transfers!$H:$H,"<>Y")+SUMIFS('Stock Received'!$I:$I,'Stock Received'!$E:$E,$A10,'Stock Received'!$L:$L,"JHB") -> 56 | G10: =SUMIFS('DBN Count'!$D:$D,'DBN Count'!$E:$E,$A10)-SUMIFS('Weekly Sales'!$F:$F,'Weekly Sales'!$H:$H,$A10,'Weekly Sales'!$I:$I,"DBN")+SUMIFS(Transfers!$F:$F,Transfers!$C:$C,$A10,Transfers!$J:$J,"DBN")-SUMIFS(Transfers!$F:$F,Transfers!$C:$C,$A10,Transfers!$I:$I,"DBN",Transfers!$H:$H,"<>Y")+SUMIFS('Stock Received'!$I:$I,'Stock Received'!$E:$E,$A10,'Stock Received'!$L:$L,"DBN") -> 58.96 | H10: =E10+F10+G10 -> 854.96 | I10: =SUMIFS('Weekly Sales'!$F:$F,'Weekly Sales'!$H:$H,$A10) -> 0 | J10: =SUMIFS(Orders!$L:$L,Orders!$D:$D,$A10,Orders!$F:$F,">="&J$4,Orders!$F:$F,"<"&EDATE(J$4,1)) -> 0 | K10: =SUMIFS(Orders!$L:$L,Orders!$D:$D,$A10,Orders!$F:$F,">="&K$4,Orders!$F:$F,"<"&EDATE(K$4,1)) -> 0 | L10: =SUMIFS(Orders!$L:$L,Orders!$D:$D,$A10,Orders!$F:$F,">="&L$4,Orders!$F:$F,"<"&EDATE(L$4,1)) -> 0 | M10: =N10-J10-K10-L10 -> 0 | N10: =SUMIFS(Orders!$L:$L,Orders!$D:$D,$A10) -> 0 | O10: =H10+N10 -> 854.96 | P10: 100 | Q10: =IF(SUMIFS('Sales History'!$E:$E,'Sales History'!$G:$G,$A10)>0,SUMIFS('Sales History'!$E:$E,'Sales History'!$G:$G,$A10)/Settings!$B$4,N(P10)) -> 100 | R10: =IF(SUMIFS('Sales History'!$E:$E,'Sales History'!$G:$G,$A10)>0,"6-month history",IF(N(P10)>0,"Current sheet","No sales data")) -> Current sheet | S10: =IF(Q10>0,H10/Q10,"") -> 8.5496 | T10: 300 | U10: =IF(T10="","",MAX(0,T10-O10)) -> 0 | V10: =IF(D10="End of range","END OF RANGE",IF(T10="","NO BUFFER SET",IF(H10<=0,IF(O10<T10,"OUT - REORDER","OUT - ON ORDER"),IF(O10<T10,"REORDER",IF(H10<T10,"LOW - ON ORDER",IF(AND(S10<>"",N(S10)>Settings!$B$5),"SLOW MOVER","OK")))))) -> OK | X10: =IF(OR(D10="End of range",U10=""),0,IF(N(U10)>0,U10+ROW()/1000000,0)) -> 0
A11: GAZ015 | B11: GAZELLE OYSTER | C11: Hide | D11: Active | E11: =SUMIFS('CPT Count'!$D:$D,'CPT Count'!$A:$A,$A11)-SUMIFS('Weekly Sales'!$F:$F,'Weekly Sales'!$H:$H,$A11,'Weekly Sales'!$I:$I,"CPT")+SUMIFS(Transfers!$F:$F,Transfers!$C:$C,$A11,Transfers!$J:$J,"CPT")-SUMIFS(Transfers!$F:$F,Transfers!$C:$C,$A11,Transfers!$I:$I,"CPT",Transfers!$H:$H,"<>Y")+SUMIFS('Stock Received'!$I:$I,'Stock Received'!$E:$E,$A11,'Stock Received'!$L:$L,"CPT") -> 160.06 | F11: =SUMIFS('JHB Count'!$E:$E,'JHB Count'!$F:$F,$A11)-SUMIFS('Weekly Sales'!$F:$F,'Weekly Sales'!$H:$H,$A11,'Weekly Sales'!$I:$I,"JHB")+SUMIFS(Transfers!$F:$F,Transfers!$C:$C,$A11,Transfers!$J:$J,"JHB")-SUMIFS(Transfers!$F:$F,Transfers!$C:$C,$A11,Transfers!$I:$I,"JHB",Transfers!$H:$H,"<>Y")+SUMIFS('Stock Received'!$I:$I,'Stock Received'!$E:$E,$A11,'Stock Received'!$L:$L,"JHB") -> 87.18 | G11: =SUMIFS('DBN Count'!$D:$D,'DBN Count'!$E:$E,$A11)-SUMIFS('Weekly Sales'!$F:$F,'Weekly Sales'!$H:$H,$A11,'Weekly Sales'!$I:$I,"DBN")+SUMIFS(Transfers!$F:$F,Transfers!$C:$C,$A11,Transfers!$J:$J,"DBN")-SUMIFS(Transfers!$F:$F,Transfers!$C:$C,$A11,Transfers!$I:$I,"DBN",Transfers!$H:$H,"<>Y")+SUMIFS('Stock Received'!$I:$I,'Stock Received'!$E:$E,$A11,'Stock Received'!$L:$L,"DBN") -> 49.17 | H11: =E11+F11+G11 -> 296.41 | I11: =SUMIFS('Weekly Sales'!$F:$F,'Weekly Sales'!$H:$H,$A11) -> 64.76 | J11: =SUMIFS(Orders!$L:$L,Orders!$D:$D,$A11,Orders!$F:$F,">="&J$4,Orders!$F:$F,"<"&EDATE(J$4,1)) -> 0 | K11: =SUMIFS(Orders!$L:$L,Orders!$D:$D,$A11,Orders!$F:$F,">="&K$4,Orders!$F:$F,"<"&EDATE(K$4,1)) -> 500 | L11: =SUMIFS(Orders!$L:$L,Orders!$D:$D,$A11,Orders!$F:$F,">="&L$4,Orders!$F:$F,"<"&EDATE(L$4,1)) -> 0 | M11: =N11-J11-K11-L11 -> 0 | N11: =SUMIFS(Orders!$L:$L,Orders!$D:$D,$A11) -> 500 | O11: =H11+N11 -> 796.41 | P11: 210 | Q11: =IF(SUMIFS('Sales History'!$E:$E,'Sales History'!$G:$G,$A11)>0,SUMIFS('Sales History'!$E:$E,'Sales History'!$G:$G,$A11)/Settings!$B$4,N(P11)) -> 210 | R11: =IF(SUMIFS('Sales History'!$E:$E,'Sales History'!$G:$G,$A11)>0,"6-month history",IF(N(P11)>0,"Current sheet","No sales data")) -> Current sheet | S11: =IF(Q11>0,H11/Q11,"") -> 1.4114762 | T11: 300 | U11: =IF(T11="","",MAX(0,T11-O11)) -> 0 | V11: =IF(D11="End of range","END OF RANGE",IF(T11="","NO BUFFER SET",IF(H11<=0,IF(O11<T11,"OUT - REORDER","OUT - ON ORDER"),IF(O11<T11,"REORDER",IF(H11<T11,"LOW - ON ORDER",IF(AND(S11<>"",N(S11)>Settings!$B$5),"SLOW MOVER","OK")))))) -> LOW - ON ORDER | X11: =IF(OR(D11="End of range",U11=""),0,IF(N(U11)>0,U11+ROW()/1000000,0)) -> 0
A12: GAZ012 | B12: GAZELLE GREY | C12: Hide | D12: Active | E12: =SUMIFS('CPT Count'!$D:$D,'CPT Count'!$A:$A,$A12)-SUMIFS('Weekly Sales'!$F:$F,'Weekly Sales'!$H:$H,$A12,'Weekly Sales'!$I:$I,"CPT")+SUMIFS(Transfers!$F:$F,Transfers!$C:$C,$A12,Transfers!$J:$J,"CPT")-SUMIFS(Transfers!$F:$F,Transfers!$C:$C,$A12,Transfers!$I:$I,"CPT",Transfers!$H:$H,"<>Y")+SUMIFS('Stock Received'!$I:$I,'Stock Received'!$E:$E,$A12,'Stock Received'!$L:$L,"CPT") -> 288 | F12: =SUMIFS('JHB Count'!$E:$E,'JHB Count'!$F:$F,$A12)-SUMIFS('Weekly Sales'!$F:$F,'Weekly Sales'!$H:$H,$A12,'Weekly Sales'!$I:$I,"JHB")+SUMIFS(Transfers!$F:$F,Transfers!$C:$C,$A12,Transfers!$J:$J,"JHB")-SUMIFS(Transfers!$F:$F,Transfers!$C:$C,$A12,Transfers!$I:$I,"JHB",Transfers!$H:$H,"<>Y")+SUMIFS('Stock Received'!$I:$I,'Stock Received'!$E:$E,$A12,'Stock Received'!$L:$L,"JHB") -> 92 | G12: =SUMIFS('DBN Count'!$D:$D,'DBN Count'!$E:$E,$A12)-SUMIFS('Weekly Sales'!$F:$F,'Weekly Sales'!$H:$H,$A12,'Weekly Sales'!$I:$I,"DBN")+SUMIFS(Transfers!$F:$F,Transfers!$C:$C,$A12,Transfers!$J:$J,"DBN")-SUMIFS(Transfers!$F:$F,Transfers!$C:$C,$A12,Transfers!$I:$I,"DBN",Transfers!$H:$H,"<>Y")+SUMIFS('Stock Received'!$I:$I,'Stock Received'!$E:$E,$A12,'Stock Received'!$L:$L,"DBN") -> 81.3 | H12: =E12+F12+G12 -> 461.3 | I12: =SUMIFS('Weekly Sales'!$F:$F,'Weekly Sales'!$H:$H,$A12) -> 0 | J12: =SUMIFS(Orders!$L:$L,Orders!$D:$D,$A12,Orders!$F:$F,">="&J$4,Orders!$F:$F,"<"&EDATE(J$4,1)) -> 0 | K12: =SUMIFS(Orders!$L:$L,Orders!$D:$D,$A12,Orders!$F:$F,">="&K$4,Orders!$F:$F,"<"&EDATE(K$4,1)) -> 0 | L12: =SUMIFS(Orders!$L:$L,Orders!$D:$D,$A12,Orders!$F:$F,">="&L$4,Orders!$F:$F,"<"&EDATE(L$4,1)) -> 0 | M12: =N12-J12-K12-L12 -> 0 | N12: =SUMIFS(Orders!$L:$L,Orders!$D:$D,$A12) -> 0 | O12: =H12+N12 -> 461.3 | P12: 35 | Q12: =IF(SUMIFS('Sales History'!$E:$E,'Sales History'!$G:$G,$A12)>0,SUMIFS('Sales History'!$E:$E,'Sales History'!$G:$G,$A12)/Settings!$B$4,N(P12)) -> 35 | R12: =IF(SUMIFS('Sales History'!$E:$E,'Sales History'!$G:$G,$A12)>0,"6-month history",IF(N(P12)>0,"Current sheet","No sales data")) -> Current sheet | S12: =IF(Q12>0,H12/Q12,"") -> 13.18 | T12: 200 | U12: =IF(T12="","",MAX(0,T12-O12)) -> 0 | V12: =IF(D12="End of range","END OF RANGE",IF(T12="","NO BUFFER SET",IF(H12<=0,IF(O12<T12,"OUT - REORDER","OUT - ON ORDER"),IF(O12<T12,"REORDER",IF(H12<T12,"LOW - ON ORDER",IF(AND(S12<>"",N(S12)>Settings!$B$5),"SLOW MOVER","OK")))))) -> SLOW MOVER | X12: =IF(OR(D12="End of range",U12=""),0,IF(N(U12)>0,U12+ROW()/1000000,0)) -> 0
A13: PRE001 | B13: GAZELLE LATTE | C13: Hide | D13: Active | E13: =SUMIFS('CPT Count'!$D:$D,'CPT Count'!$A:$A,$A13)-SUMIFS('Weekly Sales'!$F:$F,'Weekly Sales'!$H:$H,$A13,'Weekly Sales'!$I:$I,"CPT")+SUMIFS(Transfers!$F:$F,Transfers!$C:$C,$A13,Transfers!$J:$J,"CPT")-SUMIFS(Transfers!$F:$F,Transfers!$C:$C,$A13,Transfers!$I:$I,"CPT",Transfers!$H:$H,"<>Y")+SUMIFS('Stock Received'!$I:$I,'Stock Received'!$E:$E,$A13,'Stock Received'!$L:$L,"CPT") -> 1452.11 | F13: =SUMIFS('JHB Count'!$E:$E,'JHB Count'!$F:$F,$A13)-SUMIFS('Weekly Sales'!$F:$F,'Weekly Sales'!$H:$H,$A13,'Weekly Sales'!$I:$I,"JHB")+SUMIFS(Transfers!$F:$F,Transfers!$C:$C,$A13,Transfers!$J:$J,"JHB")-SUMIFS(Transfers!$F:$F,Transfers!$C:$C,$A13,Transfers!$I:$I,"JHB",Transfers!$H:$H,"<>Y")+SUMIFS('Stock Received'!$I:$I,'Stock Received'!$E:$E,$A13,'Stock Received'!$L:$L,"JHB") -> 95.8 | G13: =SUMIFS('DBN Count'!$D:$D,'DBN Count'!$E:$E,$A13)-SUMIFS('Weekly Sales'!$F:$F,'Weekly Sales'!$H:$H,$A13,'Weekly Sales'!$I:$I,"DBN")+SUMIFS(Transfers!$F:$F,Transfers!$C:$C,$A13,Transfers!$J:$J,"DBN")-SUMIFS(Transfers!$F:$F,Transfers!$C:$C,$A13,Transfers!$I:$I,"DBN",Transfers!$H:$H,"<>Y")+SUMIFS('Stock Received'!$I:$I,'Stock Received'!$E:$E,$A13,'Stock Received'!$L:$L,"DBN") -> 48.45 | H13: =E13+F13+G13 -> 1596.36 | I13: =SUMIFS('Weekly Sales'!$F:$F,'Weekly Sales'!$H:$H,$A13) -> 36.09 | J13: =SUMIFS(Orders!$L:$L,Orders!$D:$D,$A13,Orders!$F:$F,">="&J$4,Orders!$F:$F,"<"&EDATE(J$4,1)) -> 0 | K13: =SUMIFS(Orders!$L:$L,Orders!$D:$D,$A13,Orders!$F:$F,">="&K$4,Orders!$F:$F,"<"&EDATE(K$4,1)) -> 0 | L13: =SUMIFS(Orders!$L:$L,Orders!$D:$D,$A13,Orders!$F:$F,">="&L$4,Orders!$F:$F,"<"&EDATE(L$4,1)) -> 0 | M13: =N13-J13-K13-L13 -> 0 | N13: =SUMIFS(Orders!$L:$L,Orders!$D:$D,$A13) -> 0 | O13: =H13+N13 -> 1596.36 | P13: 175 | Q13: =IF(SUMIFS('Sales History'!$E:$E,'Sales History'!$G:$G,$A13)>0,SUMIFS('Sales History'!$E:$E,'Sales History'!$G:$G,$A13)/Settings!$B$4,N(P13)) -> 175 | R13: =IF(SUMIFS('Sales History'!$E:$E,'Sales History'!$G:$G,$A13)>0,"6-month history",IF(N(P13)>0,"Current sheet","No sales data")) -> Current sheet | S13: =IF(Q13>0,H13/Q13,"") -> 9.1220571 | T13: 300 | U13: =IF(T13="","",MAX(0,T13-O13)) -> 0 | V13: =IF(D13="End of range","END OF RANGE",IF(T13="","NO BUFFER SET",IF(H13<=0,IF(O13<T13,"OUT - REORDER","OUT - ON ORDER"),IF(O13<T13,"REORDER",IF(H13<T13,"LOW - ON ORDER",IF(AND(S13<>"",N(S13)>Settings!$B$5),"SLOW MOVER","OK")))))) -> OK | X13: =IF(OR(D13="End of range",U13=""),0,IF(N(U13)>0,U13+ROW()/1000000,0)) -> 0
A14: NAP010 | B14: BALLET NAPPA NUDE (HAN) | C14: Hide | D14: Active | E14: =SUMIFS('CPT Count'!$D:$D,'CPT Count'!$A:$A,$A14)-SUMIFS('Weekly Sales'!$F:$F,'Weekly Sales'!$H:$H,$A14,'Weekly Sales'!$I:$I,"CPT")+SUMIFS(Transfers!$F:$F,Transfers!$C:$C,$A14,Transfers!$J:$J,"CPT")-SUMIFS(Transfers!$F:$F,Transfers!$C:$C,$A14,Transfers!$I:$I,"CPT",Transfers!$H:$H,"<>Y")+SUMIFS('Stock Received'!$I:$I,'Stock Received'!$E:$E,$A14,'Stock Received'!$L:$L,"CPT") -> 275.88 | F14: =SUMIFS('JHB Count'!$E:$E,'JHB Count'!$F:$F,$A14)-SUMIFS('Weekly Sales'!$F:$F,'Weekly Sales'!$H:$H,$A14,'Weekly Sales'!$I:$I,"JHB")+SUMIFS(Transfers!$F:$F,Transfers!$C:$C,$A14,Transfers!$J:$J,"JHB")-SUMIFS(Transfers!$F:$F,Transfers!$C:$C,$A14,Transfers!$I:$I,"JHB",Transfers!$H:$H,"<>Y")+SUMIFS('Stock Received'!$I:$I,'Stock Received'!$E:$E,$A14,'Stock Received'!$L:$L,"JHB") -> 0 | G14: =SUMIFS('DBN Count'!$D:$D,'DBN Count'!$E:$E,$A14)-SUMIFS('Weekly Sales'!$F:$F,'Weekly Sales'!$H:$H,$A14,'Weekly Sales'!$I:$I,"DBN")+SUMIFS(Transfers!$F:$F,Transfers!$C:$C,$A14,Transfers!$J:$J,"DBN")-SUMIFS(Transfers!$F:$F,Transfers!$C:$C,$A14,Transfers!$I:$I,"DBN",Transfers!$H:$H,"<>Y")+SUMIFS('Stock Received'!$I:$I,'Stock Received'!$E:$E,$A14,'Stock Received'!$L:$L,"DBN") -> 2.13 | H14: =E14+F14+G14 -> 278.01 | I14: =SUMIFS('Weekly Sales'!$F:$F,'Weekly Sales'!$H:$H,$A14) -> 4.12 | J14: =SUMIFS(Orders!$L:$L,Orders!$D:$D,$A14,Orders!$F:$F,">="&J$4,Orders!$F:$F,"<"&EDATE(J$4,1)) -> 0 | K14: =SUMIFS(Orders!$L:$L,Orders!$D:$D,$A14,Orders!$F:$F,">="&K$4,Orders!$F:$F,"<"&EDATE(K$4,1)) -> 0 | L14: =SUMIFS(Orders!$L:$L,Orders!$D:$D,$A14,Orders!$F:$F,">="&L$4,Orders!$F:$F,"<"&EDATE(L$4,1)) -> 0 | M14: =N14-J14-K14-L14 -> 0 | N14: =SUMIFS(Orders!$L:$L,Orders!$D:$D,$A14) -> 0 | O14: =H14+N14 -> 278.01 | P14: 50 | Q14: =IF(SUMIFS('Sales History'!$E:$E,'Sales History'!$G:$G,$A14)>0,SUMIFS('Sales History'!$E:$E,'Sales History'!$G:$G,$A14)/Settings!$B$4,N(P14)) -> 50 | R14: =IF(SUMIFS('Sales History'!$E:$E,'Sales History'!$G:$G,$A14)>0,"6-month history",IF(N(P14)>0,"Current sheet","No sales data")) -> Current sheet | S14: =IF(Q14>0,H14/Q14,"") -> 5.5602 | T14: 200 | U14: =IF(T14="","",MAX(0,T14-O14)) -> 0 | V14: =IF(D14="End of range","END OF RANGE",IF(T14="","NO BUFFER SET",IF(H14<=0,IF(O14<T14,"OUT - REORDER","OUT - ON ORDER"),IF(O14<T14,"REORDER",IF(H14<T14,"LOW - ON ORDER",IF(AND(S14<>"",N(S14)>Settings!$B$5),"SLOW MOVER","OK")))))) -> OK | X14: =IF(OR(D14="End of range",U14=""),0,IF(N(U14)>0,U14+ROW()/1000000,0)) -> 0
A15: MOR004 | B15: MOROCCO STRAW | C15: Hide | D15: Active | E15: =SUMIFS('CPT Count'!$D:$D,'CPT Count'!$A:$A,$A15)-SUMIFS('Weekly Sales'!$F:$F,'Weekly Sales'!$H:$H,$A15,'Weekly Sales'!$I:$I,"CPT")+SUMIFS(Transfers!$F:$F,Transfers!$C:$C,$A15,Transfers!$J:$J,"CPT")-SUMIFS(Transfers!$F:$F,Transfers!$C:$C,$A15,Transfers!$I:$I,"CPT",Transfers!$H:$H,"<>Y")+SUMIFS('Stock Received'!$I:$I,'Stock Received'!$E:$E,$A15,'Stock Received'!$L:$L,"CPT") -> 598.42 | F15: =SUMIFS('JHB Count'!$E:$E,'JHB Count'!$F:$F,$A15)-SUMIFS('Weekly Sales'!$F:$F,'Weekly Sales'!$H:$H,$A15,'Weekly Sales'!$I:$I,"JHB")+SUMIFS(Transfers!$F:$F,Transfers!$C:$C,$A15,Transfers!$J:$J,"JHB")-SUMIFS(Transfers!$F:$F,Transfers!$C:$C,$A15,Transfers!$I:$I,"JHB",Transfers!$H:$H,"<>Y")+SUMIFS('Stock Received'!$I:$I,'Stock Received'!$E:$E,$A15,'Stock Received'!$L:$L,"JHB") -> 39.88 | G15: =SUMIFS('DBN Count'!$D:$D,'DBN Count'!$E:$E,$A15)-SUMIFS('Weekly Sales'!$F:$F,'Weekly Sales'!$H:$H,$A15,'Weekly Sales'!$I:$I,"DBN")+SUMIFS(Transfers!$F:$F,Transfers!$C:$C,$A15,Transfers!$J:$J,"DBN")-SUMIFS(Transfers!$F:$F,Transfers!$C:$C,$A15,Transfers!$I:$I,"DBN",Transfers!$H:$H,"<>Y")+SUMIFS('Stock Received'!$I:$I,'Stock Received'!$E:$E,$A15,'Stock Received'!$L:$L,"DBN") -> 15.56 | H15: =E15+F15+G15 -> 653.86 | I15: =SUMIFS('Weekly Sales'!$F:$F,'Weekly Sales'!$H:$H,$A15) -> 25.33 | J15: =SUMIFS(Orders!$L:$L,Orders!$D:$D,$A15,Orders!$F:$F,">="&J$4,Orders!$F:$F,"<"&EDATE(J$4,1)) -> 0 | K15: =SUMIFS(Orders!$L:$L,Orders!$D:$D,$A15,Orders!$F:$F,">="&K$4,Orders!$F:$F,"<"&EDATE(K$4,1)) -> 0 | L15: =SUMIFS(Orders!$L:$L,Orders!$D:$D,$A15,Orders!$F:$F,">="&L$4,Orders!$F:$F,"<"&EDATE(L$4,1)) -> 300 | M15: =N15-J15-K15-L15 -> 0 | N15: =SUMIFS(Orders!$L:$L,Orders!$D:$D,$A15) -> 300 | O15: =H15+N15 -> 953.86 | P15: 200 | Q15: =IF(SUMIFS('Sales History'!$E:$E,'Sales History'!$G:$G,$A15)>0,SUMIFS('Sales History'!$E:$E,'Sales History'!$G:$G,$A15)/Settings!$B$4,N(P15)) -> 200 | R15: =IF(SUMIFS('Sales History'!$E:$E,'Sales History'!$G:$G,$A15)>0,"6-month history",IF(N(P15)>0,"Current sheet","No sales data")) -> Current sheet | S15: =IF(Q15>0,H15/Q15,"") -> 3.2693 | T15: 300 | U15: =IF(T15="","",MAX(0,T15-O15)) -> 0 | V15: =IF(D15="End of range","END OF RANGE",IF(T15="","NO BUFFER SET",IF(H15<=0,IF(O15<T15,"OUT - REORDER","OUT - ON ORDER"),IF(O15<T15,"REORDER",IF(H15<T15,"LOW - ON ORDER",IF(AND(S15<>"",N(S15)>Settings!$B$5),"SLOW MOVER","OK")))))) -> OK | X15: =IF(OR(D15="End of range",U15=""),0,IF(N(U15)>0,U15+ROW()/1000000,0)) -> 0
A16: MOR003 | B16: MOROCCO CHOCOLATE | C16: Hide | D16: Active | E16: =SUMIFS('CPT Count'!$D:$D,'CPT Count'!$A:$A,$A16)-SUMIFS('Weekly Sales'!$F:$F,'Weekly Sales'!$H:$H,$A16,'Weekly Sales'!$I:$I,"CPT")+SUMIFS(Transfers!$F:$F,Transfers!$C:$C,$A16,Transfers!$J:$J,"CPT")-SUMIFS(Transfers!$F:$F,Transfers!$C:$C,$A16,Transfers!$I:$I,"CPT",Transfers!$H:$H,"<>Y")+SUMIFS('Stock Received'!$I:$I,'Stock Received'!$E:$E,$A16,'Stock Received'!$L:$L,"CPT") -> 309 | F16: =SUMIFS('JHB Count'!$E:$E,'JHB Count'!$F:$F,$A16)-SUMIFS('Weekly Sales'!$F:$F,'Weekly Sales'!$H:$H,$A16,'Weekly Sales'!$I:$I,"JHB")+SUMIFS(Transfers!$F:$F,Transfers!$C:$C,$A16,Transfers!$J:$J,"JHB")-SUMIFS(Transfers!$F:$F,Transfers!$C:$C,$A16,Transfers!$I:$I,"JHB",Transfers!$H:$H,"<>Y")+SUMIFS('Stock Received'!$I:$I,'Stock Received'!$E:$E,$A16,'Stock Received'!$L:$L,"JHB") -> 64.33 | G16: =SUMIFS('DBN Count'!$D:$D,'DBN Count'!$E:$E,$A16)-SUMIFS('Weekly Sales'!$F:$F,'Weekly Sales'!$H:$H,$A16,'Weekly Sales'!$I:$I,"DBN")+SUMIFS(Transfers!$F:$F,Transfers!$C:$C,$A16,Transfers!$J:$J,"DBN")-SUMIFS(Transfers!$F:$F,Transfers!$C:$C,$A16,Transfers!$I:$I,"DBN",Transfers!$H:$H,"<>Y")+SUMIFS('Stock Received'!$I:$I,'Stock Received'!$E:$E,$A16,'Stock Received'!$L:$L,"DBN") -> 23.9 | H16: =E16+F16+G16 -> 397.23 | I16: =SUMIFS('Weekly Sales'!$F:$F,'Weekly Sales'!$H:$H,$A16) -> 3.67 | J16: =SUMIFS(Orders!$L:$L,Orders!$D:$D,$A16,Orders!$F:$F,">="&J$4,Orders!$F:$F,"<"&EDATE(J$4,1)) -> 0 | K16: =SUMIFS(Orders!$L:$L,Orders!$D:$D,$A16,Orders!$F:$F,">="&K$4,Orders!$F:$F,"<"&EDATE(K$4,1)) -> 300 | L16: =SUMIFS(Orders!$L:$L,Orders!$D:$D,$A16,Orders!$F:$F,">="&L$4,Orders!$F:$F,"<"&EDATE(L$4,1)) -> 300 | M16: =N16-J16-K16-L16 -> 0 | N16: =SUMIFS(Orders!$L:$L,Orders!$D:$D,$A16) -> 600 | O16: =H16+N16 -> 997.23 | P16: 85 | Q16: =IF(SUMIFS('Sales History'!$E:$E,'Sales History'!$G:$G,$A16)>0,SUMIFS('Sales History'!$E:$E,'Sales History'!$G:$G,$A16)/Settings!$B$4,N(P16)) -> 85 | R16: =IF(SUMIFS('Sales History'!$E:$E,'Sales History'!$G:$G,$A16)>0,"6-month history",IF(N(P16)>0,"Current sheet","No sales data")) -> Current sheet | S16: =IF(Q16>0,H16/Q16,"") -> 4.6732941 | T16: 300 | U16: =IF(T16="","",MAX(0,T16-O16)) -> 0 | V16: =IF(D16="End of range","END OF RANGE",IF(T16="","NO BUFFER SET",IF(H16<=0,IF(O16<T16,"OUT - REORDER","OUT - ON ORDER"),IF(O16<T16,"REORDER",IF(H16<T16,"LOW - ON ORDER",IF(AND(S16<>"",N(S16)>Settings!$B$5),"SLOW MOVER","OK")))))) -> OK | X16: =IF(OR(D16="End of range",U16=""),0,IF(N(U16)>0,U16+ROW()/1000000,0)) -> 0
... A18: MOR010 | B18: MOROCCO RUBY | C18: Hide | D18: Active | E18: =SUMIFS('CPT Count'!$D:$D,'CPT Count'!$A:$A,$A18)-SUMIFS('Weekly Sales'!$F:$F,'Weekly Sales'!$H:$H,$A18,'Weekly Sales'!$I:$I,"CPT")+SUMIFS(Transfers!$F:$F,Transfers!$C:$C,$A18,Transfers!$J:$J,"CPT")-SUMIFS(Transfers!$F:$F,Transfers!$C:$C,$A18,Transfers!$I:$I,"CPT",Transfers!$H:$H,"<>Y")+SUMIFS('Stock Received'!$I:$I,'Stock Received'!$E:$E,$A18,'Stock Received'!$L:$L,"CPT") -> 406.37 | F18: =SUMIFS('JHB Count'!$E:$E,'JHB Count'!$F:$F,$A18)-SUMIFS('Weekly Sales'!$F:$F,'Weekly Sales'!$H:$H,$A18,'Weekly Sales'!$I:$I,"JHB")+SUMIFS(Transfers!$F:$F,Transfers!$C:$C,$A18,Transfers!$J:$J,"JHB")-SUMIFS(Transfers!$F:$F,Transfers!$C:$C,$A18,Transfers!$I:$I,"JHB",Transfers!$H:$H,"<>Y")+SUMIFS('Stock Received'!$I:$I,'Stock Received'!$E:$E,$A18,'Stock Received'!$L:$L,"JHB") -> 24.86 | G18: =SUMIFS('DBN Count'!$D:$D,'DBN Count'!$E:$E,$A18)-SUMIFS('Weekly Sales'!$F:$F,'Weekly Sales'!$H:$H,$A18,'Weekly Sales'!$I:$I,"DBN")+SUMIFS(Transfers!$F:$F,Transfers!$C:$C,$A18,Transfers!$J:$J,"DBN")-SUMIFS(Transfers!$F:$F,Transfers!$C:$C,$A18,Transfers!$I:$I,"DBN",Transfers!$H:$H,"<>Y")+SUMIFS('Stock Received'!$I:$I,'Stock Received'!$E:$E,$A18,'Stock Received'!$L:$L,"DBN") -> 24.23 | H18: =E18+F18+G18 -> 455.46 | I18: =SUMIFS('Weekly Sales'!$F:$F,'Weekly Sales'!$H:$H,$A18) -> 69.36 | J18: =SUMIFS(Orders!$L:$L,Orders!$D:$D,$A18,Orders!$F:$F,">="&J$4,Orders!$F:$F,"<"&EDATE(J$4,1)) -> 0 | K18: =SUMIFS(Orders!$L:$L,Orders!$D:$D,$A18,Orders!$F:$F,">="&K$4,Orders!$F:$F,"<"&EDATE(K$4,1)) -> 300 | L18: =SUMIFS(Orders!$L:$L,Orders!$D:$D,$A18,Orders!$F:$F,">="&L$4,Orders!$F:$F,"<"&EDATE(L$4,1)) -> 0 | M18: =N18-J18-K18-L18 -> 0 | N18: =SUMIFS(Orders!$L:$L,Orders!$D:$D,$A18) -> 300 | O18: =H18+N18 -> 755.46 | P18: 200 | Q18: =IF(SUMIFS('Sales History'!$E:$E,'Sales History'!$G:$G,$A18)>0,SUMIFS('Sales History'!$E:$E,'Sales History'!$G:$G,$A18)/Settings!$B$4,N(P18)) -> 200 | R18: =IF(SUMIFS('Sales History'!$E:$E,'Sales History'!$G:$G,$A18)>0,"6-month history",IF(N(P18)>0,"Current sheet","No sales data")) -> Current sheet | S18: =IF(Q18>0,H18/Q18,"") -> 2.2773 | T18: 300 | U18: =IF(T18="","",MAX(0,T18-O18)) -> 0 | V18: =IF(D18="End of range","END OF RANGE",IF(T18="","NO BUFFER SET",IF(H18<=0,IF(O18<T18,"OUT - REORDER","OUT - ON ORDER"),IF(O18<T18,"REORDER",IF(H18<T18,"LOW - ON ORDER",IF(AND(S18<>"",N(S18)>Settings!$B$5),"SLOW MOVER","OK")))))) -> OK | X18: =IF(OR(D18="End of range",U18=""),0,IF(N(U18)>0,U18+ROW()/1000000,0)) -> 0
A19: SOR001 | B19: SORRENTO BLACK | C19: Hide | D19: Active | E19: =SUMIFS('CPT Count'!$D:$D,'CPT Count'!$A:$A,$A19)-SUMIFS('Weekly Sales'!$F:$F,'Weekly Sales'!$H:$H,$A19,'Weekly Sales'!$I:$I,"CPT")+SUMIFS(Transfers!$F:$F,Transfers!$C:$C,$A19,Transfers!$J:$J,"CPT")-SUMIFS(Transfers!$F:$F,Transfers!$C:$C,$A19,Transfers!$I:$I,"CPT",Transfers!$H:$H,"<>Y")+SUMIFS('Stock Received'!$I:$I,'Stock Received'!$E:$E,$A19,'Stock Received'!$L:$L,"CPT") -> 0 | F19: =SUMIFS('JHB Count'!$E:$E,'JHB Count'!$F:$F,$A19)-SUMIFS('Weekly Sales'!$F:$F,'Weekly Sales'!$H:$H,$A19,'Weekly Sales'!$I:$I,"JHB")+SUMIFS(Transfers!$F:$F,Transfers!$C:$C,$A19,Transfers!$J:$J,"JHB")-SUMIFS(Transfers!$F:$F,Transfers!$C:$C,$A19,Transfers!$I:$I,"JHB",Transfers!$H:$H,"<>Y")+SUMIFS('Stock Received'!$I:$I,'Stock Received'!$E:$E,$A19,'Stock Received'!$L:$L,"JHB") -> 1265.16 | G19: =SUMIFS('DBN Count'!$D:$D,'DBN Count'!$E:$E,$A19)-SUMIFS('Weekly Sales'!$F:$F,'Weekly Sales'!$H:$H,$A19,'Weekly Sales'!$I:$I,"DBN")+SUMIFS(Transfers!$F:$F,Transfers!$C:$C,$A19,Transfers!$J:$J,"DBN")-SUMIFS(Transfers!$F:$F,Transfers!$C:$C,$A19,Transfers!$I:$I,"DBN",Transfers!$H:$H,"<>Y")+SUMIFS('Stock Received'!$I:$I,'Stock Received'!$E:$E,$A19,'Stock Received'!$L:$L,"DBN") -> 109.15 | H19: =E19+F19+G19 -> 1374.31 | I19: =SUMIFS('Weekly Sales'!$F:$F,'Weekly Sales'!$H:$H,$A19) -> 126.84 | J19: =SUMIFS(Orders!$L:$L,Orders!$D:$D,$A19,Orders!$F:$F,">="&J$4,Orders!$F:$F,"<"&EDATE(J$4,1)) -> 0 | K19: =SUMIFS(Orders!$L:$L,Orders!$D:$D,$A19,Orders!$F:$F,">="&K$4,Orders!$F:$F,"<"&EDATE(K$4,1)) -> 1000 | L19: =SUMIFS(Orders!$L:$L,Orders!$D:$D,$A19,Orders!$F:$F,">="&L$4,Orders!$F:$F,"<"&EDATE(L$4,1)) -> 0 | M19: =N19-J19-K19-L19 -> 0 | N19: =SUMIFS(Orders!$L:$L,Orders!$D:$D,$A19) -> 1000 | O19: =H19+N19 -> 2374.31 | P19: 0 | Q19: =IF(SUMIFS('Sales History'!$E:$E,'Sales History'!$G:$G,$A19)>0,SUMIFS('Sales History'!$E:$E,'Sales History'!$G:$G,$A19)/Settings!$B$4,N(P19)) -> 0 | R19: =IF(SUMIFS('Sales History'!$E:$E,'Sales History'!$G:$G,$A19)>0,"6-month history",IF(N(P19)>0,"Current sheet","No sales data")) -> No sales data | S19: =IF(Q19>0,H19/Q19,"") | U19: =IF(T19="","",MAX(0,T19-O19)) | V19: =IF(D19="End of range","END OF RANGE",IF(T19="","NO BUFFER SET",IF(H19<=0,IF(O19<T19,"OUT - REORDER","OUT - ON ORDER"),IF(O19<T19,"REORDER",IF(H19<T19,"LOW - ON ORDER",IF(AND(S19<>"",N(S19)>Settings!$B$5),"SLOW MOVER","OK")))))) -> NO BUFFER SET | X19: =IF(OR(D19="End of range",U19=""),0,IF(N(U19)>0,U19+ROW()/1000000,0)) -> 0
A20: SOR012 | B20: SORRENTO OYSTER | C20: Hide | D20: Active | E20: =SUMIFS('CPT Count'!$D:$D,'CPT Count'!$A:$A,$A20)-SUMIFS('Weekly Sales'!$F:$F,'Weekly Sales'!$H:$H,$A20,'Weekly Sales'!$I:$I,"CPT")+SUMIFS(Transfers!$F:$F,Transfers!$C:$C,$A20,Transfers!$J:$J,"CPT")-SUMIFS(Transfers!$F:$F,Transfers!$C:$C,$A20,Transfers!$I:$I,"CPT",Transfers!$H:$H,"<>Y")+SUMIFS('Stock Received'!$I:$I,'Stock Received'!$E:$E,$A20,'Stock Received'!$L:$L,"CPT") -> 0 | F20: =SUMIFS('JHB Count'!$E:$E,'JHB Count'!$F:$F,$A20)-SUMIFS('Weekly Sales'!$F:$F,'Weekly Sales'!$H:$H,$A20,'Weekly Sales'!$I:$I,"JHB")+SUMIFS(Transfers!$F:$F,Transfers!$C:$C,$A20,Transfers!$J:$J,"JHB")-SUMIFS(Transfers!$F:$F,Transfers!$C:$C,$A20,Transfers!$I:$I,"JHB",Transfers!$H:$H,"<>Y")+SUMIFS('Stock Received'!$I:$I,'Stock Received'!$E:$E,$A20,'Stock Received'!$L:$L,"JHB") -> 0 | G20: =SUMIFS('DBN Count'!$D:$D,'DBN Count'!$E:$E,$A20)-SUMIFS('Weekly Sales'!$F:$F,'Weekly Sales'!$H:$H,$A20,'Weekly Sales'!$I:$I,"DBN")+SUMIFS(Transfers!$F:$F,Transfers!$C:$C,$A20,Transfers!$J:$J,"DBN")-SUMIFS(Transfers!$F:$F,Transfers!$C:$C,$A20,Transfers!$I:$I,"DBN",Transfers!$H:$H,"<>Y")+SUMIFS('Stock Received'!$I:$I,'Stock Received'!$E:$E,$A20,'Stock Received'!$L:$L,"DBN") -> 0 | H20: =E20+F20+G20 -> 0 | I20: =SUMIFS('Weekly Sales'!$F:$F,'Weekly Sales'!$H:$H,$A20) -> 0 | J20: =SUMIFS(Orders!$L:$L,Orders!$D:$D,$A20,Orders!$F:$F,">="&J$4,Orders!$F:$F,"<"&EDATE(J$4,1)) -> 0 | K20: =SUMIFS(Orders!$L:$L,Orders!$D:$D,$A20,Orders!$F:$F,">="&K$4,Orders!$F:$F,"<"&EDATE(K$4,1)) -> 200 | L20: =SUMIFS(Orders!$L:$L,Orders!$D:$D,$A20,Orders!$F:$F,">="&L$4,Orders!$F:$F,"<"&EDATE(L$4,1)) -> 0 | M20: =N20-J20-K20-L20 -> 0 | N20: =SUMIFS(Orders!$L:$L,Orders!$D:$D,$A20) -> 200 | O20: =H20+N20 -> 200 | Q20: =IF(SUMIFS('Sales History'!$E:$E,'Sales History'!$G:$G,$A20)>0,SUMIFS('Sales History'!$E:$E,'Sales History'!$G:$G,$A20)/Settings!$B$4,N(P20)) -> 0 | R20: =IF(SUMIFS('Sales History'!$E:$E,'Sales History'!$G:$G,$A20)>0,"6-month history",IF(N(P20)>0,"Current sheet","No sales data")) -> No sales data | S20: =IF(Q20>0,H20/Q20,"") | U20: =IF(T20="","",MAX(0,T20-O20)) | V20: =IF(D20="End of range","END OF RANGE",IF(T20="","NO BUFFER SET",IF(H20<=0,IF(O20<T20,"OUT - REORDER","OUT - ON ORDER"),IF(O20<T20,"REORDER",IF(H20<T20,"LOW - ON ORDER",IF(AND(S20<>"",N(S20)>Settings!$B$5),"SLOW MOVER","OK")))))) -> NO BUFFER SET | X20: =IF(OR(D20="End of range",U20=""),0,IF(N(U20)>0,U20+ROW()/1000000,0)) -> 0
A21: SAN010 | B21: SANTOS ICE WHITE | C21: Hide | D21: Active | E21: =SUMIFS('CPT Count'!$D:$D,'CPT Count'!$A:$A,$A21)-SUMIFS('Weekly Sales'!$F:$F,'Weekly Sales'!$H:$H,$A21,'Weekly Sales'!$I:$I,"CPT")+SUMIFS(Transfers!$F:$F,Transfers!$C:$C,$A21,Transfers!$J:$J,"CPT")-SUMIFS(Transfers!$F:$F,Transfers!$C:$C,$A21,Transfers!$I:$I,"CPT",Transfers!$H:$H,"<>Y")+SUMIFS('Stock Received'!$I:$I,'Stock Received'!$E:$E,$A21,'Stock Received'!$L:$L,"CPT") -> 337.5 | F21: =SUMIFS('JHB Count'!$E:$E,'JHB Count'!$F:$F,$A21)-SUMIFS('Weekly Sales'!$F:$F,'Weekly Sales'!$H:$H,$A21,'Weekly Sales'!$I:$I,"JHB")+SUMIFS(Transfers!$F:$F,Transfers!$C:$C,$A21,Transfers!$J:$J,"JHB")-SUMIFS(Transfers!$F:$F,Transfers!$C:$C,$A21,Transfers!$I:$I,"JHB",Transfers!$H:$H,"<>Y")+SUMIFS('Stock Received'!$I:$I,'Stock Received'!$E:$E,$A21,'Stock Received'!$L:$L,"JHB") -> 80 | G21: =SUMIFS('DBN Count'!$D:$D,'DBN Count'!$E:$E,$A21)-SUMIFS('Weekly Sales'!$F:$F,'Weekly Sales'!$H:$H,$A21,'Weekly Sales'!$I:$I,"DBN")+SUMIFS(Transfers!$F:$F,Transfers!$C:$C,$A21,Transfers!$J:$J,"DBN")-SUMIFS(Transfers!$F:$F,Transfers!$C:$C,$A21,Transfers!$I:$I,"DBN",Transfers!$H:$H,"<>Y")+SUMIFS('Stock Received'!$I:$I,'Stock Received'!$E:$E,$A21,'Stock Received'!$L:$L,"DBN") -> 67.4 | H21: =E21+F21+G21 -> 484.9 | I21: =SUMIFS('Weekly Sales'!$F:$F,'Weekly Sales'!$H:$H,$A21) -> 0.5 | J21: =SUMIFS(Orders!$L:$L,Orders!$D:$D,$A21,Orders!$F:$F,">="&J$4,Orders!$F:$F,"<"&EDATE(J$4,1)) -> 0 | K21: =SUMIFS(Orders!$L:$L,Orders!$D:$D,$A21,Orders!$F:$F,">="&K$4,Orders!$F:$F,"<"&EDATE(K$4,1)) -> 300 | L21: =SUMIFS(Orders!$L:$L,Orders!$D:$D,$A21,Orders!$F:$F,">="&L$4,Orders!$F:$F,"<"&EDATE(L$4,1)) -> 0 | M21: =N21-J21-K21-L21 -> 0 | N21: =SUMIFS(Orders!$L:$L,Orders!$D:$D,$A21) -> 300 | O21: =H21+N21 -> 784.9 | P21: 150 | Q21: =IF(SUMIFS('Sales History'!$E:$E,'Sales History'!$G:$G,$A21)>0,SUMIFS('Sales History'!$E:$E,'Sales History'!$G:$G,$A21)/Settings!$B$4,N(P21)) -> 150 | R21: =IF(SUMIFS('Sales History'!$E:$E,'Sales History'!$G:$G,$A21)>0,"6-month history",IF(N(P21)>0,"Current sheet","No sales data")) -> Current sheet | S21: =IF(Q21>0,H21/Q21,"") -> 3.2326667 | T21: 300 | U21: =IF(T21="","",MAX(0,T21-O21)) -> 0 | V21: =IF(D21="End of range","END OF RANGE",IF(T21="","NO BUFFER SET",IF(H21<=0,IF(O21<T21,"OUT - REORDER","OUT - ON ORDER"),IF(O21<T21,"REORDER",IF(H21<T21,"LOW - ON ORDER",IF(AND(S21<>"",N(S21)>Settings!$B$5),"SLOW MOVER","OK")))))) -> OK | X21: =IF(OR(D21="End of range",U21=""),0,IF(N(U21)>0,U21+ROW()/1000000,0)) -> 0
A22: SAN006 | B22: SANTOS COTTON WHITE | C22: Hide | D22: Active | E22: =SUMIFS('CPT Count'!$D:$D,'CPT Count'!$A:$A,$A22)-SUMIFS('Weekly Sales'!$F:$F,'Weekly Sales'!$H:$H,$A22,'Weekly Sales'!$I:$I,"CPT")+SUMIFS(Transfers!$F:$F,Transfers!$C:$C,$A22,Transfers!$J:$J,"CPT")-SUMIFS(Transfers!$F:$F,Transfers!$C:$C,$A22,Transfers!$I:$I,"CPT",Transfers!$H:$H,"<>Y")+SUMIFS('Stock Received'!$I:$I,'Stock Received'!$E:$E,$A22,'Stock Received'!$L:$L,"CPT") -> 209.57 | F22: =SUMIFS('JHB Count'!$E:$E,'JHB Count'!$F:$F,$A22)-SUMIFS('Weekly Sales'!$F:$F,'Weekly Sales'!$H:$H,$A22,'Weekly Sales'!$I:$I,"JHB")+SUMIFS(Transfers!$F:$F,Transfers!$C:$C,$A22,Transfers!$J:$J,"JHB")-SUMIFS(Transfers!$F:$F,Transfers!$C:$C,$A22,Transfers!$I:$I,"JHB",Transfers!$H:$H,"<>Y")+SUMIFS('Stock Received'!$I:$I,'Stock Received'!$E:$E,$A22,'Stock Received'!$L:$L,"JHB") -> 0 | G22: =SUMIFS('DBN Count'!$D:$D,'DBN Count'!$E:$E,$A22)-SUMIFS('Weekly Sales'!$F:$F,'Weekly Sales'!$H:$H,$A22,'Weekly Sales'!$I:$I,"DBN")+SUMIFS(Transfers!$F:$F,Transfers!$C:$C,$A22,Transfers!$J:$J,"DBN")-SUMIFS(Transfers!$F:$F,Transfers!$C:$C,$A22,Transfers!$I:$I,"DBN",Transfers!$H:$H,"<>Y")+SUMIFS('Stock Received'!$I:$I,'Stock Received'!$E:$E,$A22,'Stock Received'!$L:$L,"DBN") -> 51.46 | H22: =E22+F22+G22 -> 261.03 | I22: =SUMIFS('Weekly Sales'!$F:$F,'Weekly Sales'!$H:$H,$A22) -> 9.43 | J22: =SUMIFS(Orders!$L:$L,Orders!$D:$D,$A22,Orders!$F:$F,">="&J$4,Orders!$F:$F,"<"&EDATE(J$4,1)) -> 0 | K22: =SUMIFS(Orders!$L:$L,Orders!$D:$D,$A22,Orders!$F:$F,">="&K$4,Orders!$F:$F,"<"&EDATE(K$4,1)) -> 300 | L22: =SUMIFS(Orders!$L:$L,Orders!$D:$D,$A22,Orders!$F:$F,">="&L$4,Orders!$F:$F,"<"&EDATE(L$4,1)) -> 0 | M22: =N22-J22-K22-L22 -> 0 | N22: =SUMIFS(Orders!$L:$L,Orders!$D:$D,$A22) -> 300 | O22: =H22+N22 -> 561.03 | P22: 80 | Q22: =IF(SUMIFS('Sales History'!$E:$E,'Sales History'!$G:$G,$A22)>0,SUMIFS('Sales History'!$E:$E,'Sales History'!$G:$G,$A22)/Settings!$B$4,N(P22)) -> 80 | R22: =IF(SUMIFS('Sales History'!$E:$E,'Sales History'!$G:$G,$A22)>0,"6-month history",IF(N(P22)>0,"Current sheet","No sales data")) -> Current sheet | S22: =IF(Q22>0,H22/Q22,"") -> 3.262875 | T22: 200 | U22: =IF(T22="","",MAX(0,T22-O22)) -> 0 | V22: =IF(D22="End of range","END OF RANGE",IF(T22="","NO BUFFER SET",IF(H22<=0,IF(O22<T22,"OUT - REORDER","OUT - ON ORDER"),IF(O22<T22,"REORDER",IF(H22<T22,"LOW - ON ORDER",IF(AND(S22<>"",N(S22)>Settings!$B$5),"SLOW MOVER","OK")))))) -> OK | X22: =IF(OR(D22="End of range",U22=""),0,IF(N(U22)>0,U22+ROW()/1000000,0)) -> 0
A23: SAN017 | B23: SANTOS RED/PAPRIKA | C23: Hide | D23: Active | E23: =SUMIFS('CPT Count'!$D:$D,'CPT Count'!$A:$A,$A23)-SUMIFS('Weekly Sales'!$F:$F,'Weekly Sales'!$H:$H,$A23,'Weekly Sales'!$I:$I,"CPT")+SUMIFS(Transfers!$F:$F,Transfers!$C:$C,$A23,Transfers!$J:$J,"CPT")-SUMIFS(Transfers!$F:$F,Transfers!$C:$C,$A23,Transfers!$I:$I,"CPT",Transfers!$H:$H,"<>Y")+SUMIFS('Stock Received'!$I:$I,'Stock Received'!$E:$E,$A23,'Stock Received'!$L:$L,"CPT") -> 318.72 | F23: =SUMIFS('JHB Count'!$E:$E,'JHB Count'!$F:$F,$A23)-SUMIFS('Weekly Sales'!$F:$F,'Weekly Sales'!$H:$H,$A23,'Weekly Sales'!$I:$I,"JHB")+SUMIFS(Transfers!$F:$F,Transfers!$C:$C,$A23,Transfers!$J:$J,"JHB")-SUMIFS(Transfers!$F:$F,Transfers!$C:$C,$A23,Transfers!$I:$I,"JHB",Transfers!$H:$H,"<>Y")+SUMIFS('Stock Received'!$I:$I,'Stock Received'!$E:$E,$A23,'Stock Received'!$L:$L,"JHB") -> 67.79 | G23: =SUMIFS('DBN Count'!$D:$D,'DBN Count'!$E:$E,$A23)-SUMIFS('Weekly Sales'!$F:$F,'Weekly Sales'!$H:$H,$A23,'Weekly Sales'!$I:$I,"DBN")+SUMIFS(Transfers!$F:$F,Transfers!$C:$C,$A23,Transfers!$J:$J,"DBN")-SUMIFS(Transfers!$F:$F,Transfers!$C:$C,$A23,Transfers!$I:$I,"DBN",Transfers!$H:$H,"<>Y")+SUMIFS('Stock Received'!$I:$I,'Stock Received'!$E:$E,$A23,'Stock Received'!$L:$L,"DBN") -> 32.74 | H23: =E23+F23+G23 -> 419.25 | I23: =SUMIFS('Weekly Sales'!$F:$F,'Weekly Sales'!$H:$H,$A23) -> 4.21 | J23: =SUMIFS(Orders!$L:$L,Orders!$D:$D,$A23,Orders!$F:$F,">="&J$4,Orders!$F:$F,"<"&EDATE(J$4,1)) -> 0 | K23: =SUMIFS(Orders!$L:$L,Orders!$D:$D,$A23,Orders!$F:$F,">="&K$4,Orders!$F:$F,"<"&EDATE(K$4,1)) -> 0 | L23: =SUMIFS(Orders!$L:$L,Orders!$D:$D,$A23,Orders!$F:$F,">="&L$4,Orders!$F:$F,"<"&EDATE(L$4,1)) -> 0 | M23: =N23-J23-K23-L23 -> 0 | N23: =SUMIFS(Orders!$L:$L,Orders!$D:$D,$A23) -> 0 | O23: =H23+N23 -> 419.25 | P23: 45 | Q23: =IF(SUMIFS('Sales History'!$E:$E,'Sales History'!$G:$G,$A23)>0,SUMIFS('Sales History'!$E:$E,'Sales History'!$G:$G,$A23)/Settings!$B$4,N(P23)) -> 45 | R23: =IF(SUMIFS('Sales History'!$E:$E,'Sales History'!$G:$G,$A23)>0,"6-month history",IF(N(P23)>0,"Current sheet","No sales data")) -> Current sheet | S23: =IF(Q23>0,H23/Q23,"") -> 9.3166667 | T23: 200 | U23: =IF(T23="","",MAX(0,T23-O23)) -> 0 | V23: =IF(D23="End of range","END OF RANGE",IF(T23="","NO BUFFER SET",IF(H23<=0,IF(O23<T23,"OUT - REORDER","OUT - ON ORDER"),IF(O23<T23,"REORDER",IF(H23<T23,"LOW - ON ORDER",IF(AND(S23<>"",N(S23)>Settings!$B$5),"SLOW MOVER","OK")))))) -> OK | X23: =IF(OR(D23="End of range",U23=""),0,IF(N(U23)>0,U23+ROW()/1000000,0)) -> 0
A24: SAN018 | B24: SANTOS OCHRE/TUMERIC | C24: Hide | D24: Active | E24: =SUMIFS('CPT Count'!$D:$D,'CPT Count'!$A:$A,$A24)-SUMIFS('Weekly Sales'!$F:$F,'Weekly Sales'!$H:$H,$A24,'Weekly Sales'!$I:$I,"CPT")+SUMIFS(Transfers!$F:$F,Transfers!$C:$C,$A24,Transfers!$J:$J,"CPT")-SUMIFS(Transfers!$F:$F,Transfers!$C:$C,$A24,Transfers!$I:$I,"CPT",Transfers!$H:$H,"<>Y")+SUMIFS('Stock Received'!$I:$I,'Stock Received'!$E:$E,$A24,'Stock Received'!$L:$L,"CPT") -> 260 | F24: =SUMIFS('JHB Count'!$E:$E,'JHB Count'!$F:$F,$A24)-SUMIFS('Weekly Sales'!$F:$F,'Weekly Sales'!$H:$H,$A24,'Weekly Sales'!$I:$I,"JHB")+SUMIFS(Transfers!$F:$F,Transfers!$C:$C,$A24,Transfers!$J:$J,"JHB")-SUMIFS(Transfers!$F:$F,Transfers!$C:$C,$A24,Transfers!$I:$I,"JHB",Transfers!$H:$H,"<>Y")+SUMIFS('Stock Received'!$I:$I,'Stock Received'!$E:$E,$A24,'Stock Received'!$L:$L,"JHB") -> -0.01 | G24: =SUMIFS('DBN Count'!$D:$D,'DBN Count'!$E:$E,$A24)-SUMIFS('Weekly Sales'!$F:$F,'Weekly Sales'!$H:$H,$A24,'Weekly Sales'!$I:$I,"DBN")+SUMIFS(Transfers!$F:$F,Transfers!$C:$C,$A24,Transfers!$J:$J,"DBN")-SUMIFS(Transfers!$F:$F,Transfers!$C:$C,$A24,Transfers!$I:$I,"DBN",Transfers!$H:$H,"<>Y")+SUMIFS('Stock Received'!$I:$I,'Stock Received'!$E:$E,$A24,'Stock Received'!$L:$L,"DBN") -> 41.16 | H24: =E24+F24+G24 -> 301.15 | I24: =SUMIFS('Weekly Sales'!$F:$F,'Weekly Sales'!$H:$H,$A24) -> 33.01 | J24: =SUMIFS(Orders!$L:$L,Orders!$D:$D,$A24,Orders!$F:$F,">="&J$4,Orders!$F:$F,"<"&EDATE(J$4,1)) -> 0 | K24: =SUMIFS(Orders!$L:$L,Orders!$D:$D,$A24,Orders!$F:$F,">="&K$4,Orders!$F:$F,"<"&EDATE(K$4,1)) -> 0 | L24: =SUMIFS(Orders!$L:$L,Orders!$D:$D,$A24,Orders!$F:$F,">="&L$4,Orders!$F:$F,"<"&EDATE(L$4,1)) -> 0 | M24: =N24-J24-K24-L24 -> 0 | N24: =SUMIFS(Orders!$L:$L,Orders!$D:$D,$A24) -> 0 | O24: =H24+N24 -> 301.15 | P24: 55 | Q24: =IF(SUMIFS('Sales History'!$E:$E,'Sales History'!$G:$G,$A24)>0,SUMIFS('Sales History'!$E:$E,'Sales History'!$G:$G,$A24)/Settings!$B$4,N(P24)) -> 55 | R24: =IF(SUMIFS('Sales History'!$E:$E,'Sales History'!$G:$G,$A24)>0,"6-month history",IF(N(P24)>0,"Current sheet","No sales data")) -> Current sheet | S24: =IF(Q24>0,H24/Q24,"") -> 5.4754545 | T24: 200 | U24: =IF(T24="","",MAX(0,T24-O24)) -> 0 | V24: =IF(D24="End of range","END OF RANGE",IF(T24="","NO BUFFER SET",IF(H24<=0,IF(O24<T24,"OUT - REORDER","OUT - ON ORDER"),IF(O24<T24,"REORDER",IF(H24<T24,"LOW - ON ORDER",IF(AND(S24<>"",N(S24)>Settings!$B$5),"SLOW MOVER","OK")))))) -> OK | X24: =IF(OR(D24="End of range",U24=""),0,IF(N(U24)>0,U24+ROW()/1000000,0)) -> 0
A25: SAN019 | B25: SANTOS RUBY/SAFFRON | C25: Hide | D25: Active | E25: =SUMIFS('CPT Count'!$D:$D,'CPT Count'!$A:$A,$A25)-SUMIFS('Weekly Sales'!$F:$F,'Weekly Sales'!$H:$H,$A25,'Weekly Sales'!$I:$I,"CPT")+SUMIFS(Transfers!$F:$F,Transfers!$C:$C,$A25,Transfers!$J:$J,"CPT")-SUMIFS(Transfers!$F:$F,Transfers!$C:$C,$A25,Transfers!$I:$I,"CPT",Transfers!$H:$H,"<>Y")+SUMIFS('Stock Received'!$I:$I,'Stock Received'!$E:$E,$A25,'Stock Received'!$L:$L,"CPT") -> 420.55 | F25: =SUMIFS('JHB Count'!$E:$E,'JHB Count'!$F:$F,$A25)-SUMIFS('Weekly Sales'!$F:$F,'Weekly Sales'!$H:$H,$A25,'Weekly Sales'!$I:$I,"JHB")+SUMIFS(Transfers!$F:$F,Transfers!$C:$C,$A25,Transfers!$J:$J,"JHB")-SUMIFS(Transfers!$F:$F,Transfers!$C:$C,$A25,Transfers!$I:$I,"JHB",Transfers!$H:$H,"<>Y")+SUMIFS('Stock Received'!$I:$I,'Stock Received'!$E:$E,$A25,'Stock Received'!$L:$L,"JHB") -> 0 | G25: =SUMIFS('DBN Count'!$D:$D,'DBN Count'!$E:$E,$A25)-SUMIFS('Weekly Sales'!$F:$F,'Weekly Sales'!$H:$H,$A25,'Weekly Sales'!$I:$I,"DBN")+SUMIFS(Transfers!$F:$F,Transfers!$C:$C,$A25,Transfers!$J:$J,"DBN")-SUMIFS(Transfers!$F:$F,Transfers!$C:$C,$A25,Transfers!$I:$I,"DBN",Transfers!$H:$H,"<>Y")+SUMIFS('Stock Received'!$I:$I,'Stock Received'!$E:$E,$A25,'Stock Received'!$L:$L,"DBN") -> 30.96 | H25: =E25+F25+G25 -> 451.51 | I25: =SUMIFS('Weekly Sales'!$F:$F,'Weekly Sales'!$H:$H,$A25) -> 59.45 | J25: =SUMIFS(Orders!$L:$L,Orders!$D:$D,$A25,Orders!$F:$F,">="&J$4,Orders!$F:$F,"<"&EDATE(J$4,1)) -> 0 | K25: =SUMIFS(Orders!$L:$L,Orders!$D:$D,$A25,Orders!$F:$F,">="&K$4,Orders!$F:$F,"<"&EDATE(K$4,1)) -> 0 | L25: =SUMIFS(Orders!$L:$L,Orders!$D:$D,$A25,Orders!$F:$F,">="&L$4,Orders!$F:$F,"<"&EDATE(L$4,1)) -> 0 | M25: =N25-J25-K25-L25 -> 0 | N25: =SUMIFS(Orders!$L:$L,Orders!$D:$D,$A25) -> 0 | O25: =H25+N25 -> 451.51 | P25: 25 | Q25: =IF(SUMIFS('Sales History'!$E:$E,'Sales History'!$G:$G,$A25)>0,SUMIFS('Sales History'!$E:$E,'Sales History'!$G:$G,$A25)/Settings!$B$4,N(P25)) -> 25 | R25: =IF(SUMIFS('Sales History'!$E:$E,'Sales History'!$G:$G,$A25)>0,"6-month history",IF(N(P25)>0,"Current sheet","No sales data")) -> Current sheet | S25: =IF(Q25>0,H25/Q25,"") -> 18.0604 | T25: 200 | U25: =IF(T25="","",MAX(0,T25-O25)) -> 0 | V25: =IF(D25="End of range","END OF RANGE",IF(T25="","NO BUFFER SET",IF(H25<=0,IF(O25<T25,"OUT - REORDER","OUT - ON ORDER"),IF(O25<T25,"REORDER",IF(H25<T25,"LOW - ON ORDER",IF(AND(S25<>"",N(S25)>Settings!$B$5),"SLOW MOVER","OK")))))) -> SLOW MOVER | X25: =IF(OR(D25="End of range",U25=""),0,IF(N(U25)>0,U25+ROW()/1000000,0)) -> 0
A26: SAN012 | B26: SANTOS BLUE/AQUA | C26: Hide | D26: Active | E26: =SUMIFS('CPT Count'!$D:$D,'CPT Count'!$A:$A,$A26)-SUMIFS('Weekly Sales'!$F:$F,'Weekly Sales'!$H:$H,$A26,'Weekly Sales'!$I:$I,"CPT")+SUMIFS(Transfers!$F:$F,Transfers!$C:$C,$A26,Transfers!$J:$J,"CPT")-SUMIFS(Transfers!$F:$F,Transfers!$C:$C,$A26,Transfers!$I:$I,"CPT",Transfers!$H:$H,"<>Y")+SUMIFS('Stock Received'!$I:$I,'Stock Received'!$E:$E,$A26,'Stock Received'!$L:$L,"CPT") -> 380 | F26: =SUMIFS('JHB Count'!$E:$E,'JHB Count'!$F:$F,$A26)-SUMIFS('Weekly Sales'!$F:$F,'Weekly Sales'!$H:$H,$A26,'Weekly Sales'!$I:$I,"JHB")+SUMIFS(Transfers!$F:$F,Transfers!$C:$C,$A26,Transfers!$J:$J,"JHB")-SUMIFS(Transfers!$F:$F,Transfers!$C:$C,$A26,Transfers!$I:$I,"JHB",Transfers!$H:$H,"<>Y")+SUMIFS('Stock Received'!$I:$I,'Stock Received'!$E:$E,$A26,'Stock Received'!$L:$L,"JHB") -> 0 | G26: =SUMIFS('DBN Count'!$D:$D,'DBN Count'!$E:$E,$A26)-SUMIFS('Weekly Sales'!$F:$F,'Weekly Sales'!$H:$H,$A26,'Weekly Sales'!$I:$I,"DBN")+SUMIFS(Transfers!$F:$F,Transfers!$C:$C,$A26,Transfers!$J:$J,"DBN")-SUMIFS(Transfers!$F:$F,Transfers!$C:$C,$A26,Transfers!$I:$I,"DBN",Transfers!$H:$H,"<>Y")+SUMIFS('Stock Received'!$I:$I,'Stock Received'!$E:$E,$A26,'Stock Received'!$L:$L,"DBN") -> 53.68 | H26: =E26+F26+G26 -> 433.68 | I26: =SUMIFS('Weekly Sales'!$F:$F,'Weekly Sales'!$H:$H,$A26) -> 0 | J26: =SUMIFS(Orders!$L:$L,Orders!$D:$D,$A26,Orders!$F:$F,">="&J$4,Orders!$F:$F,"<"&EDATE(J$4,1)) -> 0 | K26: =SUMIFS(Orders!$L:$L,Orders!$D:$D,$A26,Orders!$F:$F,">="&K$4,Orders!$F:$F,"<"&EDATE(K$4,1)) -> 0 | L26: =SUMIFS(Orders!$L:$L,Orders!$D:$D,$A26,Orders!$F:$F,">="&L$4,Orders!$F:$F,"<"&EDATE(L$4,1)) -> 0 | M26: =N26-J26-K26-L26 -> 0 | N26: =SUMIFS(Orders!$L:$L,Orders!$D:$D,$A26) -> 0 | O26: =H26+N26 -> 433.68 | P26: 30 | Q26: =IF(SUMIFS('Sales History'!$E:$E,'Sales History'!$G:$G,$A26)>0,SUMIFS('Sales History'!$E:$E,'Sales History'!$G:$G,$A26)/Settings!$B$4,N(P26)) -> 30 | R26: =IF(SUMIFS('Sales History'!$E:$E,'Sales History'!$G:$G,$A26)>0,"6-month history",IF(N(P26)>0,"Current sheet","No sales data")) -> Current sheet | S26: =IF(Q26>0,H26/Q26,"") -> 14.456 | T26: 200 | U26: =IF(T26="","",MAX(0,T26-O26)) -> 0 | V26: =IF(D26="End of range","END OF RANGE",IF(T26="","NO BUFFER SET",IF(H26<=0,IF(O26<T26,"OUT - REORDER","OUT - ON ORDER"),IF(O26<T26,"REORDER",IF(H26<T26,"LOW - ON ORDER",IF(AND(S26<>"",N(S26)>Settings!$B$5),"SLOW MOVER","OK")))))) -> SLOW MOVER | X26: =IF(OR(D26="End of range",U26=""),0,IF(N(U26)>0,U26+ROW()/1000000,0)) -> 0
A27: SAN013 | B27: SANTOS GREEN/BASIL | C27: Hide | D27: Active | E27: =SUMIFS('CPT Count'!$D:$D,'CPT Count'!$A:$A,$A27)-SUMIFS('Weekly Sales'!$F:$F,'Weekly Sales'!$H:$H,$A27,'Weekly Sales'!$I:$I,"CPT")+SUMIFS(Transfers!$F:$F,Transfers!$C:$C,$A27,Transfers!$J:$J,"CPT")-SUMIFS(Transfers!$F:$F,Transfers!$C:$C,$A27,Transfers!$I:$I,"CPT",Transfers!$H:$H,"<>Y")+SUMIFS('Stock Received'!$I:$I,'Stock Received'!$E:$E,$A27,'Stock Received'!$L:$L,"CPT") -> 172 | F27: =SUMIFS('JHB Count'!$E:$E,'JHB Count'!$F:$F,$A27)-SUMIFS('Weekly Sales'!$F:$F,'Weekly Sales'!$H:$H,$A27,'Weekly Sales'!$I:$I,"JHB")+SUMIFS(Transfers!$F:$F,Transfers!$C:$C,$A27,Transfers!$J:$J,"JHB")-SUMIFS(Transfers!$F:$F,Transfers!$C:$C,$A27,Transfers!$I:$I,"JHB",Transfers!$H:$H,"<>Y")+SUMIFS('Stock Received'!$I:$I,'Stock Received'!$E:$E,$A27,'Stock Received'!$L:$L,"JHB") -> 0 | G27: =SUMIFS('DBN Count'!$D:$D,'DBN Count'!$E:$E,$A27)-SUMIFS('Weekly Sales'!$F:$F,'Weekly Sales'!$H:$H,$A27,'Weekly Sales'!$I:$I,"DBN")+SUMIFS(Transfers!$F:$F,Transfers!$C:$C,$A27,Transfers!$J:$J,"DBN")-SUMIFS(Transfers!$F:$F,Transfers!$C:$C,$A27,Transfers!$I:$I,"DBN",Transfers!$H:$H,"<>Y")+SUMIFS('Stock Received'!$I:$I,'Stock Received'!$E:$E,$A27,'Stock Received'!$L:$L,"DBN") -> 42.63 | H27: =E27+F27+G27 -> 214.63 | I27: =SUMIFS('Weekly Sales'!$F:$F,'Weekly Sales'!$H:$H,$A27) -> 0 | J27: =SUMIFS(Orders!$L:$L,Orders!$D:$D,$A27,Orders!$F:$F,">="&J$4,Orders!$F:$F,"<"&EDATE(J$4,1)) -> 0 | K27: =SUMIFS(Orders!$L:$L,Orders!$D:$D,$A27,Orders!$F:$F,">="&K$4,Orders!$F:$F,"<"&EDATE(K$4,1)) -> 0 | L27: =SUMIFS(Orders!$L:$L,Orders!$D:$D,$A27,Orders!$F:$F,">="&L$4,Orders!$F:$F,"<"&EDATE(L$4,1)) -> 200 | M27: =N27-J27-K27-L27 -> 0 | N27: =SUMIFS(Orders!$L:$L,Orders!$D:$D,$A27) -> 200 | O27: =H27+N27 -> 414.63 | P27: 70 | Q27: =IF(SUMIFS('Sales History'!$E:$E,'Sales History'!$G:$G,$A27)>0,SUMIFS('Sales History'!$E:$E,'Sales History'!$G:$G,$A27)/Settings!$B$4,N(P27)) -> 70 | R27: =IF(SUMIFS('Sales History'!$E:$E,'Sales History'!$G:$G,$A27)>0,"6-month history",IF(N(P27)>0,"Current sheet","No sales data")) -> Current sheet | S27: =IF(Q27>0,H27/Q27,"") -> 3.0661429 | T27: 200 | U27: =IF(T27="","",MAX(0,T27-O27)) -> 0 | V27: =IF(D27="End of range","END OF RANGE",IF(T27="","NO BUFFER SET",IF(H27<=0,IF(O27<T27,"OUT - REORDER","OUT - ON ORDER"),IF(O27<T27,"REORDER",IF(H27<T27,"LOW - ON ORDER",IF(AND(S27<>"",N(S27)>Settings!$B$5),"SLOW MOVER","OK")))))) -> OK | X27: =IF(OR(D27="End of range",U27=""),0,IF(N(U27)>0,U27+ROW()/1000000,0)) -> 0
A28: SAN014 | B28: SANTOS GREY/STEEL | C28: Hide | D28: Active | E28: =SUMIFS('CPT Count'!$D:$D,'CPT Count'!$A:$A,$A28)-SUMIFS('Weekly Sales'!$F:$F,'Weekly Sales'!$H:$H,$A28,'Weekly Sales'!$I:$I,"CPT")+SUMIFS(Transfers!$F:$F,Transfers!$C:$C,$A28,Transfers!$J:$J,"CPT")-SUMIFS(Transfers!$F:$F,Transfers!$C:$C,$A28,Transfers!$I:$I,"CPT",Transfers!$H:$H,"<>Y")+SUMIFS('Stock Received'!$I:$I,'Stock Received'!$E:$E,$A28,'Stock Received'!$L:$L,"CPT") -> 431.02 | F28: =SUMIFS('JHB Count'!$E:$E,'JHB Count'!$F:$F,$A28)-SUMIFS('Weekly Sales'!$F:$F,'Weekly Sales'!$H:$H,$A28,'Weekly Sales'!$I:$I,"JHB")+SUMIFS(Transfers!$F:$F,Transfers!$C:$C,$A28,Transfers!$J:$J,"JHB")-SUMIFS(Transfers!$F:$F,Transfers!$C:$C,$A28,Transfers!$I:$I,"JHB",Transfers!$H:$H,"<>Y")+SUMIFS('Stock Received'!$I:$I,'Stock Received'!$E:$E,$A28,'Stock Received'!$L:$L,"JHB") -> 0 | G28: =SUMIFS('DBN Count'!$D:$D,'DBN Count'!$E:$E,$A28)-SUMIFS('Weekly Sales'!$F:$F,'Weekly Sales'!$H:$H,$A28,'Weekly Sales'!$I:$I,"DBN")+SUMIFS(Transfers!$F:$F,Transfers!$C:$C,$A28,Transfers!$J:$J,"DBN")-SUMIFS(Transfers!$F:$F,Transfers!$C:$C,$A28,Transfers!$I:$I,"DBN",Transfers!$H:$H,"<>Y")+SUMIFS('Stock Received'!$I:$I,'Stock Received'!$E:$E,$A28,'Stock Received'!$L:$L,"DBN") -> 26.3 | H28: =E28+F28+G28 -> 457.32 | I28: =SUMIFS('Weekly Sales'!$F:$F,'Weekly Sales'!$H:$H,$A28) -> 0 | J28: =SUMIFS(Orders!$L:$L,Orders!$D:$D,$A28,Orders!$F:$F,">="&J$4,Orders!$F:$F,"<"&EDATE(J$4,1)) -> 0 | K28: =SUMIFS(Orders!$L:$L,Orders!$D:$D,$A28,Orders!$F:$F,">="&K$4,Orders!$F:$F,"<"&EDATE(K$4,1)) -> 0 | L28: =SUMIFS(Orders!$L:$L,Orders!$D:$D,$A28,Orders!$F:$F,">="&L$4,Orders!$F:$F,"<"&EDATE(L$4,1)) -> 0 | M28: =N28-J28-K28-L28 -> 0 | N28: =SUMIFS(Orders!$L:$L,Orders!$D:$D,$A28) -> 0 | O28: =H28+N28 -> 457.32 | P28: 60 | Q28: =IF(SUMIFS('Sales History'!$E:$E,'Sales History'!$G:$G,$A28)>0,SUMIFS('Sales History'!$E:$E,'Sales History'!$G:$G,$A28)/Settings!$B$4,N(P28)) -> 60 | R28: =IF(SUMIFS('Sales History'!$E:$E,'Sales History'!$G:$G,$A28)>0,"6-month history",IF(N(P28)>0,"Current sheet","No sales data")) -> Current sheet | S28: =IF(Q28>0,H28/Q28,"") -> 7.622 | T28: 200 | U28: =IF(T28="","",MAX(0,T28-O28)) -> 0 | V28: =IF(D28="End of range","END OF RANGE",IF(T28="","NO BUFFER SET",IF(H28<=0,IF(O28<T28,"OUT - REORDER","OUT - ON ORDER"),IF(O28<T28,"REORDER",IF(H28<T28,"LOW - ON ORDER",IF(AND(S28<>"",N(S28)>Settings!$B$5),"SLOW MOVER","OK")))))) -> OK | X28: =IF(OR(D28="End of range",U28=""),0,IF(N(U28)>0,U28+ROW()/1000000,0)) -> 0
A29: SAN015 | B29: SANTOS OXBLOOD/COFFEE | C29: Hide | D29: Active | E29: =SUMIFS('CPT Count'!$D:$D,'CPT Count'!$A:$A,$A29)-SUMIFS('Weekly Sales'!$F:$F,'Weekly Sales'!$H:$H,$A29,'Weekly Sales'!$I:$I,"CPT")+SUMIFS(Transfers!$F:$F,Transfers!$C:$C,$A29,Transfers!$J:$J,"CPT")-SUMIFS(Transfers!$F:$F,Transfers!$C:$C,$A29,Transfers!$I:$I,"CPT",Transfers!$H:$H,"<>Y")+SUMIFS('Stock Received'!$I:$I,'Stock Received'!$E:$E,$A29,'Stock Received'!$L:$L,"CPT") -> 360 | F29: =SUMIFS('JHB Count'!$E:$E,'JHB Count'!$F:$F,$A29)-SUMIFS('Weekly Sales'!$F:$F,'Weekly Sales'!$H:$H,$A29,'Weekly Sales'!$I:$I,"JHB")+SUMIFS(Transfers!$F:$F,Transfers!$C:$C,$A29,Transfers!$J:$J,"JHB")-SUMIFS(Transfers!$F:$F,Transfers!$C:$C,$A29,Transfers!$I:$I,"JHB",Transfers!$H:$H,"<>Y")+SUMIFS('Stock Received'!$I:$I,'Stock Received'!$E:$E,$A29,'Stock Received'!$L:$L,"JHB") -> 0 | G29: =SUMIFS('DBN Count'!$D:$D,'DBN Count'!$E:$E,$A29)-SUMIFS('Weekly Sales'!$F:$F,'Weekly Sales'!$H:$H,$A29,'Weekly Sales'!$I:$I,"DBN")+SUMIFS(Transfers!$F:$F,Transfers!$C:$C,$A29,Transfers!$J:$J,"DBN")-SUMIFS(Transfers!$F:$F,Transfers!$C:$C,$A29,Transfers!$I:$I,"DBN",Transfers!$H:$H,"<>Y")+SUMIFS('Stock Received'!$I:$I,'Stock Received'!$E:$E,$A29,'Stock Received'!$L:$L,"DBN") -> 38.67 | H29: =E29+F29+G29 -> 398.67 | I29: =SUMIFS('Weekly Sales'!$F:$F,'Weekly Sales'!$H:$H,$A29) -> 0 | J29: =SUMIFS(Orders!$L:$L,Orders!$D:$D,$A29,Orders!$F:$F,">="&J$4,Orders!$F:$F,"<"&EDATE(J$4,1)) -> 0 | K29: =SUMIFS(Orders!$L:$L,Orders!$D:$D,$A29,Orders!$F:$F,">="&K$4,Orders!$F:$F,"<"&EDATE(K$4,1)) -> 0 | L29: =SUMIFS(Orders!$L:$L,Orders!$D:$D,$A29,Orders!$F:$F,">="&L$4,Orders!$F:$F,"<"&EDATE(L$4,1)) -> 0 | M29: =N29-J29-K29-L29 -> 0 | N29: =SUMIFS(Orders!$L:$L,Orders!$D:$D,$A29) -> 0 | O29: =H29+N29 -> 398.67 | P29: 30 | Q29: =IF(SUMIFS('Sales History'!$E:$E,'Sales History'!$G:$G,$A29)>0,SUMIFS('Sales History'!$E:$E,'Sales History'!$G:$G,$A29)/Settings!$B$4,N(P29)) -> 30 | R29: =IF(SUMIFS('Sales History'!$E:$E,'Sales History'!$G:$G,$A29)>0,"6-month history",IF(N(P29)>0,"Current sheet","No sales data")) -> Current sheet | S29: =IF(Q29>0,H29/Q29,"") -> 13.289 | T29: 200 | U29: =IF(T29="","",MAX(0,T29-O29)) -> 0 | V29: =IF(D29="End of range","END OF RANGE",IF(T29="","NO BUFFER SET",IF(H29<=0,IF(O29<T29,"OUT - REORDER","OUT - ON ORDER"),IF(O29<T29,"REORDER",IF(H29<T29,"LOW - ON ORDER",IF(AND(S29<>"",N(S29)>Settings!$B$5),"SLOW MOVER","OK")))))) -> SLOW MOVER | X29: =IF(OR(D29="End of range",U29=""),0,IF(N(U29)>0,U29+ROW()/1000000,0)) -> 0
A30: SAN002 | B30: SANTOS BLACK | C30: Hide | D30: Active | E30: =SUMIFS('CPT Count'!$D:$D,'CPT Count'!$A:$A,$A30)-SUMIFS('Weekly Sales'!$F:$F,'Weekly Sales'!$H:$H,$A30,'Weekly Sales'!$I:$I,"CPT")+SUMIFS(Transfers!$F:$F,Transfers!$C:$C,$A30,Transfers!$J:$J,"CPT")-SUMIFS(Transfers!$F:$F,Transfers!$C:$C,$A30,Transfers!$I:$I,"CPT",Transfers!$H:$H,"<>Y")+SUMIFS('Stock Received'!$I:$I,'Stock Received'!$E:$E,$A30,'Stock Received'!$L:$L,"CPT") -> 1176.04 | F30: =SUMIFS('JHB Count'!$E:$E,'JHB Count'!$F:$F,$A30)-SUMIFS('Weekly Sales'!$F:$F,'Weekly Sales'!$H:$H,$A30,'Weekly Sales'!$I:$I,"JHB")+SUMIFS(Transfers!$F:$F,Transfers!$C:$C,$A30,Transfers!$J:$J,"JHB")-SUMIFS(Transfers!$F:$F,Transfers!$C:$C,$A30,Transfers!$I:$I,"JHB",Transfers!$H:$H,"<>Y")+SUMIFS('Stock Received'!$I:$I,'Stock Received'!$E:$E,$A30,'Stock Received'!$L:$L,"JHB") -> 0 | G30: =SUMIFS('DBN Count'!$D:$D,'DBN Count'!$E:$E,$A30)-SUMIFS('Weekly Sales'!$F:$F,'Weekly Sales'!$H:$H,$A30,'Weekly Sales'!$I:$I,"DBN")+SUMIFS(Transfers!$F:$F,Transfers!$C:$C,$A30,Transfers!$J:$J,"DBN")-SUMIFS(Transfers!$F:$F,Transfers!$C:$C,$A30,Transfers!$I:$I,"DBN",Transfers!$H:$H,"<>Y")+SUMIFS('Stock Received'!$I:$I,'Stock Received'!$E:$E,$A30,'Stock Received'!$L:$L,"DBN") -> 20.19 | H30: =E30+F30+G30 -> 1196.23 | I30: =SUMIFS('Weekly Sales'!$F:$F,'Weekly Sales'!$H:$H,$A30) -> 3.96 | J30: =SUMIFS(Orders!$L:$L,Orders!$D:$D,$A30,Orders!$F:$F,">="&J$4,Orders!$F:$F,"<"&EDATE(J$4,1)) -> 0 | K30: =SUMIFS(Orders!$L:$L,Orders!$D:$D,$A30,Orders!$F:$F,">="&K$4,Orders!$F:$F,"<"&EDATE(K$4,1)) -> 0 | L30: =SUMIFS(Orders!$L:$L,Orders!$D:$D,$A30,Orders!$F:$F,">="&L$4,Orders!$F:$F,"<"&EDATE(L$4,1)) -> 0 | M30: =N30-J30-K30-L30 -> 0 | N30: =SUMIFS(Orders!$L:$L,Orders!$D:$D,$A30) -> 0 | O30: =H30+N30 -> 1196.23 | P30: 120 | Q30: =IF(SUMIFS('Sales History'!$E:$E,'Sales History'!$G:$G,$A30)>0,SUMIFS('Sales History'!$E:$E,'Sales History'!$G:$G,$A30)/Settings!$B$4,N(P30)) -> 120 | R30: =IF(SUMIFS('Sales History'!$E:$E,'Sales History'!$G:$G,$A30)>0,"6-month history",IF(N(P30)>0,"Current sheet","No sales data")) -> Current sheet | S30: =IF(Q30>0,H30/Q30,"") -> 9.9685833 | T30: 300 | U30: =IF(T30="","",MAX(0,T30-O30)) -> 0 | V30: =IF(D30="End of range","END OF RANGE",IF(T30="","NO BUFFER SET",IF(H30<=0,IF(O30<T30,"OUT - REORDER","OUT - ON ORDER"),IF(O30<T30,"REORDER",IF(H30<T30,"LOW - ON ORDER",IF(AND(S30<>"",N(S30)>Settings!$B$5),"SLOW MOVER","OK")))))) -> OK | X30: =IF(OR(D30="End of range",U30=""),0,IF(N(U30)>0,U30+ROW()/1000000,0)) -> 0
A31: SAN011 | B31: SANTOS SPICE/CIGAR | C31: Hide | D31: Active | E31: =SUMIFS('CPT Count'!$D:$D,'CPT Count'!$A:$A,$A31)-SUMIFS('Weekly Sales'!$F:$F,'Weekly Sales'!$H:$H,$A31,'Weekly Sales'!$I:$I,"CPT")+SUMIFS(Transfers!$F:$F,Transfers!$C:$C,$A31,Transfers!$J:$J,"CPT")-SUMIFS(Transfers!$F:$F,Transfers!$C:$C,$A31,Transfers!$I:$I,"CPT",Transfers!$H:$H,"<>Y")+SUMIFS('Stock Received'!$I:$I,'Stock Received'!$E:$E,$A31,'Stock Received'!$L:$L,"CPT") -> 356.97 | F31: =SUMIFS('JHB Count'!$E:$E,'JHB Count'!$F:$F,$A31)-SUMIFS('Weekly Sales'!$F:$F,'Weekly Sales'!$H:$H,$A31,'Weekly Sales'!$I:$I,"JHB")+SUMIFS(Transfers!$F:$F,Transfers!$C:$C,$A31,Transfers!$J:$J,"JHB")-SUMIFS(Transfers!$F:$F,Transfers!$C:$C,$A31,Transfers!$I:$I,"JHB",Transfers!$H:$H,"<>Y")+SUMIFS('Stock Received'!$I:$I,'Stock Received'!$E:$E,$A31,'Stock Received'!$L:$L,"JHB") -> 0.02 | G31: =SUMIFS('DBN Count'!$D:$D,'DBN Count'!$E:$E,$A31)-SUMIFS('Weekly Sales'!$F:$F,'Weekly Sales'!$H:$H,$A31,'Weekly Sales'!$I:$I,"DBN")+SUMIFS(Transfers!$F:$F,Transfers!$C:$C,$A31,Transfers!$J:$J,"DBN")-SUMIFS(Transfers!$F:$F,Transfers!$C:$C,$A31,Transfers!$I:$I,"DBN",Transfers!$H:$H,"<>Y")+SUMIFS('Stock Received'!$I:$I,'Stock Received'!$E:$E,$A31,'Stock Received'!$L:$L,"DBN") -> 29.66 | H31: =E31+F31+G31 -> 386.65 | I31: =SUMIFS('Weekly Sales'!$F:$F,'Weekly Sales'!$H:$H,$A31) -> 26.48 | J31: =SUMIFS(Orders!$L:$L,Orders!$D:$D,$A31,Orders!$F:$F,">="&J$4,Orders!$F:$F,"<"&EDATE(J$4,1)) -> 0 | K31: =SUMIFS(Orders!$L:$L,Orders!$D:$D,$A31,Orders!$F:$F,">="&K$4,Orders!$F:$F,"<"&EDATE(K$4,1)) -> 0 | L31: =SUMIFS(Orders!$L:$L,Orders!$D:$D,$A31,Orders!$F:$F,">="&L$4,Orders!$F:$F,"<"&EDATE(L$4,1)) -> 0 | M31: =N31-J31-K31-L31 -> 0 | N31: =SUMIFS(Orders!$L:$L,Orders!$D:$D,$A31) -> 0 | O31: =H31+N31 -> 386.65 | P31: 40 | Q31: =IF(SUMIFS('Sales History'!$E:$E,'Sales History'!$G:$G,$A31)>0,SUMIFS('Sales History'!$E:$E,'Sales History'!$G:$G,$A31)/Settings!$B$4,N(P31)) -> 40 | R31: =IF(SUMIFS('Sales History'!$E:$E,'Sales History'!$G:$G,$A31)>0,"6-month history",IF(N(P31)>0,"Current sheet","No sales data")) -> Current sheet | S31: =IF(Q31>0,H31/Q31,"") -> 9.66625 | T31: 200 | U31: =IF(T31="","",MAX(0,T31-O31)) -> 0 | V31: =IF(D31="End of range","END OF RANGE",IF(T31="","NO BUFFER SET",IF(H31<=0,IF(O31<T31,"OUT - REORDER","OUT - ON ORDER"),IF(O31<T31,"REORDER",IF(H31<T31,"LOW - ON ORDER",IF(AND(S31<>"",N(S31)>Settings!$B$5),"SLOW MOVER","OK")))))) -> OK | X31: =IF(OR(D31="End of range",U31=""),0,IF(N(U31)>0,U31+ROW()/1000000,0)) -> 0
A32: PUL010 | B32: CLASSIC MUSTARD | C32: Hide | D32: Active | E32: =SUMIFS('CPT Count'!$D:$D,'CPT Count'!$A:$A,$A32)-SUMIFS('Weekly Sales'!$F:$F,'Weekly Sales'!$H:$H,$A32,'Weekly Sales'!$I:$I,"CPT")+SUMIFS(Transfers!$F:$F,Transfers!$C:$C,$A32,Transfers!$J:$J,"CPT")-SUMIFS(Transfers!$F:$F,Transfers!$C:$C,$A32,Transfers!$I:$I,"CPT",Transfers!$H:$H,"<>Y")+SUMIFS('Stock Received'!$I:$I,'Stock Received'!$E:$E,$A32,'Stock Received'!$L:$L,"CPT") -> 120 | F32: =SUMIFS('JHB Count'!$E:$E,'JHB Count'!$F:$F,$A32)-SUMIFS('Weekly Sales'!$F:$F,'Weekly Sales'!$H:$H,$A32,'Weekly Sales'!$I:$I,"JHB")+SUMIFS(Transfers!$F:$F,Transfers!$C:$C,$A32,Transfers!$J:$J,"JHB")-SUMIFS(Transfers!$F:$F,Transfers!$C:$C,$A32,Transfers!$I:$I,"JHB",Transfers!$H:$H,"<>Y")+SUMIFS('Stock Received'!$I:$I,'Stock Received'!$E:$E,$A32,'Stock Received'!$L:$L,"JHB") -> 68 | G32: =SUMIFS('DBN Count'!$D:$D,'DBN Count'!$E:$E,$A32)-SUMIFS('Weekly Sales'!$F:$F,'Weekly Sales'!$H:$H,$A32,'Weekly Sales'!$I:$I,"DBN")+SUMIFS(Transfers!$F:$F,Transfers!$C:$C,$A32,Transfers!$J:$J,"DBN")-SUMIFS(Transfers!$F:$F,Transfers!$C:$C,$A32,Transfers!$I:$I,"DBN",Transfers!$H:$H,"<>Y")+SUMIFS('Stock Received'!$I:$I,'Stock Received'!$E:$E,$A32,'Stock Received'!$L:$L,"DBN") -> 30.25 | H32: =E32+F32+G32 -> 218.25 | I32: =SUMIFS('Weekly Sales'!$F:$F,'Weekly Sales'!$H:$H,$A32) -> 0 | J32: =SUMIFS(Orders!$L:$L,Orders!$D:$D,$A32,Orders!$F:$F,">="&J$4,Orders!$F:$F,"<"&EDATE(J$4,1)) -> 300 | K32: =SUMIFS(Orders!$L:$L,Orders!$D:$D,$A32,Orders!$F:$F,">="&K$4,Orders!$F:$F,"<"&EDATE(K$4,1)) -> 300 | L32: =SUMIFS(Orders!$L:$L,Orders!$D:$D,$A32,Orders!$F:$F,">="&L$4,Orders!$F:$F,"<"&EDATE(L$4,1)) -> 0 | M32: =N32-J32-K32-L32 -> 0 | N32: =SUMIFS(Orders!$L:$L,Orders!$D:$D,$A32) -> 600 | O32: =H32+N32 -> 818.25 | P32: 110 | Q32: =IF(SUMIFS('Sales History'!$E:$E,'Sales History'!$G:$G,$A32)>0,SUMIFS('Sales History'!$E:$E,'Sales History'!$G:$G,$A32)/Settings!$B$4,N(P32)) -> 110 | R32: =IF(SUMIFS('Sales History'!$E:$E,'Sales History'!$G:$G,$A32)>0,"6-month history",IF(N(P32)>0,"Current sheet","No sales data")) -> Current sheet | S32: =IF(Q32>0,H32/Q32,"") -> 1.9840909 | T32: 300 | U32: =IF(T32="","",MAX(0,T32-O32)) -> 0 | V32: =IF(D32="End of range","END OF RANGE",IF(T32="","NO BUFFER SET",IF(H32<=0,IF(O32<T32,"OUT - REORDER","OUT - ON ORDER"),IF(O32<T32,"REORDER",IF(H32<T32,"LOW - ON ORDER",IF(AND(S32<>"",N(S32)>Settings!$B$5),"SLOW MOVER","OK")))))) -> LOW - ON ORDER | X32: =IF(OR(D32="End of range",U32=""),0,IF(N(U32)>0,U32+ROW()/1000000,0)) -> 0
... A43: NOV006 | B43: NOVA TOBACCO | C43: Hide | D43: Active | E43: =SUMIFS('CPT Count'!$D:$D,'CPT Count'!$A:$A,$A43)-SUMIFS('Weekly Sales'!$F:$F,'Weekly Sales'!$H:$H,$A43,'Weekly Sales'!$I:$I,"CPT")+SUMIFS(Transfers!$F:$F,Transfers!$C:$C,$A43,Transfers!$J:$J,"CPT")-SUMIFS(Transfers!$F:$F,Transfers!$C:$C,$A43,Transfers!$I:$I,"CPT",Transfers!$H:$H,"<>Y")+SUMIFS('Stock Received'!$I:$I,'Stock Received'!$E:$E,$A43,'Stock Received'!$L:$L,"CPT") -> 203.9 | F43: =SUMIFS('JHB Count'!$E:$E,'JHB Count'!$F:$F,$A43)-SUMIFS('Weekly Sales'!$F:$F,'Weekly Sales'!$H:$H,$A43,'Weekly Sales'!$I:$I,"JHB")+SUMIFS(Transfers!$F:$F,Transfers!$C:$C,$A43,Transfers!$J:$J,"JHB")-SUMIFS(Transfers!$F:$F,Transfers!$C:$C,$A43,Transfers!$I:$I,"JHB",Transfers!$H:$H,"<>Y")+SUMIFS('Stock Received'!$I:$I,'Stock Received'!$E:$E,$A43,'Stock Received'!$L:$L,"JHB") -> 56.04 | G43: =SUMIFS('DBN Count'!$D:$D,'DBN Count'!$E:$E,$A43)-SUMIFS('Weekly Sales'!$F:$F,'Weekly Sales'!$H:$H,$A43,'Weekly Sales'!$I:$I,"DBN")+SUMIFS(Transfers!$F:$F,Transfers!$C:$C,$A43,Transfers!$J:$J,"DBN")-SUMIFS(Transfers!$F:$F,Transfers!$C:$C,$A43,Transfers!$I:$I,"DBN",Transfers!$H:$H,"<>Y")+SUMIFS('Stock Received'!$I:$I,'Stock Received'!$E:$E,$A43,'Stock Received'!$L:$L,"DBN") -> 23.95 | H43: =E43+F43+G43 -> 283.89 | I43: =SUMIFS('Weekly Sales'!$F:$F,'Weekly Sales'!$H:$H,$A43) -> 8.06 | J43: =SUMIFS(Orders!$L:$L,Orders!$D:$D,$A43,Orders!$F:$F,">="&J$4,Orders!$F:$F,"<"&EDATE(J$4,1)) -> 0 | K43: =SUMIFS(Orders!$L:$L,Orders!$D:$D,$A43,Orders!$F:$F,">="&K$4,Orders!$F:$F,"<"&EDATE(K$4,1)) -> 0 | L43: =SUMIFS(Orders!$L:$L,Orders!$D:$D,$A43,Orders!$F:$F,">="&L$4,Orders!$F:$F,"<"&EDATE(L$4,1)) -> 0 | M43: =N43-J43-K43-L43 -> 0 | N43: =SUMIFS(Orders!$L:$L,Orders!$D:$D,$A43) -> 0 | O43: =H43+N43 -> 283.89 | P43: 30 | Q43: =IF(SUMIFS('Sales History'!$E:$E,'Sales History'!$G:$G,$A43)>0,SUMIFS('Sales History'!$E:$E,'Sales History'!$G:$G,$A43)/Settings!$B$4,N(P43)) -> 30 | R43: =IF(SUMIFS('Sales History'!$E:$E,'Sales History'!$G:$G,$A43)>0,"6-month history",IF(N(P43)>0,"Current sheet","No sales data")) -> Current sheet | S43: =IF(Q43>0,H43/Q43,"") -> 9.463 | T43: 200 | U43: =IF(T43="","",MAX(0,T43-O43)) -> 0 | V43: =IF(D43="End of range","END OF RANGE",IF(T43="","NO BUFFER SET",IF(H43<=0,IF(O43<T43,"OUT - REORDER","OUT - ON ORDER"),IF(O43<T43,"REORDER",IF(H43<T43,"LOW - ON ORDER",IF(AND(S43<>"",N(S43)>Settings!$B$5),"SLOW MOVER","OK")))))) -> OK | X43: =IF(OR(D43="End of range",U43=""),0,IF(N(U43)>0,U43+ROW()/1000000,0)) -> 0
A44: AVI001 | B44: AVIATOR WARRIOR | C44: Hide | D44: Active | E44: =SUMIFS('CPT Count'!$D:$D,'CPT Count'!$A:$A,$A44)-SUMIFS('Weekly Sales'!$F:$F,'Weekly Sales'!$H:$H,$A44,'Weekly Sales'!$I:$I,"CPT")+SUMIFS(Transfers!$F:$F,Transfers!$C:$C,$A44,Transfers!$J:$J,"CPT")-SUMIFS(Transfers!$F:$F,Transfers!$C:$C,$A44,Transfers!$I:$I,"CPT",Transfers!$H:$H,"<>Y")+SUMIFS('Stock Received'!$I:$I,'Stock Received'!$E:$E,$A44,'Stock Received'!$L:$L,"CPT") -> 8 | F44: =SUMIFS('JHB Count'!$E:$E,'JHB Count'!$F:$F,$A44)-SUMIFS('Weekly Sales'!$F:$F,'Weekly Sales'!$H:$H,$A44,'Weekly Sales'!$I:$I,"JHB")+SUMIFS(Transfers!$F:$F,Transfers!$C:$C,$A44,Transfers!$J:$J,"JHB")-SUMIFS(Transfers!$F:$F,Transfers!$C:$C,$A44,Transfers!$I:$I,"JHB",Transfers!$H:$H,"<>Y")+SUMIFS('Stock Received'!$I:$I,'Stock Received'!$E:$E,$A44,'Stock Received'!$L:$L,"JHB") -> 116.54 | G44: =SUMIFS('DBN Count'!$D:$D,'DBN Count'!$E:$E,$A44)-SUMIFS('Weekly Sales'!$F:$F,'Weekly Sales'!$H:$H,$A44,'Weekly Sales'!$I:$I,"DBN")+SUMIFS(Transfers!$F:$F,Transfers!$C:$C,$A44,Transfers!$J:$J,"DBN")-SUMIFS(Transfers!$F:$F,Transfers!$C:$C,$A44,Transfers!$I:$I,"DBN",Transfers!$H:$H,"<>Y")+SUMIFS('Stock Received'!$I:$I,'Stock Received'!$E:$E,$A44,'Stock Received'!$L:$L,"DBN") -> 0 | H44: =E44+F44+G44 -> 124.54 | I44: =SUMIFS('Weekly Sales'!$F:$F,'Weekly Sales'!$H:$H,$A44) -> 3.46 | J44: =SUMIFS(Orders!$L:$L,Orders!$D:$D,$A44,Orders!$F:$F,">="&J$4,Orders!$F:$F,"<"&EDATE(J$4,1)) -> 300 | K44: =SUMIFS(Orders!$L:$L,Orders!$D:$D,$A44,Orders!$F:$F,">="&K$4,Orders!$F:$F,"<"&EDATE(K$4,1)) -> 0 | L44: =SUMIFS(Orders!$L:$L,Orders!$D:$D,$A44,Orders!$F:$F,">="&L$4,Orders!$F:$F,"<"&EDATE(L$4,1)) -> 0 | M44: =N44-J44-K44-L44 -> 0 | N44: =SUMIFS(Orders!$L:$L,Orders!$D:$D,$A44) -> 300 | O44: =H44+N44 -> 424.54 | Q44: =IF(SUMIFS('Sales History'!$E:$E,'Sales History'!$G:$G,$A44)>0,SUMIFS('Sales History'!$E:$E,'Sales History'!$G:$G,$A44)/Settings!$B$4,N(P44)) -> 0 | R44: =IF(SUMIFS('Sales History'!$E:$E,'Sales History'!$G:$G,$A44)>0,"6-month history",IF(N(P44)>0,"Current sheet","No sales data")) -> No sales data | S44: =IF(Q44>0,H44/Q44,"") | T44: 100 | U44: =IF(T44="","",MAX(0,T44-O44)) -> 0 | V44: =IF(D44="End of range","END OF RANGE",IF(T44="","NO BUFFER SET",IF(H44<=0,IF(O44<T44,"OUT - REORDER","OUT - ON ORDER"),IF(O44<T44,"REORDER",IF(H44<T44,"LOW - ON ORDER",IF(AND(S44<>"",N(S44)>Settings!$B$5),"SLOW MOVER","OK")))))) -> OK | X44: =IF(OR(D44="End of range",U44=""),0,IF(N(U44)>0,U44+ROW()/1000000,0)) -> 0
A45: COL001 | B45: COLUMBIAN BROWN | C45: Hide | D45: Active | E45: =SUMIFS('CPT Count'!$D:$D,'CPT Count'!$A:$A,$A45)-SUMIFS('Weekly Sales'!$F:$F,'Weekly Sales'!$H:$H,$A45,'Weekly Sales'!$I:$I,"CPT")+SUMIFS(Transfers!$F:$F,Transfers!$C:$C,$A45,Transfers!$J:$J,"CPT")-SUMIFS(Transfers!$F:$F,Transfers!$C:$C,$A45,Transfers!$I:$I,"CPT",Transfers!$H:$H,"<>Y")+SUMIFS('Stock Received'!$I:$I,'Stock Received'!$E:$E,$A45,'Stock Received'!$L:$L,"CPT") -> 161.23 | F45: =SUMIFS('JHB Count'!$E:$E,'JHB Count'!$F:$F,$A45)-SUMIFS('Weekly Sales'!$F:$F,'Weekly Sales'!$H:$H,$A45,'Weekly Sales'!$I:$I,"JHB")+SUMIFS(Transfers!$F:$F,Transfers!$C:$C,$A45,Transfers!$J:$J,"JHB")-SUMIFS(Transfers!$F:$F,Transfers!$C:$C,$A45,Transfers!$I:$I,"JHB",Transfers!$H:$H,"<>Y")+SUMIFS('Stock Received'!$I:$I,'Stock Received'!$E:$E,$A45,'Stock Received'!$L:$L,"JHB") -> 120 | G45: =SUMIFS('DBN Count'!$D:$D,'DBN Count'!$E:$E,$A45)-SUMIFS('Weekly Sales'!$F:$F,'Weekly Sales'!$H:$H,$A45,'Weekly Sales'!$I:$I,"DBN")+SUMIFS(Transfers!$F:$F,Transfers!$C:$C,$A45,Transfers!$J:$J,"DBN")-SUMIFS(Transfers!$F:$F,Transfers!$C:$C,$A45,Transfers!$I:$I,"DBN",Transfers!$H:$H,"<>Y")+SUMIFS('Stock Received'!$I:$I,'Stock Received'!$E:$E,$A45,'Stock Received'!$L:$L,"DBN") -> 0 | H45: =E45+F45+G45 -> 281.23 | I45: =SUMIFS('Weekly Sales'!$F:$F,'Weekly Sales'!$H:$H,$A45) -> 0 | J45: =SUMIFS(Orders!$L:$L,Orders!$D:$D,$A45,Orders!$F:$F,">="&J$4,Orders!$F:$F,"<"&EDATE(J$4,1)) -> 0 | K45: =SUMIFS(Orders!$L:$L,Orders!$D:$D,$A45,Orders!$F:$F,">="&K$4,Orders!$F:$F,"<"&EDATE(K$4,1)) -> 0 | L45: =SUMIFS(Orders!$L:$L,Orders!$D:$D,$A45,Orders!$F:$F,">="&L$4,Orders!$F:$F,"<"&EDATE(L$4,1)) -> 0 | M45: =N45-J45-K45-L45 -> 0 | N45: =SUMIFS(Orders!$L:$L,Orders!$D:$D,$A45) -> 0 | O45: =H45+N45 -> 281.23 | Q45: =IF(SUMIFS('Sales History'!$E:$E,'Sales History'!$G:$G,$A45)>0,SUMIFS('Sales History'!$E:$E,'Sales History'!$G:$G,$A45)/Settings!$B$4,N(P45)) -> 0 | R45: =IF(SUMIFS('Sales History'!$E:$E,'Sales History'!$G:$G,$A45)>0,"6-month history",IF(N(P45)>0,"Current sheet","No sales data")) -> No sales data | S45: =IF(Q45>0,H45/Q45,"") | T45: 100 | U45: =IF(T45="","",MAX(0,T45-O45)) -> 0 | V45: =IF(D45="End of range","END OF RANGE",IF(T45="","NO BUFFER SET",IF(H45<=0,IF(O45<T45,"OUT - REORDER","OUT - ON ORDER"),IF(O45<T45,"REORDER",IF(H45<T45,"LOW - ON ORDER",IF(AND(S45<>"",N(S45)>Settings!$B$5),"SLOW MOVER","OK")))))) -> OK | X45: =IF(OR(D45="End of range",U45=""),0,IF(N(U45)>0,U45+ROW()/1000000,0)) -> 0
A46: COL002 | B46: COLUMBIAN TAN | C46: Hide | D46: Active | E46: =SUMIFS('CPT Count'!$D:$D,'CPT Count'!$A:$A,$A46)-SUMIFS('Weekly Sales'!$F:$F,'Weekly Sales'!$H:$H,$A46,'Weekly Sales'!$I:$I,"CPT")+SUMIFS(Transfers!$F:$F,Transfers!$C:$C,$A46,Transfers!$J:$J,"CPT")-SUMIFS(Transfers!$F:$F,Transfers!$C:$C,$A46,Transfers!$I:$I,"CPT",Transfers!$H:$H,"<>Y")+SUMIFS('Stock Received'!$I:$I,'Stock Received'!$E:$E,$A46,'Stock Received'!$L:$L,"CPT") -> 157.49 | F46: =SUMIFS('JHB Count'!$E:$E,'JHB Count'!$F:$F,$A46)-SUMIFS('Weekly Sales'!$F:$F,'Weekly Sales'!$H:$H,$A46,'Weekly Sales'!$I:$I,"JHB")+SUMIFS(Transfers!$F:$F,Transfers!$C:$C,$A46,Transfers!$J:$J,"JHB")-SUMIFS(Transfers!$F:$F,Transfers!$C:$C,$A46,Transfers!$I:$I,"JHB",Transfers!$H:$H,"<>Y")+SUMIFS('Stock Received'!$I:$I,'Stock Received'!$E:$E,$A46,'Stock Received'!$L:$L,"JHB") -> 120 | G46: =SUMIFS('DBN Count'!$D:$D,'DBN Count'!$E:$E,$A46)-SUMIFS('Weekly Sales'!$F:$F,'Weekly Sales'!$H:$H,$A46,'Weekly Sales'!$I:$I,"DBN")+SUMIFS(Transfers!$F:$F,Transfers!$C:$C,$A46,Transfers!$J:$J,"DBN")-SUMIFS(Transfers!$F:$F,Transfers!$C:$C,$A46,Transfers!$I:$I,"DBN",Transfers!$H:$H,"<>Y")+SUMIFS('Stock Received'!$I:$I,'Stock Received'!$E:$E,$A46,'Stock Received'!$L:$L,"DBN") -> 0 | H46: =E46+F46+G46 -> 277.49 | I46: =SUMIFS('Weekly Sales'!$F:$F,'Weekly Sales'!$H:$H,$A46) -> 0 | J46: =SUMIFS(Orders!$L:$L,Orders!$D:$D,$A46,Orders!$F:$F,">="&J$4,Orders!$F:$F,"<"&EDATE(J$4,1)) -> 0 | K46: =SUMIFS(Orders!$L:$L,Orders!$D:$D,$A46,Orders!$F:$F,">="&K$4,Orders!$F:$F,"<"&EDATE(K$4,1)) -> 0 | L46: =SUMIFS(Orders!$L:$L,Orders!$D:$D,$A46,Orders!$F:$F,">="&L$4,Orders!$F:$F,"<"&EDATE(L$4,1)) -> 0 | M46: =N46-J46-K46-L46 -> 0 | N46: =SUMIFS(Orders!$L:$L,Orders!$D:$D,$A46) -> 0 | O46: =H46+N46 -> 277.49 | Q46: =IF(SUMIFS('Sales History'!$E:$E,'Sales History'!$G:$G,$A46)>0,SUMIFS('Sales History'!$E:$E,'Sales History'!$G:$G,$A46)/Settings!$B$4,N(P46)) -> 0 | R46: =IF(SUMIFS('Sales History'!$E:$E,'Sales History'!$G:$G,$A46)>0,"6-month history",IF(N(P46)>0,"Current sheet","No sales data")) -> No sales data | S46: =IF(Q46>0,H46/Q46,"") | T46: 100 | U46: =IF(T46="","",MAX(0,T46-O46)) -> 0 | V46: =IF(D46="End of range","END OF RANGE",IF(T46="","NO BUFFER SET",IF(H46<=0,IF(O46<T46,"OUT - REORDER","OUT - ON ORDER"),IF(O46<T46,"REORDER",IF(H46<T46,"LOW - ON ORDER",IF(AND(S46<>"",N(S46)>Settings!$B$5),"SLOW MOVER","OK")))))) -> OK | X46: =IF(OR(D46="End of range",U46=""),0,IF(N(U46)>0,U46+ROW()/1000000,0)) -> 0
A47: DIE001 | B47: DIESEL BROWN | C47: Hide | D47: Active | E47: =SUMIFS('CPT Count'!$D:$D,'CPT Count'!$A:$A,$A47)-SUMIFS('Weekly Sales'!$F:$F,'Weekly Sales'!$H:$H,$A47,'Weekly Sales'!$I:$I,"CPT")+SUMIFS(Transfers!$F:$F,Transfers!$C:$C,$A47,Transfers!$J:$J,"CPT")-SUMIFS(Transfers!$F:$F,Transfers!$C:$C,$A47,Transfers!$I:$I,"CPT",Transfers!$H:$H,"<>Y")+SUMIFS('Stock Received'!$I:$I,'Stock Received'!$E:$E,$A47,'Stock Received'!$L:$L,"CPT") -> 799.49 | F47: =SUMIFS('JHB Count'!$E:$E,'JHB Count'!$F:$F,$A47)-SUMIFS('Weekly Sales'!$F:$F,'Weekly Sales'!$H:$H,$A47,'Weekly Sales'!$I:$I,"JHB")+SUMIFS(Transfers!$F:$F,Transfers!$C:$C,$A47,Transfers!$J:$J,"JHB")-SUMIFS(Transfers!$F:$F,Transfers!$C:$C,$A47,Transfers!$I:$I,"JHB",Transfers!$H:$H,"<>Y")+SUMIFS('Stock Received'!$I:$I,'Stock Received'!$E:$E,$A47,'Stock Received'!$L:$L,"JHB") -> 53.89 | G47: =SUMIFS('DBN Count'!$D:$D,'DBN Count'!$E:$E,$A47)-SUMIFS('Weekly Sales'!$F:$F,'Weekly Sales'!$H:$H,$A47,'Weekly Sales'!$I:$I,"DBN")+SUMIFS(Transfers!$F:$F,Transfers!$C:$C,$A47,Transfers!$J:$J,"DBN")-SUMIFS(Transfers!$F:$F,Transfers!$C:$C,$A47,Transfers!$I:$I,"DBN",Transfers!$H:$H,"<>Y")+SUMIFS('Stock Received'!$I:$I,'Stock Received'!$E:$E,$A47,'Stock Received'!$L:$L,"DBN") -> 53.2 | H47: =E47+F47+G47 -> 906.58 | I47: =SUMIFS('Weekly Sales'!$F:$F,'Weekly Sales'!$H:$H,$A47) -> 149.81 | J47: =SUMIFS(Orders!$L:$L,Orders!$D:$D,$A47,Orders!$F:$F,">="&J$4,Orders!$F:$F,"<"&EDATE(J$4,1)) -> 0 | K47: =SUMIFS(Orders!$L:$L,Orders!$D:$D,$A47,Orders!$F:$F,">="&K$4,Orders!$F:$F,"<"&EDATE(K$4,1)) -> 800 | L47: =SUMIFS(Orders!$L:$L,Orders!$D:$D,$A47,Orders!$F:$F,">="&L$4,Orders!$F:$F,"<"&EDATE(L$4,1)) -> 500 | M47: =N47-J47-K47-L47 -> 0 | N47: =SUMIFS(Orders!$L:$L,Orders!$D:$D,$A47) -> 1300 | O47: =H47+N47 -> 2206.58 | P47: 600 | Q47: =IF(SUMIFS('Sales History'!$E:$E,'Sales History'!$G:$G,$A47)>0,SUMIFS('Sales History'!$E:$E,'Sales History'!$G:$G,$A47)/Settings!$B$4,N(P47)) -> 600 | R47: =IF(SUMIFS('Sales History'!$E:$E,'Sales History'!$G:$G,$A47)>0,"6-month history",IF(N(P47)>0,"Current sheet","No sales data")) -> Current sheet | S47: =IF(Q47>0,H47/Q47,"") -> 1.5109667 | T47: 800 | U47: =IF(T47="","",MAX(0,T47-O47)) -> 0 | V47: =IF(D47="End of range","END OF RANGE",IF(T47="","NO BUFFER SET",IF(H47<=0,IF(O47<T47,"OUT - REORDER","OUT - ON ORDER"),IF(O47<T47,"REORDER",IF(H47<T47,"LOW - ON ORDER",IF(AND(S47<>"",N(S47)>Settings!$B$5),"SLOW MOVER","OK")))))) -> OK | X47: =IF(OR(D47="End of range",U47=""),0,IF(N(U47)>0,U47+ROW()/1000000,0)) -> 0
A48: DIE011 | B48: DIESEL TOFFEE | C48: Hide | D48: Active | E48: =SUMIFS('CPT Count'!$D:$D,'CPT Count'!$A:$A,$A48)-SUMIFS('Weekly Sales'!$F:$F,'Weekly Sales'!$H:$H,$A48,'Weekly Sales'!$I:$I,"CPT")+SUMIFS(Transfers!$F:$F,Transfers!$C:$C,$A48,Transfers!$J:$J,"CPT")-SUMIFS(Transfers!$F:$F,Transfers!$C:$C,$A48,Transfers!$I:$I,"CPT",Transfers!$H:$H,"<>Y")+SUMIFS('Stock Received'!$I:$I,'Stock Received'!$E:$E,$A48,'Stock Received'!$L:$L,"CPT") -> 1611.9 | F48: =SUMIFS('JHB Count'!$E:$E,'JHB Count'!$F:$F,$A48)-SUMIFS('Weekly Sales'!$F:$F,'Weekly Sales'!$H:$H,$A48,'Weekly Sales'!$I:$I,"JHB")+SUMIFS(Transfers!$F:$F,Transfers!$C:$C,$A48,Transfers!$J:$J,"JHB")-SUMIFS(Transfers!$F:$F,Transfers!$C:$C,$A48,Transfers!$I:$I,"JHB",Transfers!$H:$H,"<>Y")+SUMIFS('Stock Received'!$I:$I,'Stock Received'!$E:$E,$A48,'Stock Received'!$L:$L,"JHB") -> 191.35 | G48: =SUMIFS('DBN Count'!$D:$D,'DBN Count'!$E:$E,$A48)-SUMIFS('Weekly Sales'!$F:$F,'Weekly Sales'!$H:$H,$A48,'Weekly Sales'!$I:$I,"DBN")+SUMIFS(Transfers!$F:$F,Transfers!$C:$C,$A48,Transfers!$J:$J,"DBN")-SUMIFS(Transfers!$F:$F,Transfers!$C:$C,$A48,Transfers!$I:$I,"DBN",Transfers!$H:$H,"<>Y")+SUMIFS('Stock Received'!$I:$I,'Stock Received'!$E:$E,$A48,'Stock Received'!$L:$L,"DBN") -> 29.79 | H48: =E48+F48+G48 -> 1833.04 | I48: =SUMIFS('Weekly Sales'!$F:$F,'Weekly Sales'!$H:$H,$A48) -> 135.04 | J48: =SUMIFS(Orders!$L:$L,Orders!$D:$D,$A48,Orders!$F:$F,">="&J$4,Orders!$F:$F,"<"&EDATE(J$4,1)) -> 0 | K48: =SUMIFS(Orders!$L:$L,Orders!$D:$D,$A48,Orders!$F:$F,">="&K$4,Orders!$F:$F,"<"&EDATE(K$4,1)) -> 500 | L48: =SUMIFS(Orders!$L:$L,Orders!$D:$D,$A48,Orders!$F:$F,">="&L$4,Orders!$F:$F,"<"&EDATE(L$4,1)) -> 0 | M48: =N48-J48-K48-L48 -> 0 | N48: =SUMIFS(Orders!$L:$L,Orders!$D:$D,$A48) -> 500 | O48: =H48+N48 -> 2333.04 | P48: 450 | Q48: =IF(SUMIFS('Sales History'!$E:$E,'Sales History'!$G:$G,$A48)>0,SUMIFS('Sales History'!$E:$E,'Sales History'!$G:$G,$A48)/Settings!$B$4,N(P48)) -> 450 | R48: =IF(SUMIFS('Sales History'!$E:$E,'Sales History'!$G:$G,$A48)>0,"6-month history",IF(N(P48)>0,"Current sheet","No sales data")) -> Current sheet | S48: =IF(Q48>0,H48/Q48,"") -> 4.0734222 | T48: 800 | U48: =IF(T48="","",MAX(0,T48-O48)) -> 0 | V48: =IF(D48="End of range","END OF RANGE",IF(T48="","NO BUFFER SET",IF(H48<=0,IF(O48<T48,"OUT - REORDER","OUT - ON ORDER"),IF(O48<T48,"REORDER",IF(H48<T48,"LOW - ON ORDER",IF(AND(S48<>"",N(S48)>Settings!$B$5),"SLOW MOVER","OK")))))) -> OK | X48: =IF(OR(D48="End of range",U48=""),0,IF(N(U48)>0,U48+ROW()/1000000,0)) -> 0
A49: DIE013 | B49: DIESEL DENIM | C49: Hide | D49: Active | E49: =SUMIFS('CPT Count'!$D:$D,'CPT Count'!$A:$A,$A49)-SUMIFS('Weekly Sales'!$F:$F,'Weekly Sales'!$H:$H,$A49,'Weekly Sales'!$I:$I,"CPT")+SUMIFS(Transfers!$F:$F,Transfers!$C:$C,$A49,Transfers!$J:$J,"CPT")-SUMIFS(Transfers!$F:$F,Transfers!$C:$C,$A49,Transfers!$I:$I,"CPT",Transfers!$H:$H,"<>Y")+SUMIFS('Stock Received'!$I:$I,'Stock Received'!$E:$E,$A49,'Stock Received'!$L:$L,"CPT") -> 372 | F49: =SUMIFS('JHB Count'!$E:$E,'JHB Count'!$F:$F,$A49)-SUMIFS('Weekly Sales'!$F:$F,'Weekly Sales'!$H:$H,$A49,'Weekly Sales'!$I:$I,"JHB")+SUMIFS(Transfers!$F:$F,Transfers!$C:$C,$A49,Transfers!$J:$J,"JHB")-SUMIFS(Transfers!$F:$F,Transfers!$C:$C,$A49,Transfers!$I:$I,"JHB",Transfers!$H:$H,"<>Y")+SUMIFS('Stock Received'!$I:$I,'Stock Received'!$E:$E,$A49,'Stock Received'!$L:$L,"JHB") -> 56.72 | G49: =SUMIFS('DBN Count'!$D:$D,'DBN Count'!$E:$E,$A49)-SUMIFS('Weekly Sales'!$F:$F,'Weekly Sales'!$H:$H,$A49,'Weekly Sales'!$I:$I,"DBN")+SUMIFS(Transfers!$F:$F,Transfers!$C:$C,$A49,Transfers!$J:$J,"DBN")-SUMIFS(Transfers!$F:$F,Transfers!$C:$C,$A49,Transfers!$I:$I,"DBN",Transfers!$H:$H,"<>Y")+SUMIFS('Stock Received'!$I:$I,'Stock Received'!$E:$E,$A49,'Stock Received'!$L:$L,"DBN") -> 0 | H49: =E49+F49+G49 -> 428.72 | I49: =SUMIFS('Weekly Sales'!$F:$F,'Weekly Sales'!$H:$H,$A49) -> 7.28 | J49: =SUMIFS(Orders!$L:$L,Orders!$D:$D,$A49,Orders!$F:$F,">="&J$4,Orders!$F:$F,"<"&EDATE(J$4,1)) -> 0 | K49: =SUMIFS(Orders!$L:$L,Orders!$D:$D,$A49,Orders!$F:$F,">="&K$4,Orders!$F:$F,"<"&EDATE(K$4,1)) -> 0 | L49: =SUMIFS(Orders!$L:$L,Orders!$D:$D,$A49,Orders!$F:$F,">="&L$4,Orders!$F:$F,"<"&EDATE(L$4,1)) -> 0 | M49: =N49-J49-K49-L49 -> 0 | N49: =SUMIFS(Orders!$L:$L,Orders!$D:$D,$A49) -> 0 | O49: =H49+N49 -> 428.72 | P49: 75 | Q49: =IF(SUMIFS('Sales History'!$E:$E,'Sales History'!$G:$G,$A49)>0,SUMIFS('Sales History'!$E:$E,'Sales History'!$G:$G,$A49)/Settings!$B$4,N(P49)) -> 75 | R49: =IF(SUMIFS('Sales History'!$E:$E,'Sales History'!$G:$G,$A49)>0,"6-month history",IF(N(P49)>0,"Current sheet","No sales data")) -> Current sheet | S49: =IF(Q49>0,H49/Q49,"") -> 5.7162667 | T49: 200 | U49: =IF(T49="","",MAX(0,T49-O49)) -> 0 | V49: =IF(D49="End of range","END OF RANGE",IF(T49="","NO BUFFER SET",IF(H49<=0,IF(O49<T49,"OUT - REORDER","OUT - ON ORDER"),IF(O49<T49,"REORDER",IF(H49<T49,"LOW - ON ORDER",IF(AND(S49<>"",N(S49)>Settings!$B$5),"SLOW MOVER","OK")))))) -> OK | X49: =IF(OR(D49="End of range",U49=""),0,IF(N(U49)>0,U49+ROW()/1000000,0)) -> 0
A50: DIE018 | B50: DIESEL TOBACCO | C50: Hide | D50: Active | E50: =SUMIFS('CPT Count'!$D:$D,'CPT Count'!$A:$A,$A50)-SUMIFS('Weekly Sales'!$F:$F,'Weekly Sales'!$H:$H,$A50,'Weekly Sales'!$I:$I,"CPT")+SUMIFS(Transfers!$F:$F,Transfers!$C:$C,$A50,Transfers!$J:$J,"CPT")-SUMIFS(Transfers!$F:$F,Transfers!$C:$C,$A50,Transfers!$I:$I,"CPT",Transfers!$H:$H,"<>Y")+SUMIFS('Stock Received'!$I:$I,'Stock Received'!$E:$E,$A50,'Stock Received'!$L:$L,"CPT") -> 1097.46 | F50: =SUMIFS('JHB Count'!$E:$E,'JHB Count'!$F:$F,$A50)-SUMIFS('Weekly Sales'!$F:$F,'Weekly Sales'!$H:$H,$A50,'Weekly Sales'!$I:$I,"JHB")+SUMIFS(Transfers!$F:$F,Transfers!$C:$C,$A50,Transfers!$J:$J,"JHB")-SUMIFS(Transfers!$F:$F,Transfers!$C:$C,$A50,Transfers!$I:$I,"JHB",Transfers!$H:$H,"<>Y")+SUMIFS('Stock Received'!$I:$I,'Stock Received'!$E:$E,$A50,'Stock Received'!$L:$L,"JHB") -> 186.64 | G50: =SUMIFS('DBN Count'!$D:$D,'DBN Count'!$E:$E,$A50)-SUMIFS('Weekly Sales'!$F:$F,'Weekly Sales'!$H:$H,$A50,'Weekly Sales'!$I:$I,"DBN")+SUMIFS(Transfers!$F:$F,Transfers!$C:$C,$A50,Transfers!$J:$J,"DBN")-SUMIFS(Transfers!$F:$F,Transfers!$C:$C,$A50,Transfers!$I:$I,"DBN",Transfers!$H:$H,"<>Y")+SUMIFS('Stock Received'!$I:$I,'Stock Received'!$E:$E,$A50,'Stock Received'!$L:$L,"DBN") -> 94.37 | H50: =E50+F50+G50 -> 1378.47 | I50: =SUMIFS('Weekly Sales'!$F:$F,'Weekly Sales'!$H:$H,$A50) -> 383.9 | J50: =SUMIFS(Orders!$L:$L,Orders!$D:$D,$A50,Orders!$F:$F,">="&J$4,Orders!$F:$F,"<"&EDATE(J$4,1)) -> 500 | K50: =SUMIFS(Orders!$L:$L,Orders!$D:$D,$A50,Orders!$F:$F,">="&K$4,Orders!$F:$F,"<"&EDATE(K$4,1)) -> 500 | L50: =SUMIFS(Orders!$L:$L,Orders!$D:$D,$A50,Orders!$F:$F,">="&L$4,Orders!$F:$F,"<"&EDATE(L$4,1)) -> 800 | M50: =N50-J50-K50-L50 -> 0 | N50: =SUMIFS(Orders!$L:$L,Orders!$D:$D,$A50) -> 1800 | O50: =H50+N50 -> 3178.47 | P50: 830 | Q50: =IF(SUMIFS('Sales History'!$E:$E,'Sales History'!$G:$G,$A50)>0,SUMIFS('Sales History'!$E:$E,'Sales History'!$G:$G,$A50)/Settings!$B$4,N(P50)) -> 830 | R50: =IF(SUMIFS('Sales History'!$E:$E,'Sales History'!$G:$G,$A50)>0,"6-month history",IF(N(P50)>0,"Current sheet","No sales data")) -> Current sheet | S50: =IF(Q50>0,H50/Q50,"") -> 1.6608072 | T50: 1500 | U50: =IF(T50="","",MAX(0,T50-O50)) -> 0 | V50: =IF(D50="End of range","END OF RANGE",IF(T50="","NO BUFFER SET",IF(H50<=0,IF(O50<T50,"OUT - REORDER","OUT - ON ORDER"),IF(O50<T50,"REORDER",IF(H50<T50,"LOW - ON ORDER",IF(AND(S50<>"",N(S50)>Settings!$B$5),"SLOW MOVER","OK")))))) -> LOW - ON ORDER | X50: =IF(OR(D50="End of range",U50=""),0,IF(N(U50)>0,U50+ROW()/1000000,0)) -> 0
A51: URB010 | B51: URBAN HAZELNUT | C51: Hide | D51: Active | E51: =SUMIFS('CPT Count'!$D:$D,'CPT Count'!$A:$A,$A51)-SUMIFS('Weekly Sales'!$F:$F,'Weekly Sales'!$H:$H,$A51,'Weekly Sales'!$I:$I,"CPT")+SUMIFS(Transfers!$F:$F,Transfers!$C:$C,$A51,Transfers!$J:$J,"CPT")-SUMIFS(Transfers!$F:$F,Transfers!$C:$C,$A51,Transfers!$I:$I,"CPT",Transfers!$H:$H,"<>Y")+SUMIFS('Stock Received'!$I:$I,'Stock Received'!$E:$E,$A51,'Stock Received'!$L:$L,"CPT") -> 2.75 | F51: =SUMIFS('JHB Count'!$E:$E,'JHB Count'!$F:$F,$A51)-SUMIFS('Weekly Sales'!$F:$F,'Weekly Sales'!$H:$H,$A51,'Weekly Sales'!$I:$I,"JHB")+SUMIFS(Transfers!$F:$F,Transfers!$C:$C,$A51,Transfers!$J:$J,"JHB")-SUMIFS(Transfers!$F:$F,Transfers!$C:$C,$A51,Transfers!$I:$I,"JHB",Transfers!$H:$H,"<>Y")+SUMIFS('Stock Received'!$I:$I,'Stock Received'!$E:$E,$A51,'Stock Received'!$L:$L,"JHB") -> 144.21 | G51: =SUMIFS('DBN Count'!$D:$D,'DBN Count'!$E:$E,$A51)-SUMIFS('Weekly Sales'!$F:$F,'Weekly Sales'!$H:$H,$A51,'Weekly Sales'!$I:$I,"DBN")+SUMIFS(Transfers!$F:$F,Transfers!$C:$C,$A51,Transfers!$J:$J,"DBN")-SUMIFS(Transfers!$F:$F,Transfers!$C:$C,$A51,Transfers!$I:$I,"DBN",Transfers!$H:$H,"<>Y")+SUMIFS('Stock Received'!$I:$I,'Stock Received'!$E:$E,$A51,'Stock Received'!$L:$L,"DBN") -> 50.74 | H51: =E51+F51+G51 -> 197.7 | I51: =SUMIFS('Weekly Sales'!$F:$F,'Weekly Sales'!$H:$H,$A51) -> 57.04 | J51: =SUMIFS(Orders!$L:$L,Orders!$D:$D,$A51,Orders!$F:$F,">="&J$4,Orders!$F:$F,"<"&EDATE(J$4,1)) -> 300 | K51: =SUMIFS(Orders!$L:$L,Orders!$D:$D,$A51,Orders!$F:$F,">="&K$4,Orders!$F:$F,"<"&EDATE(K$4,1)) -> 300 | L51: =SUMIFS(Orders!$L:$L,Orders!$D:$D,$A51,Orders!$F:$F,">="&L$4,Orders!$F:$F,"<"&EDATE(L$4,1)) -> 300 | M51: =N51-J51-K51-L51 -> 0 | N51: =SUMIFS(Orders!$L:$L,Orders!$D:$D,$A51) -> 900 | O51: =H51+N51 -> 1097.7 | P51: 220 | Q51: =IF(SUMIFS('Sales History'!$E:$E,'Sales History'!$G:$G,$A51)>0,SUMIFS('Sales History'!$E:$E,'Sales History'!$G:$G,$A51)/Settings!$B$4,N(P51)) -> 220 | R51: =IF(SUMIFS('Sales History'!$E:$E,'Sales History'!$G:$G,$A51)>0,"6-month history",IF(N(P51)>0,"Current sheet","No sales data")) -> Current sheet | S51: =IF(Q51>0,H51/Q51,"") -> 0.89863636 | T51: 400 | U51: =IF(T51="","",MAX(0,T51-O51)) -> 0 | V51: =IF(D51="End of range","END OF RANGE",IF(T51="","NO BUFFER SET",IF(H51<=0,IF(O51<T51,"OUT - REORDER","OUT - ON ORDER"),IF(O51<T51,"REORDER",IF(H51<T51,"LOW - ON ORDER",IF(AND(S51<>"",N(S51)>Settings!$B$5),"SLOW MOVER","OK")))))) -> LOW - ON ORDER | X51: =IF(OR(D51="End of range",U51=""),0,IF(N(U51)>0,U51+ROW()/1000000,0)) -> 0
A52: DAY008 | B52: DAYTONA BROWN/TAN | C52: Hide | D52: Active | E52: =SUMIFS('CPT Count'!$D:$D,'CPT Count'!$A:$A,$A52)-SUMIFS('Weekly Sales'!$F:$F,'Weekly Sales'!$H:$H,$A52,'Weekly Sales'!$I:$I,"CPT")+SUMIFS(Transfers!$F:$F,Transfers!$C:$C,$A52,Transfers!$J:$J,"CPT")-SUMIFS(Transfers!$F:$F,Transfers!$C:$C,$A52,Transfers!$I:$I,"CPT",Transfers!$H:$H,"<>Y")+SUMIFS('Stock Received'!$I:$I,'Stock Received'!$E:$E,$A52,'Stock Received'!$L:$L,"CPT") -> 135 | F52: =SUMIFS('JHB Count'!$E:$E,'JHB Count'!$F:$F,$A52)-SUMIFS('Weekly Sales'!$F:$F,'Weekly Sales'!$H:$H,$A52,'Weekly Sales'!$I:$I,"JHB")+SUMIFS(Transfers!$F:$F,Transfers!$C:$C,$A52,Transfers!$J:$J,"JHB")-SUMIFS(Transfers!$F:$F,Transfers!$C:$C,$A52,Transfers!$I:$I,"JHB",Transfers!$H:$H,"<>Y")+SUMIFS('Stock Received'!$I:$I,'Stock Received'!$E:$E,$A52,'Stock Received'!$L:$L,"JHB") -> 724 | G52: =SUMIFS('DBN Count'!$D:$D,'DBN Count'!$E:$E,$A52)-SUMIFS('Weekly Sales'!$F:$F,'Weekly Sales'!$H:$H,$A52,'Weekly Sales'!$I:$I,"DBN")+SUMIFS(Transfers!$F:$F,Transfers!$C:$C,$A52,Transfers!$J:$J,"DBN")-SUMIFS(Transfers!$F:$F,Transfers!$C:$C,$A52,Transfers!$I:$I,"DBN",Transfers!$H:$H,"<>Y")+SUMIFS('Stock Received'!$I:$I,'Stock Received'!$E:$E,$A52,'Stock Received'!$L:$L,"DBN") -> 46.69 | H52: =E52+F52+G52 -> 905.69 | I52: =SUMIFS('Weekly Sales'!$F:$F,'Weekly Sales'!$H:$H,$A52) -> 0 | J52: =SUMIFS(Orders!$L:$L,Orders!$D:$D,$A52,Orders!$F:$F,">="&J$4,Orders!$F:$F,"<"&EDATE(J$4,1)) -> 300 | K52: =SUMIFS(Orders!$L:$L,Orders!$D:$D,$A52,Orders!$F:$F,">="&K$4,Orders!$F:$F,"<"&EDATE(K$4,1)) -> 300 | L52: =SUMIFS(Orders!$L:$L,Orders!$D:$D,$A52,Orders!$F:$F,">="&L$4,Orders!$F:$F,"<"&EDATE(L$4,1)) -> 300 | M52: =N52-J52-K52-L52 -> 0 | N52: =SUMIFS(Orders!$L:$L,Orders!$D:$D,$A52) -> 900 | O52: =H52+N52 -> 1805.69 | P52: 260 | Q52: =IF(SUMIFS('Sales History'!$E:$E,'Sales History'!$G:$G,$A52)>0,SUMIFS('Sales History'!$E:$E,'Sales History'!$G:$G,$A52)/Settings!$B$4,N(P52)) -> 260 | R52: =IF(SUMIFS('Sales History'!$E:$E,'Sales History'!$G:$G,$A52)>0,"6-month history",IF(N(P52)>0,"Current sheet","No sales data")) -> Current sheet | S52: =IF(Q52>0,H52/Q52,"") -> 3.4834231 | T52: 400 | U52: =IF(T52="","",MAX(0,T52-O52)) -> 0 | V52: =IF(D52="End of range","END OF RANGE",IF(T52="","NO BUFFER SET",IF(H52<=0,IF(O52<T52,"OUT - REORDER","OUT - ON ORDER"),IF(O52<T52,"REORDER",IF(H52<T52,"LOW - ON ORDER",IF(AND(S52<>"",N(S52)>Settings!$B$5),"SLOW MOVER","OK")))))) -> OK | X52: =IF(OR(D52="End of range",U52=""),0,IF(N(U52)>0,U52+ROW()/1000000,0)) -> 0
A53: DAY002 | B53: DAYTONA ESPRESSO | C53: Hide | D53: Active | E53: =SUMIFS('CPT Count'!$D:$D,'CPT Count'!$A:$A,$A53)-SUMIFS('Weekly Sales'!$F:$F,'Weekly Sales'!$H:$H,$A53,'Weekly Sales'!$I:$I,"CPT")+SUMIFS(Transfers!$F:$F,Transfers!$C:$C,$A53,Transfers!$J:$J,"CPT")-SUMIFS(Transfers!$F:$F,Transfers!$C:$C,$A53,Transfers!$I:$I,"CPT",Transfers!$H:$H,"<>Y")+SUMIFS('Stock Received'!$I:$I,'Stock Received'!$E:$E,$A53,'Stock Received'!$L:$L,"CPT") -> 863.03 | F53: =SUMIFS('JHB Count'!$E:$E,'JHB Count'!$F:$F,$A53)-SUMIFS('Weekly Sales'!$F:$F,'Weekly Sales'!$H:$H,$A53,'Weekly Sales'!$I:$I,"JHB")+SUMIFS(Transfers!$F:$F,Transfers!$C:$C,$A53,Transfers!$J:$J,"JHB")-SUMIFS(Transfers!$F:$F,Transfers!$C:$C,$A53,Transfers!$I:$I,"JHB",Transfers!$H:$H,"<>Y")+SUMIFS('Stock Received'!$I:$I,'Stock Received'!$E:$E,$A53,'Stock Received'!$L:$L,"JHB") -> 64 | G53: =SUMIFS('DBN Count'!$D:$D,'DBN Count'!$E:$E,$A53)-SUMIFS('Weekly Sales'!$F:$F,'Weekly Sales'!$H:$H,$A53,'Weekly Sales'!$I:$I,"DBN")+SUMIFS(Transfers!$F:$F,Transfers!$C:$C,$A53,Transfers!$J:$J,"DBN")-SUMIFS(Transfers!$F:$F,Transfers!$C:$C,$A53,Transfers!$I:$I,"DBN",Transfers!$H:$H,"<>Y")+SUMIFS('Stock Received'!$I:$I,'Stock Received'!$E:$E,$A53,'Stock Received'!$L:$L,"DBN") -> 12.78 | H53: =E53+F53+G53 -> 939.81 | I53: =SUMIFS('Weekly Sales'!$F:$F,'Weekly Sales'!$H:$H,$A53) -> 3.97 | J53: =SUMIFS(Orders!$L:$L,Orders!$D:$D,$A53,Orders!$F:$F,">="&J$4,Orders!$F:$F,"<"&EDATE(J$4,1)) -> 0 | K53: =SUMIFS(Orders!$L:$L,Orders!$D:$D,$A53,Orders!$F:$F,">="&K$4,Orders!$F:$F,"<"&EDATE(K$4,1)) -> 0 | L53: =SUMIFS(Orders!$L:$L,Orders!$D:$D,$A53,Orders!$F:$F,">="&L$4,Orders!$F:$F,"<"&EDATE(L$4,1)) -> 0 | M53: =N53-J53-K53-L53 -> 0 | N53: =SUMIFS(Orders!$L:$L,Orders!$D:$D,$A53) -> 0 | O53: =H53+N53 -> 939.81 | P53: 180 | Q53: =IF(SUMIFS('Sales History'!$E:$E,'Sales History'!$G:$G,$A53)>0,SUMIFS('Sales History'!$E:$E,'Sales History'!$G:$G,$A53)/Settings!$B$4,N(P53)) -> 180 | R53: =IF(SUMIFS('Sales History'!$E:$E,'Sales History'!$G:$G,$A53)>0,"6-month history",IF(N(P53)>0,"Current sheet","No sales data")) -> Current sheet | S53: =IF(Q53>0,H53/Q53,"") -> 5.2211667 | T53: 300 | U53: =IF(T53="","",MAX(0,T53-O53)) -> 0 | V53: =IF(D53="End of range","END OF RANGE",IF(T53="","NO BUFFER SET",IF(H53<=0,IF(O53<T53,"OUT - REORDER","OUT - ON ORDER"),IF(O53<T53,"REORDER",IF(H53<T53,"LOW - ON ORDER",IF(AND(S53<>"",N(S53)>Settings!$B$5),"SLOW MOVER","OK")))))) -> OK | X53: =IF(OR(D53="End of range",U53=""),0,IF(N(U53)>0,U53+ROW()/1000000,0)) -> 0
A54: DAY011 | B54: DAYTONA TOFFEE | C54: Hide | D54: Active | E54: =SUMIFS('CPT Count'!$D:$D,'CPT Count'!$A:$A,$A54)-SUMIFS('Weekly Sales'!$F:$F,'Weekly Sales'!$H:$H,$A54,'Weekly Sales'!$I:$I,"CPT")+SUMIFS(Transfers!$F:$F,Transfers!$C:$C,$A54,Transfers!$J:$J,"CPT")-SUMIFS(Transfers!$F:$F,Transfers!$C:$C,$A54,Transfers!$I:$I,"CPT",Transfers!$H:$H,"<>Y")+SUMIFS('Stock Received'!$I:$I,'Stock Received'!$E:$E,$A54,'Stock Received'!$L:$L,"CPT") -> 676.37 | F54: =SUMIFS('JHB Count'!$E:$E,'JHB Count'!$F:$F,$A54)-SUMIFS('Weekly Sales'!$F:$F,'Weekly Sales'!$H:$H,$A54,'Weekly Sales'!$I:$I,"JHB")+SUMIFS(Transfers!$F:$F,Transfers!$C:$C,$A54,Transfers!$J:$J,"JHB")-SUMIFS(Transfers!$F:$F,Transfers!$C:$C,$A54,Transfers!$I:$I,"JHB",Transfers!$H:$H,"<>Y")+SUMIFS('Stock Received'!$I:$I,'Stock Received'!$E:$E,$A54,'Stock Received'!$L:$L,"JHB") -> 0.02 | G54: =SUMIFS('DBN Count'!$D:$D,'DBN Count'!$E:$E,$A54)-SUMIFS('Weekly Sales'!$F:$F,'Weekly Sales'!$H:$H,$A54,'Weekly Sales'!$I:$I,"DBN")+SUMIFS(Transfers!$F:$F,Transfers!$C:$C,$A54,Transfers!$J:$J,"DBN")-SUMIFS(Transfers!$F:$F,Transfers!$C:$C,$A54,Transfers!$I:$I,"DBN",Transfers!$H:$H,"<>Y")+SUMIFS('Stock Received'!$I:$I,'Stock Received'!$E:$E,$A54,'Stock Received'!$L:$L,"DBN") -> 90.02 | H54: =E54+F54+G54 -> 766.41 | I54: =SUMIFS('Weekly Sales'!$F:$F,'Weekly Sales'!$H:$H,$A54) -> 27.91 | J54: =SUMIFS(Orders!$L:$L,Orders!$D:$D,$A54,Orders!$F:$F,">="&J$4,Orders!$F:$F,"<"&EDATE(J$4,1)) -> 0 | K54: =SUMIFS(Orders!$L:$L,Orders!$D:$D,$A54,Orders!$F:$F,">="&K$4,Orders!$F:$F,"<"&EDATE(K$4,1)) -> 300 | L54: =SUMIFS(Orders!$L:$L,Orders!$D:$D,$A54,Orders!$F:$F,">="&L$4,Orders!$F:$F,"<"&EDATE(L$4,1)) -> 0 | M54: =N54-J54-K54-L54 -> 0 | N54: =SUMIFS(Orders!$L:$L,Orders!$D:$D,$A54) -> 300 | O54: =H54+N54 -> 1066.41 | P54: 260 | Q54: =IF(SUMIFS('Sales History'!$E:$E,'Sales History'!$G:$G,$A54)>0,SUMIFS('Sales History'!$E:$E,'Sales History'!$G:$G,$A54)/Settings!$B$4,N(P54)) -> 260 | R54: =IF(SUMIFS('Sales History'!$E:$E,'Sales History'!$G:$G,$A54)>0,"6-month history",IF(N(P54)>0,"Current sheet","No sales data")) -> Current sheet | S54: =IF(Q54>0,H54/Q54,"") -> 2.9477308 | T54: 500 | U54: =IF(T54="","",MAX(0,T54-O54)) -> 0 | V54: =IF(D54="End of range","END OF RANGE",IF(T54="","NO BUFFER SET",IF(H54<=0,IF(O54<T54,"OUT - REORDER","OUT - ON ORDER"),IF(O54<T54,"REORDER",IF(H54<T54,"LOW - ON ORDER",IF(AND(S54<>"",N(S54)>Settings!$B$5),"SLOW MOVER","OK")))))) -> OK | X54: =IF(OR(D54="End of range",U54=""),0,IF(N(U54)>0,U54+ROW()/1000000,0)) -> 0
A55: WOO006 | B55: WOODLAND TAN (CRICKET PRINT) | C55: Hide | D55: End of range | E55: =SUMIFS('CPT Count'!$D:$D,'CPT Count'!$A:$A,$A55)-SUMIFS('Weekly Sales'!$F:$F,'Weekly Sales'!$H:$H,$A55,'Weekly Sales'!$I:$I,"CPT")+SUMIFS(Transfers!$F:$F,Transfers!$C:$C,$A55,Transfers!$J:$J,"CPT")-SUMIFS(Transfers!$F:$F,Transfers!$C:$C,$A55,Transfers!$I:$I,"CPT",Transfers!$H:$H,"<>Y")+SUMIFS('Stock Received'!$I:$I,'Stock Received'!$E:$E,$A55,'Stock Received'!$L:$L,"CPT") -> 172 | F55: =SUMIFS('JHB Count'!$E:$E,'JHB Count'!$F:$F,$A55)-SUMIFS('Weekly Sales'!$F:$F,'Weekly Sales'!$H:$H,$A55,'Weekly Sales'!$I:$I,"JHB")+SUMIFS(Transfers!$F:$F,Transfers!$C:$C,$A55,Transfers!$J:$J,"JHB")-SUMIFS(Transfers!$F:$F,Transfers!$C:$C,$A55,Transfers!$I:$I,"JHB",Transfers!$H:$H,"<>Y")+SUMIFS('Stock Received'!$I:$I,'Stock Received'!$E:$E,$A55,'Stock Received'!$L:$L,"JHB") -> 8 | G55: =SUMIFS('DBN Count'!$D:$D,'DBN Count'!$E:$E,$A55)-SUMIFS('Weekly Sales'!$F:$F,'Weekly Sales'!$H:$H,$A55,'Weekly Sales'!$I:$I,"DBN")+SUMIFS(Transfers!$F:$F,Transfers!$C:$C,$A55,Transfers!$J:$J,"DBN")-SUMIFS(Transfers!$F:$F,Transfers!$C:$C,$A55,Transfers!$I:$I,"DBN",Transfers!$H:$H,"<>Y")+SUMIFS('Stock Received'!$I:$I,'Stock Received'!$E:$E,$A55,'Stock Received'!$L:$L,"DBN") -> 4.34 | H55: =E55+F55+G55 -> 184.34 | I55: =SUMIFS('Weekly Sales'!$F:$F,'Weekly Sales'!$H:$H,$A55) -> 0 | J55: =SUMIFS(Orders!$L:$L,Orders!$D:$D,$A55,Orders!$F:$F,">="&J$4,Orders!$F:$F,"<"&EDATE(J$4,1)) -> 0 | K55: =SUMIFS(Orders!$L:$L,Orders!$D:$D,$A55,Orders!$F:$F,">="&K$4,Orders!$F:$F,"<"&EDATE(K$4,1)) -> 0 | L55: =SUMIFS(Orders!$L:$L,Orders!$D:$D,$A55,Orders!$F:$F,">="&L$4,Orders!$F:$F,"<"&EDATE(L$4,1)) -> 0 | M55: =N55-J55-K55-L55 -> 0 | N55: =SUMIFS(Orders!$L:$L,Orders!$D:$D,$A55) -> 0 | O55: =H55+N55 -> 184.34 | P55: 10 | Q55: =IF(SUMIFS('Sales History'!$E:$E,'Sales History'!$G:$G,$A55)>0,SUMIFS('Sales History'!$E:$E,'Sales History'!$G:$G,$A55)/Settings!$B$4,N(P55)) -> 10 | R55: =IF(SUMIFS('Sales History'!$E:$E,'Sales History'!$G:$G,$A55)>0,"6-month history",IF(N(P55)>0,"Current sheet","No sales data")) -> Current sheet | S55: =IF(Q55>0,H55/Q55,"") -> 18.434 | U55: =IF(T55="","",MAX(0,T55-O55)) | V55: =IF(D55="End of range","END OF RANGE",IF(T55="","NO BUFFER SET",IF(H55<=0,IF(O55<T55,"OUT - REORDER","OUT - ON ORDER"),IF(O55<T55,"REORDER",IF(H55<T55,"LOW - ON ORDER",IF(AND(S55<>"",N(S55)>Settings!$B$5),"SLOW MOVER","OK")))))) -> END OF RANGE | X55: =IF(OR(D55="End of range",U55=""),0,IF(N(U55)>0,U55+ROW()/1000000,0)) -> 0
A56: WOO024 | B56: WOODLAND GRAPHITE (CRICKET PRINT) | C56: Hide | D56: End of range | E56: =SUMIFS('CPT Count'!$D:$D,'CPT Count'!$A:$A,$A56)-SUMIFS('Weekly Sales'!$F:$F,'Weekly Sales'!$H:$H,$A56,'Weekly Sales'!$I:$I,"CPT")+SUMIFS(Transfers!$F:$F,Transfers!$C:$C,$A56,Transfers!$J:$J,"CPT")-SUMIFS(Transfers!$F:$F,Transfers!$C:$C,$A56,Transfers!$I:$I,"CPT",Transfers!$H:$H,"<>Y")+SUMIFS('Stock Received'!$I:$I,'Stock Received'!$E:$E,$A56,'Stock Received'!$L:$L,"CPT") -> 220 | F56: =SUMIFS('JHB Count'!$E:$E,'JHB Count'!$F:$F,$A56)-SUMIFS('Weekly Sales'!$F:$F,'Weekly Sales'!$H:$H,$A56,'Weekly Sales'!$I:$I,"JHB")+SUMIFS(Transfers!$F:$F,Transfers!$C:$C,$A56,Transfers!$J:$J,"JHB")-SUMIFS(Transfers!$F:$F,Transfers!$C:$C,$A56,Transfers!$I:$I,"JHB",Transfers!$H:$H,"<>Y")+SUMIFS('Stock Received'!$I:$I,'Stock Received'!$E:$E,$A56,'Stock Received'!$L:$L,"JHB") -> 0 | G56: =SUMIFS('DBN Count'!$D:$D,'DBN Count'!$E:$E,$A56)-SUMIFS('Weekly Sales'!$F:$F,'Weekly Sales'!$H:$H,$A56,'Weekly Sales'!$I:$I,"DBN")+SUMIFS(Transfers!$F:$F,Transfers!$C:$C,$A56,Transfers!$J:$J,"DBN")-SUMIFS(Transfers!$F:$F,Transfers!$C:$C,$A56,Transfers!$I:$I,"DBN",Transfers!$H:$H,"<>Y")+SUMIFS('Stock Received'!$I:$I,'Stock Received'!$E:$E,$A56,'Stock Received'!$L:$L,"DBN") -> 0 | H56: =E56+F56+G56 -> 220 | I56: =SUMIFS('Weekly Sales'!$F:$F,'Weekly Sales'!$H:$H,$A56) -> 0 | J56: =SUMIFS(Orders!$L:$L,Orders!$D:$D,$A56,Orders!$F:$F,">="&J$4,Orders!$F:$F,"<"&EDATE(J$4,1)) -> 0 | K56: =SUMIFS(Orders!$L:$L,Orders!$D:$D,$A56,Orders!$F:$F,">="&K$4,Orders!$F:$F,"<"&EDATE(K$4,1)) -> 0 | L56: =SUMIFS(Orders!$L:$L,Orders!$D:$D,$A56,Orders!$F:$F,">="&L$4,Orders!$F:$F,"<"&EDATE(L$4,1)) -> 0 | M56: =N56-J56-K56-L56 -> 0 | N56: =SUMIFS(Orders!$L:$L,Orders!$D:$D,$A56) -> 0 | O56: =H56+N56 -> 220 | P56: 20 | Q56: =IF(SUMIFS('Sales History'!$E:$E,'Sales History'!$G:$G,$A56)>0,SUMIFS('Sales History'!$E:$E,'Sales History'!$G:$G,$A56)/Settings!$B$4,N(P56)) -> 20 | R56: =IF(SUMIFS('Sales History'!$E:$E,'Sales History'!$G:$G,$A56)>0,"6-month history",IF(N(P56)>0,"Current sheet","No sales data")) -> Current sheet | S56: =IF(Q56>0,H56/Q56,"") -> 11 | U56: =IF(T56="","",MAX(0,T56-O56)) | V56: =IF(D56="End of range","END OF RANGE",IF(T56="","NO BUFFER SET",IF(H56<=0,IF(O56<T56,"OUT - REORDER","OUT - ON ORDER"),IF(O56<T56,"REORDER",IF(H56<T56,"LOW - ON ORDER",IF(AND(S56<>"",N(S56)>Settings!$B$5),"SLOW MOVER","OK")))))) -> END OF RANGE | X56: =IF(OR(D56="End of range",U56=""),0,IF(N(U56)>0,U56+ROW()/1000000,0)) -> 0
A57: WOO022 | B57: WOODLAND SPICE (CRICKET PRINT) | C57: Hide | D57: End of range | E57: =SUMIFS('CPT Count'!$D:$D,'CPT Count'!$A:$A,$A57)-SUMIFS('Weekly Sales'!$F:$F,'Weekly Sales'!$H:$H,$A57,'Weekly Sales'!$I:$I,"CPT")+SUMIFS(Transfers!$F:$F,Transfers!$C:$C,$A57,Transfers!$J:$J,"CPT")-SUMIFS(Transfers!$F:$F,Transfers!$C:$C,$A57,Transfers!$I:$I,"CPT",Transfers!$H:$H,"<>Y")+SUMIFS('Stock Received'!$I:$I,'Stock Received'!$E:$E,$A57,'Stock Received'!$L:$L,"CPT") -> 440 | F57: =SUMIFS('JHB Count'!$E:$E,'JHB Count'!$F:$F,$A57)-SUMIFS('Weekly Sales'!$F:$F,'Weekly Sales'!$H:$H,$A57,'Weekly Sales'!$I:$I,"JHB")+SUMIFS(Transfers!$F:$F,Transfers!$C:$C,$A57,Transfers!$J:$J,"JHB")-SUMIFS(Transfers!$F:$F,Transfers!$C:$C,$A57,Transfers!$I:$I,"JHB",Transfers!$H:$H,"<>Y")+SUMIFS('Stock Received'!$I:$I,'Stock Received'!$E:$E,$A57,'Stock Received'!$L:$L,"JHB") -> 4 | G57: =SUMIFS('DBN Count'!$D:$D,'DBN Count'!$E:$E,$A57)-SUMIFS('Weekly Sales'!$F:$F,'Weekly Sales'!$H:$H,$A57,'Weekly Sales'!$I:$I,"DBN")+SUMIFS(Transfers!$F:$F,Transfers!$C:$C,$A57,Transfers!$J:$J,"DBN")-SUMIFS(Transfers!$F:$F,Transfers!$C:$C,$A57,Transfers!$I:$I,"DBN",Transfers!$H:$H,"<>Y")+SUMIFS('Stock Received'!$I:$I,'Stock Received'!$E:$E,$A57,'Stock Received'!$L:$L,"DBN") -> 4.54 | H57: =E57+F57+G57 -> 448.54 | I57: =SUMIFS('Weekly Sales'!$F:$F,'Weekly Sales'!$H:$H,$A57) -> 0 | J57: =SUMIFS(Orders!$L:$L,Orders!$D:$D,$A57,Orders!$F:$F,">="&J$4,Orders!$F:$F,"<"&EDATE(J$4,1)) -> 0 | K57: =SUMIFS(Orders!$L:$L,Orders!$D:$D,$A57,Orders!$F:$F,">="&K$4,Orders!$F:$F,"<"&EDATE(K$4,1)) -> 0 | L57: =SUMIFS(Orders!$L:$L,Orders!$D:$D,$A57,Orders!$F:$F,">="&L$4,Orders!$F:$F,"<"&EDATE(L$4,1)) -> 0 | M57: =N57-J57-K57-L57 -> 0 | N57: =SUMIFS(Orders!$L:$L,Orders!$D:$D,$A57) -> 0 | O57: =H57+N57 -> 448.54 | P57: 20 | Q57: =IF(SUMIFS('Sales History'!$E:$E,'Sales History'!$G:$G,$A57)>0,SUMIFS('Sales History'!$E:$E,'Sales History'!$G:$G,$A57)/Settings!$B$4,N(P57)) -> 20 | R57: =IF(SUMIFS('Sales History'!$E:$E,'Sales History'!$G:$G,$A57)>0,"6-month history",IF(N(P57)>0,"Current sheet","No sales data")) -> Current sheet | S57: =IF(Q57>0,H57/Q57,"") -> 22.427 | U57: =IF(T57="","",MAX(0,T57-O57)) | V57: =IF(D57="End of range","END OF RANGE",IF(T57="","NO BUFFER SET",IF(H57<=0,IF(O57<T57,"OUT - REORDER","OUT - ON ORDER"),IF(O57<T57,"REORDER",IF(H57<T57,"LOW - ON ORDER",IF(AND(S57<>"",N(S57)>Settings!$B$5),"SLOW MOVER","OK")))))) -> END OF RANGE | X57: =IF(OR(D57="End of range",U57=""),0,IF(N(U57)>0,U57+ROW()/1000000,0)) -> 0
A58: NAV004 | B58: NAVADA BLACK | C58: Hide | D58: Active | E58: =SUMIFS('CPT Count'!$D:$D,'CPT Count'!$A:$A,$A58)-SUMIFS('Weekly Sales'!$F:$F,'Weekly Sales'!$H:$H,$A58,'Weekly Sales'!$I:$I,"CPT")+SUMIFS(Transfers!$F:$F,Transfers!$C:$C,$A58,Transfers!$J:$J,"CPT")-SUMIFS(Transfers!$F:$F,Transfers!$C:$C,$A58,Transfers!$I:$I,"CPT",Transfers!$H:$H,"<>Y")+SUMIFS('Stock Received'!$I:$I,'Stock Received'!$E:$E,$A58,'Stock Received'!$L:$L,"CPT") -> 351.82 | F58: =SUMIFS('JHB Count'!$E:$E,'JHB Count'!$F:$F,$A58)-SUMIFS('Weekly Sales'!$F:$F,'Weekly Sales'!$H:$H,$A58,'Weekly Sales'!$I:$I,"JHB")+SUMIFS(Transfers!$F:$F,Transfers!$C:$C,$A58,Transfers!$J:$J,"JHB")-SUMIFS(Transfers!$F:$F,Transfers!$C:$C,$A58,Transfers!$I:$I,"JHB",Transfers!$H:$H,"<>Y")+SUMIFS('Stock Received'!$I:$I,'Stock Received'!$E:$E,$A58,'Stock Received'!$L:$L,"JHB") -> -0.03 | G58: =SUMIFS('DBN Count'!$D:$D,'DBN Count'!$E:$E,$A58)-SUMIFS('Weekly Sales'!$F:$F,'Weekly Sales'!$H:$H,$A58,'Weekly Sales'!$I:$I,"DBN")+SUMIFS(Transfers!$F:$F,Transfers!$C:$C,$A58,Transfers!$J:$J,"DBN")-SUMIFS(Transfers!$F:$F,Transfers!$C:$C,$A58,Transfers!$I:$I,"DBN",Transfers!$H:$H,"<>Y")+SUMIFS('Stock Received'!$I:$I,'Stock Received'!$E:$E,$A58,'Stock Received'!$L:$L,"DBN") -> 18.01 | H58: =E58+F58+G58 -> 369.8 | I58: =SUMIFS('Weekly Sales'!$F:$F,'Weekly Sales'!$H:$H,$A58) -> 104.95 | J58: =SUMIFS(Orders!$L:$L,Orders!$D:$D,$A58,Orders!$F:$F,">="&J$4,Orders!$F:$F,"<"&EDATE(J$4,1)) -> 0 | K58: =SUMIFS(Orders!$L:$L,Orders!$D:$D,$A58,Orders!$F:$F,">="&K$4,Orders!$F:$F,"<"&EDATE(K$4,1)) -> 0 | L58: =SUMIFS(Orders!$L:$L,Orders!$D:$D,$A58,Orders!$F:$F,">="&L$4,Orders!$F:$F,"<"&EDATE(L$4,1)) -> 300 | M58: =N58-J58-K58-L58 -> 0 | N58: =SUMIFS(Orders!$L:$L,Orders!$D:$D,$A58) -> 300 | O58: =H58+N58 -> 669.8 | P58: 140 | Q58: =IF(SUMIFS('Sales History'!$E:$E,'Sales History'!$G:$G,$A58)>0,SUMIFS('Sales History'!$E:$E,'Sales History'!$G:$G,$A58)/Settings!$B$4,N(P58)) -> 140 | R58: =IF(SUMIFS('Sales History'!$E:$E,'Sales History'!$G:$G,$A58)>0,"6-month history",IF(N(P58)>0,"Current sheet","No sales data")) -> Current sheet | S58: =IF(Q58>0,H58/Q58,"") -> 2.6414286 | T58: 300 | U58: =IF(T58="","",MAX(0,T58-O58)) -> 0 | V58: =IF(D58="End of range","END OF RANGE",IF(T58="","NO BUFFER SET",IF(H58<=0,IF(O58<T58,"OUT - REORDER","OUT - ON ORDER"),IF(O58<T58,"REORDER",IF(H58<T58,"LOW - ON ORDER",IF(AND(S58<>"",N(S58)>Settings!$B$5),"SLOW MOVER","OK")))))) -> OK | X58: =IF(OR(D58="End of range",U58=""),0,IF(N(U58)>0,U58+ROW()/1000000,0)) -> 0
A59: NAV005 | B59: NAVADA TAN | C59: Hide | D59: Active | E59: =SUMIFS('CPT Count'!$D:$D,'CPT Count'!$A:$A,$A59)-SUMIFS('Weekly Sales'!$F:$F,'Weekly Sales'!$H:$H,$A59,'Weekly Sales'!$I:$I,"CPT")+SUMIFS(Transfers!$F:$F,Transfers!$C:$C,$A59,Transfers!$J:$J,"CPT")-SUMIFS(Transfers!$F:$F,Transfers!$C:$C,$A59,Transfers!$I:$I,"CPT",Transfers!$H:$H,"<>Y")+SUMIFS('Stock Received'!$I:$I,'Stock Received'!$E:$E,$A59,'Stock Received'!$L:$L,"CPT") -> 260 | F59: =SUMIFS('JHB Count'!$E:$E,'JHB Count'!$F:$F,$A59)-SUMIFS('Weekly Sales'!$F:$F,'Weekly Sales'!$H:$H,$A59,'Weekly Sales'!$I:$I,"JHB")+SUMIFS(Transfers!$F:$F,Transfers!$C:$C,$A59,Transfers!$J:$J,"JHB")-SUMIFS(Transfers!$F:$F,Transfers!$C:$C,$A59,Transfers!$I:$I,"JHB",Transfers!$H:$H,"<>Y")+SUMIFS('Stock Received'!$I:$I,'Stock Received'!$E:$E,$A59,'Stock Received'!$L:$L,"JHB") -> 29.03 | G59: =SUMIFS('DBN Count'!$D:$D,'DBN Count'!$E:$E,$A59)-SUMIFS('Weekly Sales'!$F:$F,'Weekly Sales'!$H:$H,$A59,'Weekly Sales'!$I:$I,"DBN")+SUMIFS(Transfers!$F:$F,Transfers!$C:$C,$A59,Transfers!$J:$J,"DBN")-SUMIFS(Transfers!$F:$F,Transfers!$C:$C,$A59,Transfers!$I:$I,"DBN",Transfers!$H:$H,"<>Y")+SUMIFS('Stock Received'!$I:$I,'Stock Received'!$E:$E,$A59,'Stock Received'!$L:$L,"DBN") -> 36.62 | H59: =E59+F59+G59 -> 325.65 | I59: =SUMIFS('Weekly Sales'!$F:$F,'Weekly Sales'!$H:$H,$A59) -> 30.97 | J59: =SUMIFS(Orders!$L:$L,Orders!$D:$D,$A59,Orders!$F:$F,">="&J$4,Orders!$F:$F,"<"&EDATE(J$4,1)) -> 0 | K59: =SUMIFS(Orders!$L:$L,Orders!$D:$D,$A59,Orders!$F:$F,">="&K$4,Orders!$F:$F,"<"&EDATE(K$4,1)) -> 0 | L59: =SUMIFS(Orders!$L:$L,Orders!$D:$D,$A59,Orders!$F:$F,">="&L$4,Orders!$F:$F,"<"&EDATE(L$4,1)) -> 200 | M59: =N59-J59-K59-L59 -> 0 | N59: =SUMIFS(Orders!$L:$L,Orders!$D:$D,$A59) -> 200 | O59: =H59+N59 -> 525.65 | P59: 55 | Q59: =IF(SUMIFS('Sales History'!$E:$E,'Sales History'!$G:$G,$A59)>0,SUMIFS('Sales History'!$E:$E,'Sales History'!$G:$G,$A59)/Settings!$B$4,N(P59)) -> 55 | R59: =IF(SUMIFS('Sales History'!$E:$E,'Sales History'!$G:$G,$A59)>0,"6-month history",IF(N(P59)>0,"Current sheet","No sales data")) -> Current sheet | S59: =IF(Q59>0,H59/Q59,"") -> 5.9209091 | T59: 200 | U59: =IF(T59="","",MAX(0,T59-O59)) -> 0 | V59: =IF(D59="End of range","END OF RANGE",IF(T59="","NO BUFFER SET",IF(H59<=0,IF(O59<T59,"OUT - REORDER","OUT - ON ORDER"),IF(O59<T59,"REORDER",IF(H59<T59,"LOW - ON ORDER",IF(AND(S59<>"",N(S59)>Settings!$B$5),"SLOW MOVER","OK")))))) -> OK | X59: =IF(OR(D59="End of range",U59=""),0,IF(N(U59)>0,U59+ROW()/1000000,0)) -> 0
A60: NAV006 | B60: NAVADA BROWN | C60: Hide | D60: Active | E60: =SUMIFS('CPT Count'!$D:$D,'CPT Count'!$A:$A,$A60)-SUMIFS('Weekly Sales'!$F:$F,'Weekly Sales'!$H:$H,$A60,'Weekly Sales'!$I:$I,"CPT")+SUMIFS(Transfers!$F:$F,Transfers!$C:$C,$A60,Transfers!$J:$J,"CPT")-SUMIFS(Transfers!$F:$F,Transfers!$C:$C,$A60,Transfers!$I:$I,"CPT",Transfers!$H:$H,"<>Y")+SUMIFS('Stock Received'!$I:$I,'Stock Received'!$E:$E,$A60,'Stock Received'!$L:$L,"CPT") -> 760 | F60: =SUMIFS('JHB Count'!$E:$E,'JHB Count'!$F:$F,$A60)-SUMIFS('Weekly Sales'!$F:$F,'Weekly Sales'!$H:$H,$A60,'Weekly Sales'!$I:$I,"JHB")+SUMIFS(Transfers!$F:$F,Transfers!$C:$C,$A60,Transfers!$J:$J,"JHB")-SUMIFS(Transfers!$F:$F,Transfers!$C:$C,$A60,Transfers!$I:$I,"JHB",Transfers!$H:$H,"<>Y")+SUMIFS('Stock Received'!$I:$I,'Stock Received'!$E:$E,$A60,'Stock Received'!$L:$L,"JHB") -> 52.24 | G60: =SUMIFS('DBN Count'!$D:$D,'DBN Count'!$E:$E,$A60)-SUMIFS('Weekly Sales'!$F:$F,'Weekly Sales'!$H:$H,$A60,'Weekly Sales'!$I:$I,"DBN")+SUMIFS(Transfers!$F:$F,Transfers!$C:$C,$A60,Transfers!$J:$J,"DBN")-SUMIFS(Transfers!$F:$F,Transfers!$C:$C,$A60,Transfers!$I:$I,"DBN",Transfers!$H:$H,"<>Y")+SUMIFS('Stock Received'!$I:$I,'Stock Received'!$E:$E,$A60,'Stock Received'!$L:$L,"DBN") -> 0 | H60: =E60+F60+G60 -> 812.24 | I60: =SUMIFS('Weekly Sales'!$F:$F,'Weekly Sales'!$H:$H,$A60) -> 3.76 | J60: =SUMIFS(Orders!$L:$L,Orders!$D:$D,$A60,Orders!$F:$F,">="&J$4,Orders!$F:$F,"<"&EDATE(J$4,1)) -> 0 | K60: =SUMIFS(Orders!$L:$L,Orders!$D:$D,$A60,Orders!$F:$F,">="&K$4,Orders!$F:$F,"<"&EDATE(K$4,1)) -> 0 | L60: =SUMIFS(Orders!$L:$L,Orders!$D:$D,$A60,Orders!$F:$F,">="&L$4,Orders!$F:$F,"<"&EDATE(L$4,1)) -> 0 | M60: =N60-J60-K60-L60 -> 0 | N60: =SUMIFS(Orders!$L:$L,Orders!$D:$D,$A60) -> 0 | O60: =H60+N60 -> 812.24 | P60: 40 | Q60: =IF(SUMIFS('Sales History'!$E:$E,'Sales History'!$G:$G,$A60)>0,SUMIFS('Sales History'!$E:$E,'Sales History'!$G:$G,$A60)/Settings!$B$4,N(P60)) -> 40 | R60: =IF(SUMIFS('Sales History'!$E:$E,'Sales History'!$G:$G,$A60)>0,"6-month history",IF(N(P60)>0,"Current sheet","No sales data")) -> Current sheet | S60: =IF(Q60>0,H60/Q60,"") -> 20.306 | T60: 200 | U60: =IF(T60="","",MAX(0,T60-O60)) -> 0 | V60: =IF(D60="End of range","END OF RANGE",IF(T60="","NO BUFFER SET",IF(H60<=0,IF(O60<T60,"OUT - REORDER","OUT - ON ORDER"),IF(O60<T60,"REORDER",IF(H60<T60,"LOW - ON ORDER",IF(AND(S60<>"",N(S60)>Settings!$B$5),"SLOW MOVER","OK")))))) -> SLOW MOVER | X60: =IF(OR(D60="End of range",U60=""),0,IF(N(U60)>0,U60+ROW()/1000000,0)) -> 0
A61: NAV001 | B61: NAVADA CERISE/PINK | C61: Hide | D61: Active | E61: =SUMIFS('CPT Count'!$D:$D,'CPT Count'!$A:$A,$A61)-SUMIFS('Weekly Sales'!$F:$F,'Weekly Sales'!$H:$H,$A61,'Weekly Sales'!$I:$I,"CPT")+SUMIFS(Transfers!$F:$F,Transfers!$C:$C,$A61,Transfers!$J:$J,"CPT")-SUMIFS(Transfers!$F:$F,Transfers!$C:$C,$A61,Transfers!$I:$I,"CPT",Transfers!$H:$H,"<>Y")+SUMIFS('Stock Received'!$I:$I,'Stock Received'!$E:$E,$A61,'Stock Received'!$L:$L,"CPT") -> 57 | F61: =SUMIFS('JHB Count'!$E:$E,'JHB Count'!$F:$F,$A61)-SUMIFS('Weekly Sales'!$F:$F,'Weekly Sales'!$H:$H,$A61,'Weekly Sales'!$I:$I,"JHB")+SUMIFS(Transfers!$F:$F,Transfers!$C:$C,$A61,Transfers!$J:$J,"JHB")-SUMIFS(Transfers!$F:$F,Transfers!$C:$C,$A61,Transfers!$I:$I,"JHB",Transfers!$H:$H,"<>Y")+SUMIFS('Stock Received'!$I:$I,'Stock Received'!$E:$E,$A61,'Stock Received'!$L:$L,"JHB") -> 36.27 | G61: =SUMIFS('DBN Count'!$D:$D,'DBN Count'!$E:$E,$A61)-SUMIFS('Weekly Sales'!$F:$F,'Weekly Sales'!$H:$H,$A61,'Weekly Sales'!$I:$I,"DBN")+SUMIFS(Transfers!$F:$F,Transfers!$C:$C,$A61,Transfers!$J:$J,"DBN")-SUMIFS(Transfers!$F:$F,Transfers!$C:$C,$A61,Transfers!$I:$I,"DBN",Transfers!$H:$H,"<>Y")+SUMIFS('Stock Received'!$I:$I,'Stock Received'!$E:$E,$A61,'Stock Received'!$L:$L,"DBN") -> 3.59 | H61: =E61+F61+G61 -> 96.86 | I61: =SUMIFS('Weekly Sales'!$F:$F,'Weekly Sales'!$H:$H,$A61) -> 22.73 | J61: =SUMIFS(Orders!$L:$L,Orders!$D:$D,$A61,Orders!$F:$F,">="&J$4,Orders!$F:$F,"<"&EDATE(J$4,1)) -> 0 | K61: =SUMIFS(Orders!$L:$L,Orders!$D:$D,$A61,Orders!$F:$F,">="&K$4,Orders!$F:$F,"<"&EDATE(K$4,1)) -> 300 | L61: =SUMIFS(Orders!$L:$L,Orders!$D:$D,$A61,Orders!$F:$F,">="&L$4,Orders!$F:$F,"<"&EDATE(L$4,1)) -> 0 | M61: =N61-J61-K61-L61 -> 0 | N61: =SUMIFS(Orders!$L:$L,Orders!$D:$D,$A61) -> 300 | O61: =H61+N61 -> 396.86 | P61: 55 | Q61: =IF(SUMIFS('Sales History'!$E:$E,'Sales History'!$G:$G,$A61)>0,SUMIFS('Sales History'!$E:$E,'Sales History'!$G:$G,$A61)/Settings!$B$4,N(P61)) -> 55 | R61: =IF(SUMIFS('Sales History'!$E:$E,'Sales History'!$G:$G,$A61)>0,"6-month history",IF(N(P61)>0,"Current sheet","No sales data")) -> Current sheet | S61: =IF(Q61>0,H61/Q61,"") -> 1.7610909 | T61: 200 | U61: =IF(T61="","",MAX(0,T61-O61)) -> 0 | V61: =IF(D61="End of range","END OF RANGE",IF(T61="","NO BUFFER SET",IF(H61<=0,IF(O61<T61,"OUT - REORDER","OUT - ON ORDER"),IF(O61<T61,"REORDER",IF(H61<T61,"LOW - ON ORDER",IF(AND(S61<>"",N(S61)>Settings!$B$5),"SLOW MOVER","OK")))))) -> LOW - ON ORDER | X61: =IF(OR(D61="End of range",U61=""),0,IF(N(U61)>0,U61+ROW()/1000000,0)) -> 0
A62: ETO004 | B62: ETOSHA DARK ANTHRACITE | C62: Hide | D62: Active | E62: =SUMIFS('CPT Count'!$D:$D,'CPT Count'!$A:$A,$A62)-SUMIFS('Weekly Sales'!$F:$F,'Weekly Sales'!$H:$H,$A62,'Weekly Sales'!$I:$I,"CPT")+SUMIFS(Transfers!$F:$F,Transfers!$C:$C,$A62,Transfers!$J:$J,"CPT")-SUMIFS(Transfers!$F:$F,Transfers!$C:$C,$A62,Transfers!$I:$I,"CPT",Transfers!$H:$H,"<>Y")+SUMIFS('Stock Received'!$I:$I,'Stock Received'!$E:$E,$A62,'Stock Received'!$L:$L,"CPT") -> 69.01 | F62: =SUMIFS('JHB Count'!$E:$E,'JHB Count'!$F:$F,$A62)-SUMIFS('Weekly Sales'!$F:$F,'Weekly Sales'!$H:$H,$A62,'Weekly Sales'!$I:$I,"JHB")+SUMIFS(Transfers!$F:$F,Transfers!$C:$C,$A62,Transfers!$J:$J,"JHB")-SUMIFS(Transfers!$F:$F,Transfers!$C:$C,$A62,Transfers!$I:$I,"JHB",Transfers!$H:$H,"<>Y")+SUMIFS('Stock Received'!$I:$I,'Stock Received'!$E:$E,$A62,'Stock Received'!$L:$L,"JHB") -> 148 | G62: =SUMIFS('DBN Count'!$D:$D,'DBN Count'!$E:$E,$A62)-SUMIFS('Weekly Sales'!$F:$F,'Weekly Sales'!$H:$H,$A62,'Weekly Sales'!$I:$I,"DBN")+SUMIFS(Transfers!$F:$F,Transfers!$C:$C,$A62,Transfers!$J:$J,"DBN")-SUMIFS(Transfers!$F:$F,Transfers!$C:$C,$A62,Transfers!$I:$I,"DBN",Transfers!$H:$H,"<>Y")+SUMIFS('Stock Received'!$I:$I,'Stock Received'!$E:$E,$A62,'Stock Received'!$L:$L,"DBN") -> 0 | H62: =E62+F62+G62 -> 217.01 | I62: =SUMIFS('Weekly Sales'!$F:$F,'Weekly Sales'!$H:$H,$A62) -> 11.99 | J62: =SUMIFS(Orders!$L:$L,Orders!$D:$D,$A62,Orders!$F:$F,">="&J$4,Orders!$F:$F,"<"&EDATE(J$4,1)) -> 300 | K62: =SUMIFS(Orders!$L:$L,Orders!$D:$D,$A62,Orders!$F:$F,">="&K$4,Orders!$F:$F,"<"&EDATE(K$4,1)) -> 0 | L62: =SUMIFS(Orders!$L:$L,Orders!$D:$D,$A62,Orders!$F:$F,">="&L$4,Orders!$F:$F,"<"&EDATE(L$4,1)) -> 300 | M62: =N62-J62-K62-L62 -> 0 | N62: =SUMIFS(Orders!$L:$L,Orders!$D:$D,$A62) -> 600 | O62: =H62+N62 -> 817.01 | P62: 105 | Q62: =IF(SUMIFS('Sales History'!$E:$E,'Sales History'!$G:$G,$A62)>0,SUMIFS('Sales History'!$E:$E,'Sales History'!$G:$G,$A62)/Settings!$B$4,N(P62)) -> 105 | R62: =IF(SUMIFS('Sales History'!$E:$E,'Sales History'!$G:$G,$A62)>0,"6-month history",IF(N(P62)>0,"Current sheet","No sales data")) -> Current sheet | S62: =IF(Q62>0,H62/Q62,"") -> 2.0667619 | T62: 300 | U62: =IF(T62="","",MAX(0,T62-O62)) -> 0 | V62: =IF(D62="End of range","END OF RANGE",IF(T62="","NO BUFFER SET",IF(H62<=0,IF(O62<T62,"OUT - REORDER","OUT - ON ORDER"),IF(O62<T62,"REORDER",IF(H62<T62,"LOW - ON ORDER",IF(AND(S62<>"",N(S62)>Settings!$B$5),"SLOW MOVER","OK")))))) -> LOW - ON ORDER | X62: =IF(OR(D62="End of range",U62=""),0,IF(N(U62)>0,U62+ROW()/1000000,0)) -> 0
A63: ETO002 | B63: ETOSHA PECAN | C63: Hide | D63: Active | E63: =SUMIFS('CPT Count'!$D:$D,'CPT Count'!$A:$A,$A63)-SUMIFS('Weekly Sales'!$F:$F,'Weekly Sales'!$H:$H,$A63,'Weekly Sales'!$I:$I,"CPT")+SUMIFS(Transfers!$F:$F,Transfers!$C:$C,$A63,Transfers!$J:$J,"CPT")-SUMIFS(Transfers!$F:$F,Transfers!$C:$C,$A63,Transfers!$I:$I,"CPT",Transfers!$H:$H,"<>Y")+SUMIFS('Stock Received'!$I:$I,'Stock Received'!$E:$E,$A63,'Stock Received'!$L:$L,"CPT") -> 2423.13 | F63: =SUMIFS('JHB Count'!$E:$E,'JHB Count'!$F:$F,$A63)-SUMIFS('Weekly Sales'!$F:$F,'Weekly Sales'!$H:$H,$A63,'Weekly Sales'!$I:$I,"JHB")+SUMIFS(Transfers!$F:$F,Transfers!$C:$C,$A63,Transfers!$J:$J,"JHB")-SUMIFS(Transfers!$F:$F,Transfers!$C:$C,$A63,Transfers!$I:$I,"JHB",Transfers!$H:$H,"<>Y")+SUMIFS('Stock Received'!$I:$I,'Stock Received'!$E:$E,$A63,'Stock Received'!$L:$L,"JHB") -> 147.04 | G63: =SUMIFS('DBN Count'!$D:$D,'DBN Count'!$E:$E,$A63)-SUMIFS('Weekly Sales'!$F:$F,'Weekly Sales'!$H:$H,$A63,'Weekly Sales'!$I:$I,"DBN")+SUMIFS(Transfers!$F:$F,Transfers!$C:$C,$A63,Transfers!$J:$J,"DBN")-SUMIFS(Transfers!$F:$F,Transfers!$C:$C,$A63,Transfers!$I:$I,"DBN",Transfers!$H:$H,"<>Y")+SUMIFS('Stock Received'!$I:$I,'Stock Received'!$E:$E,$A63,'Stock Received'!$L:$L,"DBN") -> 115.9 | H63: =E63+F63+G63 -> 2686.07 | I63: =SUMIFS('Weekly Sales'!$F:$F,'Weekly Sales'!$H:$H,$A63) -> 224.83 | J63: =SUMIFS(Orders!$L:$L,Orders!$D:$D,$A63,Orders!$F:$F,">="&J$4,Orders!$F:$F,"<"&EDATE(J$4,1)) -> 0 | K63: =SUMIFS(Orders!$L:$L,Orders!$D:$D,$A63,Orders!$F:$F,">="&K$4,Orders!$F:$F,"<"&EDATE(K$4,1)) -> 1500 | L63: =SUMIFS(Orders!$L:$L,Orders!$D:$D,$A63,Orders!$F:$F,">="&L$4,Orders!$F:$F,"<"&EDATE(L$4,1)) -> 0 | M63: =N63-J63-K63-L63 -> 0 | N63: =SUMIFS(Orders!$L:$L,Orders!$D:$D,$A63) -> 1500 | O63: =H63+N63 -> 4186.07 | P63: 1000 | Q63: =IF(SUMIFS('Sales History'!$E:$E,'Sales History'!$G:$G,$A63)>0,SUMIFS('Sales History'!$E:$E,'Sales History'!$G:$G,$A63)/Settings!$B$4,N(P63)) -> 1000 | R63: =IF(SUMIFS('Sales History'!$E:$E,'Sales History'!$G:$G,$A63)>0,"6-month history",IF(N(P63)>0,"Current sheet","No sales data")) -> Current sheet | S63: =IF(Q63>0,H63/Q63,"") -> 2.68607 | T63: 3000 | U63: =IF(T63="","",MAX(0,T63-O63)) -> 0 | V63: =IF(D63="End of range","END OF RANGE",IF(T63="","NO BUFFER SET",IF(H63<=0,IF(O63<T63,"OUT - REORDER","OUT - ON ORDER"),IF(O63<T63,"REORDER",IF(H63<T63,"LOW - ON ORDER",IF(AND(S63<>"",N(S63)>Settings!$B$5),"SLOW MOVER","OK")))))) -> LOW - ON ORDER | X63: =IF(OR(D63="End of range",U63=""),0,IF(N(U63)>0,U63+ROW()/1000000,0)) -> 0
A64: ETO003 | B64: ETOSHA CHESTNUT | C64: Hide | D64: Active | E64: =SUMIFS('CPT Count'!$D:$D,'CPT Count'!$A:$A,$A64)-SUMIFS('Weekly Sales'!$F:$F,'Weekly Sales'!$H:$H,$A64,'Weekly Sales'!$I:$I,"CPT")+SUMIFS(Transfers!$F:$F,Transfers!$C:$C,$A64,Transfers!$J:$J,"CPT")-SUMIFS(Transfers!$F:$F,Transfers!$C:$C,$A64,Transfers!$I:$I,"CPT",Transfers!$H:$H,"<>Y")+SUMIFS('Stock Received'!$I:$I,'Stock Received'!$E:$E,$A64,'Stock Received'!$L:$L,"CPT") -> 256.96 | F64: =SUMIFS('JHB Count'!$E:$E,'JHB Count'!$F:$F,$A64)-SUMIFS('Weekly Sales'!$F:$F,'Weekly Sales'!$H:$H,$A64,'Weekly Sales'!$I:$I,"JHB")+SUMIFS(Transfers!$F:$F,Transfers!$C:$C,$A64,Transfers!$J:$J,"JHB")-SUMIFS(Transfers!$F:$F,Transfers!$C:$C,$A64,Transfers!$I:$I,"JHB",Transfers!$H:$H,"<>Y")+SUMIFS('Stock Received'!$I:$I,'Stock Received'!$E:$E,$A64,'Stock Received'!$L:$L,"JHB") -> 264 | G64: =SUMIFS('DBN Count'!$D:$D,'DBN Count'!$E:$E,$A64)-SUMIFS('Weekly Sales'!$F:$F,'Weekly Sales'!$H:$H,$A64,'Weekly Sales'!$I:$I,"DBN")+SUMIFS(Transfers!$F:$F,Transfers!$C:$C,$A64,Transfers!$J:$J,"DBN")-SUMIFS(Transfers!$F:$F,Transfers!$C:$C,$A64,Transfers!$I:$I,"DBN",Transfers!$H:$H,"<>Y")+SUMIFS('Stock Received'!$I:$I,'Stock Received'!$E:$E,$A64,'Stock Received'!$L:$L,"DBN") -> 31.24 | H64: =E64+F64+G64 -> 552.2 | I64: =SUMIFS('Weekly Sales'!$F:$F,'Weekly Sales'!$H:$H,$A64) -> 386.67 | J64: =SUMIFS(Orders!$L:$L,Orders!$D:$D,$A64,Orders!$F:$F,">="&J$4,Orders!$F:$F,"<"&EDATE(J$4,1)) -> 500 | K64: =SUMIFS(Orders!$L:$L,Orders!$D:$D,$A64,Orders!$F:$F,">="&K$4,Orders!$F:$F,"<"&EDATE(K$4,1)) -> 1500 | L64: =SUMIFS(Orders!$L:$L,Orders!$D:$D,$A64,Orders!$F:$F,">="&L$4,Orders!$F:$F,"<"&EDATE(L$4,1)) -> 500 | M64: =N64-J64-K64-L64 -> 0 | N64: =SUMIFS(Orders!$L:$L,Orders!$D:$D,$A64) -> 2500 | O64: =H64+N64 -> 3052.2 | P64: 550 | Q64: =IF(SUMIFS('Sales History'!$E:$E,'Sales History'!$G:$G,$A64)>0,SUMIFS('Sales History'!$E:$E,'Sales History'!$G:$G,$A64)/Settings!$B$4,N(P64)) -> 550 | R64: =IF(SUMIFS('Sales History'!$E:$E,'Sales History'!$G:$G,$A64)>0,"6-month history",IF(N(P64)>0,"Current sheet","No sales data")) -> Current sheet | S64: =IF(Q64>0,H64/Q64,"") -> 1.004 | T64: 1500 | U64: =IF(T64="","",MAX(0,T64-O64)) -> 0 | V64: =IF(D64="End of range","END OF RANGE",IF(T64="","NO BUFFER SET",IF(H64<=0,IF(O64<T64,"OUT - REORDER","OUT - ON ORDER"),IF(O64<T64,"REORDER",IF(H64<T64,"LOW - ON ORDER",IF(AND(S64<>"",N(S64)>Settings!$B$5),"SLOW MOVER","OK")))))) -> LOW - ON ORDER | X64: =IF(OR(D64="End of range",U64=""),0,IF(N(U64)>0,U64+ROW()/1000000,0)) -> 0
A65: ETO001 | B65: ETOSHA RUST | C65: Hide | D65: Active | E65: =SUMIFS('CPT Count'!$D:$D,'CPT Count'!$A:$A,$A65)-SUMIFS('Weekly Sales'!$F:$F,'Weekly Sales'!$H:$H,$A65,'Weekly Sales'!$I:$I,"CPT")+SUMIFS(Transfers!$F:$F,Transfers!$C:$C,$A65,Transfers!$J:$J,"CPT")-SUMIFS(Transfers!$F:$F,Transfers!$C:$C,$A65,Transfers!$I:$I,"CPT",Transfers!$H:$H,"<>Y")+SUMIFS('Stock Received'!$I:$I,'Stock Received'!$E:$E,$A65,'Stock Received'!$L:$L,"CPT") -> 165.03 | F65: =SUMIFS('JHB Count'!$E:$E,'JHB Count'!$F:$F,$A65)-SUMIFS('Weekly Sales'!$F:$F,'Weekly Sales'!$H:$H,$A65,'Weekly Sales'!$I:$I,"JHB")+SUMIFS(Transfers!$F:$F,Transfers!$C:$C,$A65,Transfers!$J:$J,"JHB")-SUMIFS(Transfers!$F:$F,Transfers!$C:$C,$A65,Transfers!$I:$I,"JHB",Transfers!$H:$H,"<>Y")+SUMIFS('Stock Received'!$I:$I,'Stock Received'!$E:$E,$A65,'Stock Received'!$L:$L,"JHB") -> 0.04 | G65: =SUMIFS('DBN Count'!$D:$D,'DBN Count'!$E:$E,$A65)-SUMIFS('Weekly Sales'!$F:$F,'Weekly Sales'!$H:$H,$A65,'Weekly Sales'!$I:$I,"DBN")+SUMIFS(Transfers!$F:$F,Transfers!$C:$C,$A65,Transfers!$J:$J,"DBN")-SUMIFS(Transfers!$F:$F,Transfers!$C:$C,$A65,Transfers!$I:$I,"DBN",Transfers!$H:$H,"<>Y")+SUMIFS('Stock Received'!$I:$I,'Stock Received'!$E:$E,$A65,'Stock Received'!$L:$L,"DBN") -> 31.32 | H65: =E65+F65+G65 -> 196.39 | I65: =SUMIFS('Weekly Sales'!$F:$F,'Weekly Sales'!$H:$H,$A65) -> 308.03 | J65: =SUMIFS(Orders!$L:$L,Orders!$D:$D,$A65,Orders!$F:$F,">="&J$4,Orders!$F:$F,"<"&EDATE(J$4,1)) -> 300 | K65: =SUMIFS(Orders!$L:$L,Orders!$D:$D,$A65,Orders!$F:$F,">="&K$4,Orders!$F:$F,"<"&EDATE(K$4,1)) -> 1000 | L65: =SUMIFS(Orders!$L:$L,Orders!$D:$D,$A65,Orders!$F:$F,">="&L$4,Orders!$F:$F,"<"&EDATE(L$4,1)) -> 500 | M65: =N65-J65-K65-L65 -> 0 | N65: =SUMIFS(Orders!$L:$L,Orders!$D:$D,$A65) -> 1800 | O65: =H65+N65 -> 1996.39 | P65: 470 | Q65: =IF(SUMIFS('Sales History'!$E:$E,'Sales History'!$G:$G,$A65)>0,SUMIFS('Sales History'!$E:$E,'Sales History'!$G:$G,$A65)/Settings!$B$4,N(P65)) -> 470 | R65: =IF(SUMIFS('Sales History'!$E:$E,'Sales History'!$G:$G,$A65)>0,"6-month history",IF(N(P65)>0,"Current sheet","No sales data")) -> Current sheet | S65: =IF(Q65>0,H65/Q65,"") -> 0.41785106 | T65: 900 | U65: =IF(T65="","",MAX(0,T65-O65)) -> 0 | V65: =IF(D65="End of range","END OF RANGE",IF(T65="","NO BUFFER SET",IF(H65<=0,IF(O65<T65,"OUT - REORDER","OUT - ON ORDER"),IF(O65<T65,"REORDER",IF(H65<T65,"LOW - ON ORDER",IF(AND(S65<>"",N(S65)>Settings!$B$5),"SLOW MOVER","OK")))))) -> LOW - ON ORDER | X65: =IF(OR(D65="End of range",U65=""),0,IF(N(U65)>0,U65+ROW()/1000000,0)) -> 0
A66: ETO007 | B66: ETOSHA EMERALD | C66: Hide | D66: Active | E66: =SUMIFS('CPT Count'!$D:$D,'CPT Count'!$A:$A,$A66)-SUMIFS('Weekly Sales'!$F:$F,'Weekly Sales'!$H:$H,$A66,'Weekly Sales'!$I:$I,"CPT")+SUMIFS(Transfers!$F:$F,Transfers!$C:$C,$A66,Transfers!$J:$J,"CPT")-SUMIFS(Transfers!$F:$F,Transfers!$C:$C,$A66,Transfers!$I:$I,"CPT",Transfers!$H:$H,"<>Y")+SUMIFS('Stock Received'!$I:$I,'Stock Received'!$E:$E,$A66,'Stock Received'!$L:$L,"CPT") -> 2.66 | F66: =SUMIFS('JHB Count'!$E:$E,'JHB Count'!$F:$F,$A66)-SUMIFS('Weekly Sales'!$F:$F,'Weekly Sales'!$H:$H,$A66,'Weekly Sales'!$I:$I,"JHB")+SUMIFS(Transfers!$F:$F,Transfers!$C:$C,$A66,Transfers!$J:$J,"JHB")-SUMIFS(Transfers!$F:$F,Transfers!$C:$C,$A66,Transfers!$I:$I,"JHB",Transfers!$H:$H,"<>Y")+SUMIFS('Stock Received'!$I:$I,'Stock Received'!$E:$E,$A66,'Stock Received'!$L:$L,"JHB") -> 117.98 | G66: =SUMIFS('DBN Count'!$D:$D,'DBN Count'!$E:$E,$A66)-SUMIFS('Weekly Sales'!$F:$F,'Weekly Sales'!$H:$H,$A66,'Weekly Sales'!$I:$I,"DBN")+SUMIFS(Transfers!$F:$F,Transfers!$C:$C,$A66,Transfers!$J:$J,"DBN")-SUMIFS(Transfers!$F:$F,Transfers!$C:$C,$A66,Transfers!$I:$I,"DBN",Transfers!$H:$H,"<>Y")+SUMIFS('Stock Received'!$I:$I,'Stock Received'!$E:$E,$A66,'Stock Received'!$L:$L,"DBN") -> 17.73 | H66: =E66+F66+G66 -> 138.37 | I66: =SUMIFS('Weekly Sales'!$F:$F,'Weekly Sales'!$H:$H,$A66) -> 211.36 | J66: =SUMIFS(Orders!$L:$L,Orders!$D:$D,$A66,Orders!$F:$F,">="&J$4,Orders!$F:$F,"<"&EDATE(J$4,1)) -> 300 | K66: =SUMIFS(Orders!$L:$L,Orders!$D:$D,$A66,Orders!$F:$F,">="&K$4,Orders!$F:$F,"<"&EDATE(K$4,1)) -> 500 | L66: =SUMIFS(Orders!$L:$L,Orders!$D:$D,$A66,Orders!$F:$F,">="&L$4,Orders!$F:$F,"<"&EDATE(L$4,1)) -> 300 | M66: =N66-J66-K66-L66 -> 0 | N66: =SUMIFS(Orders!$L:$L,Orders!$D:$D,$A66) -> 1100 | O66: =H66+N66 -> 1238.37 | P66: 170 | Q66: =IF(SUMIFS('Sales History'!$E:$E,'Sales History'!$G:$G,$A66)>0,SUMIFS('Sales History'!$E:$E,'Sales History'!$G:$G,$A66)/Settings!$B$4,N(P66)) -> 170 | R66: =IF(SUMIFS('Sales History'!$E:$E,'Sales History'!$G:$G,$A66)>0,"6-month history",IF(N(P66)>0,"Current sheet","No sales data")) -> Current sheet | S66: =IF(Q66>0,H66/Q66,"") -> 0.81394118 | T66: 500 | U66: =IF(T66="","",MAX(0,T66-O66)) -> 0 | V66: =IF(D66="End of range","END OF RANGE",IF(T66="","NO BUFFER SET",IF(H66<=0,IF(O66<T66,"OUT - REORDER","OUT - ON ORDER"),IF(O66<T66,"REORDER",IF(H66<T66,"LOW - ON ORDER",IF(AND(S66<>"",N(S66)>Settings!$B$5),"SLOW MOVER","OK")))))) -> LOW - ON ORDER | X66: =IF(OR(D66="End of range",U66=""),0,IF(N(U66)>0,U66+ROW()/1000000,0)) -> 0
A67: ETO008 | B67: ETOSHA CIGAR | C67: Hide | D67: Active | E67: =SUMIFS('CPT Count'!$D:$D,'CPT Count'!$A:$A,$A67)-SUMIFS('Weekly Sales'!$F:$F,'Weekly Sales'!$H:$H,$A67,'Weekly Sales'!$I:$I,"CPT")+SUMIFS(Transfers!$F:$F,Transfers!$C:$C,$A67,Transfers!$J:$J,"CPT")-SUMIFS(Transfers!$F:$F,Transfers!$C:$C,$A67,Transfers!$I:$I,"CPT",Transfers!$H:$H,"<>Y")+SUMIFS('Stock Received'!$I:$I,'Stock Received'!$E:$E,$A67,'Stock Received'!$L:$L,"CPT") -> 1225.17 | F67: =SUMIFS('JHB Count'!$E:$E,'JHB Count'!$F:$F,$A67)-SUMIFS('Weekly Sales'!$F:$F,'Weekly Sales'!$H:$H,$A67,'Weekly Sales'!$I:$I,"JHB")+SUMIFS(Transfers!$F:$F,Transfers!$C:$C,$A67,Transfers!$J:$J,"JHB")-SUMIFS(Transfers!$F:$F,Transfers!$C:$C,$A67,Transfers!$I:$I,"JHB",Transfers!$H:$H,"<>Y")+SUMIFS('Stock Received'!$I:$I,'Stock Received'!$E:$E,$A67,'Stock Received'!$L:$L,"JHB") -> 0 | G67: =SUMIFS('DBN Count'!$D:$D,'DBN Count'!$E:$E,$A67)-SUMIFS('Weekly Sales'!$F:$F,'Weekly Sales'!$H:$H,$A67,'Weekly Sales'!$I:$I,"DBN")+SUMIFS(Transfers!$F:$F,Transfers!$C:$C,$A67,Transfers!$J:$J,"DBN")-SUMIFS(Transfers!$F:$F,Transfers!$C:$C,$A67,Transfers!$I:$I,"DBN",Transfers!$H:$H,"<>Y")+SUMIFS('Stock Received'!$I:$I,'Stock Received'!$E:$E,$A67,'Stock Received'!$L:$L,"DBN") -> 0 | H67: =E67+F67+G67 -> 1225.17 | I67: =SUMIFS('Weekly Sales'!$F:$F,'Weekly Sales'!$H:$H,$A67) -> 3.68 | J67: =SUMIFS(Orders!$L:$L,Orders!$D:$D,$A67,Orders!$F:$F,">="&J$4,Orders!$F:$F,"<"&EDATE(J$4,1)) -> 0 | K67: =SUMIFS(Orders!$L:$L,Orders!$D:$D,$A67,Orders!$F:$F,">="&K$4,Orders!$F:$F,"<"&EDATE(K$4,1)) -> 500 | L67: =SUMIFS(Orders!$L:$L,Orders!$D:$D,$A67,Orders!$F:$F,">="&L$4,Orders!$F:$F,"<"&EDATE(L$4,1)) -> 0 | M67: =N67-J67-K67-L67 -> 0 | N67: =SUMIFS(Orders!$L:$L,Orders!$D:$D,$A67) -> 500 | O67: =H67+N67 -> 1725.17 | P67: 300 | Q67: =IF(SUMIFS('Sales History'!$E:$E,'Sales History'!$G:$G,$A67)>0,SUMIFS('Sales History'!$E:$E,'Sales History'!$G:$G,$A67)/Settings!$B$4,N(P67)) -> 300 | R67: =IF(SUMIFS('Sales History'!$E:$E,'Sales History'!$G:$G,$A67)>0,"6-month history",IF(N(P67)>0,"Current sheet","No sales data")) -> Current sheet | S67: =IF(Q67>0,H67/Q67,"") -> 4.0839 | T67: 500 | U67: =IF(T67="","",MAX(0,T67-O67)) -> 0 | V67: =IF(D67="End of range","END OF RANGE",IF(T67="","NO BUFFER SET",IF(H67<=0,IF(O67<T67,"OUT - REORDER","OUT - ON ORDER"),IF(O67<T67,"REORDER",IF(H67<T67,"LOW - ON ORDER",IF(AND(S67<>"",N(S67)>Settings!$B$5),"SLOW MOVER","OK")))))) -> OK | X67: =IF(OR(D67="End of range",U67=""),0,IF(N(U67)>0,U67+ROW()/1000000,0)) -> 0
A68: VIN001 | B68: VINTAGE PECAN | C68: Hide | D68: Active | E68: =SUMIFS('CPT Count'!$D:$D,'CPT Count'!$A:$A,$A68)-SUMIFS('Weekly Sales'!$F:$F,'Weekly Sales'!$H:$H,$A68,'Weekly Sales'!$I:$I,"CPT")+SUMIFS(Transfers!$F:$F,Transfers!$C:$C,$A68,Transfers!$J:$J,"CPT")-SUMIFS(Transfers!$F:$F,Transfers!$C:$C,$A68,Transfers!$I:$I,"CPT",Transfers!$H:$H,"<>Y")+SUMIFS('Stock Received'!$I:$I,'Stock Received'!$E:$E,$A68,'Stock Received'!$L:$L,"CPT") -> 1242.29 | F68: =SUMIFS('JHB Count'!$E:$E,'JHB Count'!$F:$F,$A68)-SUMIFS('Weekly Sales'!$F:$F,'Weekly Sales'!$H:$H,$A68,'Weekly Sales'!$I:$I,"JHB")+SUMIFS(Transfers!$F:$F,Transfers!$C:$C,$A68,Transfers!$J:$J,"JHB")-SUMIFS(Transfers!$F:$F,Transfers!$C:$C,$A68,Transfers!$I:$I,"JHB",Transfers!$H:$H,"<>Y")+SUMIFS('Stock Received'!$I:$I,'Stock Received'!$E:$E,$A68,'Stock Received'!$L:$L,"JHB") -> 95.72 | G68: =SUMIFS('DBN Count'!$D:$D,'DBN Count'!$E:$E,$A68)-SUMIFS('Weekly Sales'!$F:$F,'Weekly Sales'!$H:$H,$A68,'Weekly Sales'!$I:$I,"DBN")+SUMIFS(Transfers!$F:$F,Transfers!$C:$C,$A68,Transfers!$J:$J,"DBN")-SUMIFS(Transfers!$F:$F,Transfers!$C:$C,$A68,Transfers!$I:$I,"DBN",Transfers!$H:$H,"<>Y")+SUMIFS('Stock Received'!$I:$I,'Stock Received'!$E:$E,$A68,'Stock Received'!$L:$L,"DBN") -> 47.05 | H68: =E68+F68+G68 -> 1385.06 | I68: =SUMIFS('Weekly Sales'!$F:$F,'Weekly Sales'!$H:$H,$A68) -> 8.99 | J68: =SUMIFS(Orders!$L:$L,Orders!$D:$D,$A68,Orders!$F:$F,">="&J$4,Orders!$F:$F,"<"&EDATE(J$4,1)) -> 0 | K68: =SUMIFS(Orders!$L:$L,Orders!$D:$D,$A68,Orders!$F:$F,">="&K$4,Orders!$F:$F,"<"&EDATE(K$4,1)) -> 0 | L68: =SUMIFS(Orders!$L:$L,Orders!$D:$D,$A68,Orders!$F:$F,">="&L$4,Orders!$F:$F,"<"&EDATE(L$4,1)) -> 300 | M68: =N68-J68-K68-L68 -> 0 | N68: =SUMIFS(Orders!$L:$L,Orders!$D:$D,$A68) -> 300 | O68: =H68+N68 -> 1685.06 | P68: 360 | Q68: =IF(SUMIFS('Sales History'!$E:$E,'Sales History'!$G:$G,$A68)>0,SUMIFS('Sales History'!$E:$E,'Sales History'!$G:$G,$A68)/Settings!$B$4,N(P68)) -> 360 | R68: =IF(SUMIFS('Sales History'!$E:$E,'Sales History'!$G:$G,$A68)>0,"6-month history",IF(N(P68)>0,"Current sheet","No sales data")) -> Current sheet | S68: =IF(Q68>0,H68/Q68,"") -> 3.8473889 | T68: 700 | U68: =IF(T68="","",MAX(0,T68-O68)) -> 0 | V68: =IF(D68="End of range","END OF RANGE",IF(T68="","NO BUFFER SET",IF(H68<=0,IF(O68<T68,"OUT - REORDER","OUT - ON ORDER"),IF(O68<T68,"REORDER",IF(H68<T68,"LOW - ON ORDER",IF(AND(S68<>"",N(S68)>Settings!$B$5),"SLOW MOVER","OK")))))) -> OK | X68: =IF(OR(D68="End of range",U68=""),0,IF(N(U68)>0,U68+ROW()/1000000,0)) -> 0
A69: VIN003 | B69: VINTAGE BLACK | C69: Hide | D69: Active | E69: =SUMIFS('CPT Count'!$D:$D,'CPT Count'!$A:$A,$A69)-SUMIFS('Weekly Sales'!$F:$F,'Weekly Sales'!$H:$H,$A69,'Weekly Sales'!$I:$I,"CPT")+SUMIFS(Transfers!$F:$F,Transfers!$C:$C,$A69,Transfers!$J:$J,"CPT")-SUMIFS(Transfers!$F:$F,Transfers!$C:$C,$A69,Transfers!$I:$I,"CPT",Transfers!$H:$H,"<>Y")+SUMIFS('Stock Received'!$I:$I,'Stock Received'!$E:$E,$A69,'Stock Received'!$L:$L,"CPT") -> 226.1 | F69: =SUMIFS('JHB Count'!$E:$E,'JHB Count'!$F:$F,$A69)-SUMIFS('Weekly Sales'!$F:$F,'Weekly Sales'!$H:$H,$A69,'Weekly Sales'!$I:$I,"JHB")+SUMIFS(Transfers!$F:$F,Transfers!$C:$C,$A69,Transfers!$J:$J,"JHB")-SUMIFS(Transfers!$F:$F,Transfers!$C:$C,$A69,Transfers!$I:$I,"JHB",Transfers!$H:$H,"<>Y")+SUMIFS('Stock Received'!$I:$I,'Stock Received'!$E:$E,$A69,'Stock Received'!$L:$L,"JHB") -> 87.25 | G69: =SUMIFS('DBN Count'!$D:$D,'DBN Count'!$E:$E,$A69)-SUMIFS('Weekly Sales'!$F:$F,'Weekly Sales'!$H:$H,$A69,'Weekly Sales'!$I:$I,"DBN")+SUMIFS(Transfers!$F:$F,Transfers!$C:$C,$A69,Transfers!$J:$J,"DBN")-SUMIFS(Transfers!$F:$F,Transfers!$C:$C,$A69,Transfers!$I:$I,"DBN",Transfers!$H:$H,"<>Y")+SUMIFS('Stock Received'!$I:$I,'Stock Received'!$E:$E,$A69,'Stock Received'!$L:$L,"DBN") -> 83.3 | H69: =E69+F69+G69 -> 396.65 | I69: =SUMIFS('Weekly Sales'!$F:$F,'Weekly Sales'!$H:$H,$A69) -> 41.68 | J69: =SUMIFS(Orders!$L:$L,Orders!$D:$D,$A69,Orders!$F:$F,">="&J$4,Orders!$F:$F,"<"&EDATE(J$4,1)) -> 0 | K69: =SUMIFS(Orders!$L:$L,Orders!$D:$D,$A69,Orders!$F:$F,">="&K$4,Orders!$F:$F,"<"&EDATE(K$4,1)) -> 1000 | L69: =SUMIFS(Orders!$L:$L,Orders!$D:$D,$A69,Orders!$F:$F,">="&L$4,Orders!$F:$F,"<"&EDATE(L$4,1)) -> 500 | M69: =N69-J69-K69-L69 -> 0 | N69: =SUMIFS(Orders!$L:$L,Orders!$D:$D,$A69) -> 1500 | O69: =H69+N69 -> 1896.65 | P69: 420 | Q69: =IF(SUMIFS('Sales History'!$E:$E,'Sales History'!$G:$G,$A69)>0,SUMIFS('Sales History'!$E:$E,'Sales History'!$G:$G,$A69)/Settings!$B$4,N(P69)) -> 420 | R69: =IF(SUMIFS('Sales History'!$E:$E,'Sales History'!$G:$G,$A69)>0,"6-month history",IF(N(P69)>0,"Current sheet","No sales data")) -> Current sheet | S69: =IF(Q69>0,H69/Q69,"") -> 0.94440476 | T69: 800 | U69: =IF(T69="","",MAX(0,T69-O69)) -> 0 | V69: =IF(D69="End of range","END OF RANGE",IF(T69="","NO BUFFER SET",IF(H69<=0,IF(O69<T69,"OUT - REORDER","OUT - ON ORDER"),IF(O69<T69,"REORDER",IF(H69<T69,"LOW - ON ORDER",IF(AND(S69<>"",N(S69)>Settings!$B$5),"SLOW MOVER","OK")))))) -> LOW - ON ORDER | X69: =IF(OR(D69="End of range",U69=""),0,IF(N(U69)>0,U69+ROW()/1000000,0)) -> 0
... A72: BWO001 | B72: FORRESTER SPICE (PRINT) | C72: Hide | D72: Active | E72: =SUMIFS('CPT Count'!$D:$D,'CPT Count'!$A:$A,$A72)-SUMIFS('Weekly Sales'!$F:$F,'Weekly Sales'!$H:$H,$A72,'Weekly Sales'!$I:$I,"CPT")+SUMIFS(Transfers!$F:$F,Transfers!$C:$C,$A72,Transfers!$J:$J,"CPT")-SUMIFS(Transfers!$F:$F,Transfers!$C:$C,$A72,Transfers!$I:$I,"CPT",Transfers!$H:$H,"<>Y")+SUMIFS('Stock Received'!$I:$I,'Stock Received'!$E:$E,$A72,'Stock Received'!$L:$L,"CPT") -> 672.85 | F72: =SUMIFS('JHB Count'!$E:$E,'JHB Count'!$F:$F,$A72)-SUMIFS('Weekly Sales'!$F:$F,'Weekly Sales'!$H:$H,$A72,'Weekly Sales'!$I:$I,"JHB")+SUMIFS(Transfers!$F:$F,Transfers!$C:$C,$A72,Transfers!$J:$J,"JHB")-SUMIFS(Transfers!$F:$F,Transfers!$C:$C,$A72,Transfers!$I:$I,"JHB",Transfers!$H:$H,"<>Y")+SUMIFS('Stock Received'!$I:$I,'Stock Received'!$E:$E,$A72,'Stock Received'!$L:$L,"JHB") -> 396.98 | G72: =SUMIFS('DBN Count'!$D:$D,'DBN Count'!$E:$E,$A72)-SUMIFS('Weekly Sales'!$F:$F,'Weekly Sales'!$H:$H,$A72,'Weekly Sales'!$I:$I,"DBN")+SUMIFS(Transfers!$F:$F,Transfers!$C:$C,$A72,Transfers!$J:$J,"DBN")-SUMIFS(Transfers!$F:$F,Transfers!$C:$C,$A72,Transfers!$I:$I,"DBN",Transfers!$H:$H,"<>Y")+SUMIFS('Stock Received'!$I:$I,'Stock Received'!$E:$E,$A72,'Stock Received'!$L:$L,"DBN") -> 0 | H72: =E72+F72+G72 -> 1069.83 | I72: =SUMIFS('Weekly Sales'!$F:$F,'Weekly Sales'!$H:$H,$A72) -> 354.17 | J72: =SUMIFS(Orders!$L:$L,Orders!$D:$D,$A72,Orders!$F:$F,">="&J$4,Orders!$F:$F,"<"&EDATE(J$4,1)) -> 0 | K72: =SUMIFS(Orders!$L:$L,Orders!$D:$D,$A72,Orders!$F:$F,">="&K$4,Orders!$F:$F,"<"&EDATE(K$4,1)) -> 1500 | L72: =SUMIFS(Orders!$L:$L,Orders!$D:$D,$A72,Orders!$F:$F,">="&L$4,Orders!$F:$F,"<"&EDATE(L$4,1)) -> 0 | M72: =N72-J72-K72-L72 -> 0 | N72: =SUMIFS(Orders!$L:$L,Orders!$D:$D,$A72) -> 1500 | O72: =H72+N72 -> 2569.83 | P72: 350 | Q72: =IF(SUMIFS('Sales History'!$E:$E,'Sales History'!$G:$G,$A72)>0,SUMIFS('Sales History'!$E:$E,'Sales History'!$G:$G,$A72)/Settings!$B$4,N(P72)) -> 350 | R72: =IF(SUMIFS('Sales History'!$E:$E,'Sales History'!$G:$G,$A72)>0,"6-month history",IF(N(P72)>0,"Current sheet","No sales data")) -> Current sheet | S72: =IF(Q72>0,H72/Q72,"") -> 3.0566571 | T72: 700 | U72: =IF(T72="","",MAX(0,T72-O72)) -> 0 | V72: =IF(D72="End of range","END OF RANGE",IF(T72="","NO BUFFER SET",IF(H72<=0,IF(O72<T72,"OUT - REORDER","OUT - ON ORDER"),IF(O72<T72,"REORDER",IF(H72<T72,"LOW - ON ORDER",IF(AND(S72<>"",N(S72)>Settings!$B$5),"SLOW MOVER","OK")))))) -> OK | X72: =IF(OR(D72="End of range",U72=""),0,IF(N(U72)>0,U72+ROW()/1000000,0)) -> 0
A73: BWO007 | B73: WOODLAND PRINT WHISKEY | C73: Hide | D73: End of range | E73: =SUMIFS('CPT Count'!$D:$D,'CPT Count'!$A:$A,$A73)-SUMIFS('Weekly Sales'!$F:$F,'Weekly Sales'!$H:$H,$A73,'Weekly Sales'!$I:$I,"CPT")+SUMIFS(Transfers!$F:$F,Transfers!$C:$C,$A73,Transfers!$J:$J,"CPT")-SUMIFS(Transfers!$F:$F,Transfers!$C:$C,$A73,Transfers!$I:$I,"CPT",Transfers!$H:$H,"<>Y")+SUMIFS('Stock Received'!$I:$I,'Stock Received'!$E:$E,$A73,'Stock Received'!$L:$L,"CPT") -> 1140 | F73: =SUMIFS('JHB Count'!$E:$E,'JHB Count'!$F:$F,$A73)-SUMIFS('Weekly Sales'!$F:$F,'Weekly Sales'!$H:$H,$A73,'Weekly Sales'!$I:$I,"JHB")+SUMIFS(Transfers!$F:$F,Transfers!$C:$C,$A73,Transfers!$J:$J,"JHB")-SUMIFS(Transfers!$F:$F,Transfers!$C:$C,$A73,Transfers!$I:$I,"JHB",Transfers!$H:$H,"<>Y")+SUMIFS('Stock Received'!$I:$I,'Stock Received'!$E:$E,$A73,'Stock Received'!$L:$L,"JHB") -> 256.11 | G73: =SUMIFS('DBN Count'!$D:$D,'DBN Count'!$E:$E,$A73)-SUMIFS('Weekly Sales'!$F:$F,'Weekly Sales'!$H:$H,$A73,'Weekly Sales'!$I:$I,"DBN")+SUMIFS(Transfers!$F:$F,Transfers!$C:$C,$A73,Transfers!$J:$J,"DBN")-SUMIFS(Transfers!$F:$F,Transfers!$C:$C,$A73,Transfers!$I:$I,"DBN",Transfers!$H:$H,"<>Y")+SUMIFS('Stock Received'!$I:$I,'Stock Received'!$E:$E,$A73,'Stock Received'!$L:$L,"DBN") -> 0 | H73: =E73+F73+G73 -> 1396.11 | I73: =SUMIFS('Weekly Sales'!$F:$F,'Weekly Sales'!$H:$H,$A73) -> 123.89 | J73: =SUMIFS(Orders!$L:$L,Orders!$D:$D,$A73,Orders!$F:$F,">="&J$4,Orders!$F:$F,"<"&EDATE(J$4,1)) -> 0 | K73: =SUMIFS(Orders!$L:$L,Orders!$D:$D,$A73,Orders!$F:$F,">="&K$4,Orders!$F:$F,"<"&EDATE(K$4,1)) -> 0 | L73: =SUMIFS(Orders!$L:$L,Orders!$D:$D,$A73,Orders!$F:$F,">="&L$4,Orders!$F:$F,"<"&EDATE(L$4,1)) -> 0 | M73: =N73-J73-K73-L73 -> 0 | N73: =SUMIFS(Orders!$L:$L,Orders!$D:$D,$A73) -> 0 | O73: =H73+N73 -> 1396.11 | Q73: =IF(SUMIFS('Sales History'!$E:$E,'Sales History'!$G:$G,$A73)>0,SUMIFS('Sales History'!$E:$E,'Sales History'!$G:$G,$A73)/Settings!$B$4,N(P73)) -> 0 | R73: =IF(SUMIFS('Sales History'!$E:$E,'Sales History'!$G:$G,$A73)>0,"6-month history",IF(N(P73)>0,"Current sheet","No sales data")) -> No sales data | S73: =IF(Q73>0,H73/Q73,"") | T73: 50 | U73: =IF(T73="","",MAX(0,T73-O73)) -> 0 | V73: =IF(D73="End of range","END OF RANGE",IF(T73="","NO BUFFER SET",IF(H73<=0,IF(O73<T73,"OUT - REORDER","OUT - ON ORDER"),IF(O73<T73,"REORDER",IF(H73<T73,"LOW - ON ORDER",IF(AND(S73<>"",N(S73)>Settings!$B$5),"SLOW MOVER","OK")))))) -> END OF RANGE | X73: =IF(OR(D73="End of range",U73=""),0,IF(N(U73)>0,U73+ROW()/1000000,0)) -> 0
A74: BWO002 | B74: FORRESTER TAN | C74: Hide | D74: Active | E74: =SUMIFS('CPT Count'!$D:$D,'CPT Count'!$A:$A,$A74)-SUMIFS('Weekly Sales'!$F:$F,'Weekly Sales'!$H:$H,$A74,'Weekly Sales'!$I:$I,"CPT")+SUMIFS(Transfers!$F:$F,Transfers!$C:$C,$A74,Transfers!$J:$J,"CPT")-SUMIFS(Transfers!$F:$F,Transfers!$C:$C,$A74,Transfers!$I:$I,"CPT",Transfers!$H:$H,"<>Y")+SUMIFS('Stock Received'!$I:$I,'Stock Received'!$E:$E,$A74,'Stock Received'!$L:$L,"CPT") -> 865 | F74: =SUMIFS('JHB Count'!$E:$E,'JHB Count'!$F:$F,$A74)-SUMIFS('Weekly Sales'!$F:$F,'Weekly Sales'!$H:$H,$A74,'Weekly Sales'!$I:$I,"JHB")+SUMIFS(Transfers!$F:$F,Transfers!$C:$C,$A74,Transfers!$J:$J,"JHB")-SUMIFS(Transfers!$F:$F,Transfers!$C:$C,$A74,Transfers!$I:$I,"JHB",Transfers!$H:$H,"<>Y")+SUMIFS('Stock Received'!$I:$I,'Stock Received'!$E:$E,$A74,'Stock Received'!$L:$L,"JHB") -> 864 | G74: =SUMIFS('DBN Count'!$D:$D,'DBN Count'!$E:$E,$A74)-SUMIFS('Weekly Sales'!$F:$F,'Weekly Sales'!$H:$H,$A74,'Weekly Sales'!$I:$I,"DBN")+SUMIFS(Transfers!$F:$F,Transfers!$C:$C,$A74,Transfers!$J:$J,"DBN")-SUMIFS(Transfers!$F:$F,Transfers!$C:$C,$A74,Transfers!$I:$I,"DBN",Transfers!$H:$H,"<>Y")+SUMIFS('Stock Received'!$I:$I,'Stock Received'!$E:$E,$A74,'Stock Received'!$L:$L,"DBN") -> 0 | H74: =E74+F74+G74 -> 1729 | I74: =SUMIFS('Weekly Sales'!$F:$F,'Weekly Sales'!$H:$H,$A74) -> 0 | J74: =SUMIFS(Orders!$L:$L,Orders!$D:$D,$A74,Orders!$F:$F,">="&J$4,Orders!$F:$F,"<"&EDATE(J$4,1)) -> 0 | K74: =SUMIFS(Orders!$L:$L,Orders!$D:$D,$A74,Orders!$F:$F,">="&K$4,Orders!$F:$F,"<"&EDATE(K$4,1)) -> 1000 | L74: =SUMIFS(Orders!$L:$L,Orders!$D:$D,$A74,Orders!$F:$F,">="&L$4,Orders!$F:$F,"<"&EDATE(L$4,1)) -> 0 | M74: =N74-J74-K74-L74 -> 0 | N74: =SUMIFS(Orders!$L:$L,Orders!$D:$D,$A74) -> 1000 | O74: =H74+N74 -> 2729 | P74: 100 | Q74: =IF(SUMIFS('Sales History'!$E:$E,'Sales History'!$G:$G,$A74)>0,SUMIFS('Sales History'!$E:$E,'Sales History'!$G:$G,$A74)/Settings!$B$4,N(P74)) -> 100 | R74: =IF(SUMIFS('Sales History'!$E:$E,'Sales History'!$G:$G,$A74)>0,"6-month history",IF(N(P74)>0,"Current sheet","No sales data")) -> Current sheet | S74: =IF(Q74>0,H74/Q74,"") -> 17.29 | T74: 700 | U74: =IF(T74="","",MAX(0,T74-O74)) -> 0 | V74: =IF(D74="End of range","END OF RANGE",IF(T74="","NO BUFFER SET",IF(H74<=0,IF(O74<T74,"OUT - REORDER","OUT - ON ORDER"),IF(O74<T74,"REORDER",IF(H74<T74,"LOW - ON ORDER",IF(AND(S74<>"",N(S74)>Settings!$B$5),"SLOW MOVER","OK")))))) -> SLOW MOVER | X74: =IF(OR(D74="End of range",U74=""),0,IF(N(U74)>0,U74+ROW()/1000000,0)) -> 0
A75: BWO003 | B75: FORRETER BROWN | C75: Hide | D75: Active | E75: =SUMIFS('CPT Count'!$D:$D,'CPT Count'!$A:$A,$A75)-SUMIFS('Weekly Sales'!$F:$F,'Weekly Sales'!$H:$H,$A75,'Weekly Sales'!$I:$I,"CPT")+SUMIFS(Transfers!$F:$F,Transfers!$C:$C,$A75,Transfers!$J:$J,"CPT")-SUMIFS(Transfers!$F:$F,Transfers!$C:$C,$A75,Transfers!$I:$I,"CPT",Transfers!$H:$H,"<>Y")+SUMIFS('Stock Received'!$I:$I,'Stock Received'!$E:$E,$A75,'Stock Received'!$L:$L,"CPT") -> 1100 | F75: =SUMIFS('JHB Count'!$E:$E,'JHB Count'!$F:$F,$A75)-SUMIFS('Weekly Sales'!$F:$F,'Weekly Sales'!$H:$H,$A75,'Weekly Sales'!$I:$I,"JHB")+SUMIFS(Transfers!$F:$F,Transfers!$C:$C,$A75,Transfers!$J:$J,"JHB")-SUMIFS(Transfers!$F:$F,Transfers!$C:$C,$A75,Transfers!$I:$I,"JHB",Transfers!$H:$H,"<>Y")+SUMIFS('Stock Received'!$I:$I,'Stock Received'!$E:$E,$A75,'Stock Received'!$L:$L,"JHB") -> 0 | G75: =SUMIFS('DBN Count'!$D:$D,'DBN Count'!$E:$E,$A75)-SUMIFS('Weekly Sales'!$F:$F,'Weekly Sales'!$H:$H,$A75,'Weekly Sales'!$I:$I,"DBN")+SUMIFS(Transfers!$F:$F,Transfers!$C:$C,$A75,Transfers!$J:$J,"DBN")-SUMIFS(Transfers!$F:$F,Transfers!$C:$C,$A75,Transfers!$I:$I,"DBN",Transfers!$H:$H,"<>Y")+SUMIFS('Stock Received'!$I:$I,'Stock Received'!$E:$E,$A75,'Stock Received'!$L:$L,"DBN") -> 0 | H75: =E75+F75+G75 -> 1100 | I75: =SUMIFS('Weekly Sales'!$F:$F,'Weekly Sales'!$H:$H,$A75) -> 0 | J75: =SUMIFS(Orders!$L:$L,Orders!$D:$D,$A75,Orders!$F:$F,">="&J$4,Orders!$F:$F,"<"&EDATE(J$4,1)) -> 0 | K75: =SUMIFS(Orders!$L:$L,Orders!$D:$D,$A75,Orders!$F:$F,">="&K$4,Orders!$F:$F,"<"&EDATE(K$4,1)) -> 0 | L75: =SUMIFS(Orders!$L:$L,Orders!$D:$D,$A75,Orders!$F:$F,">="&L$4,Orders!$F:$F,"<"&EDATE(L$4,1)) -> 0 | M75: =N75-J75-K75-L75 -> 0 | N75: =SUMIFS(Orders!$L:$L,Orders!$D:$D,$A75) -> 0 | O75: =H75+N75 -> 1100 | P75: 15 | Q75: =IF(SUMIFS('Sales History'!$E:$E,'Sales History'!$G:$G,$A75)>0,SUMIFS('Sales History'!$E:$E,'Sales History'!$G:$G,$A75)/Settings!$B$4,N(P75)) -> 15 | R75: =IF(SUMIFS('Sales History'!$E:$E,'Sales History'!$G:$G,$A75)>0,"6-month history",IF(N(P75)>0,"Current sheet","No sales data")) -> Current sheet | S75: =IF(Q75>0,H75/Q75,"") -> 73.333333 | T75: 300 | U75: =IF(T75="","",MAX(0,T75-O75)) -> 0 | V75: =IF(D75="End of range","END OF RANGE",IF(T75="","NO BUFFER SET",IF(H75<=0,IF(O75<T75,"OUT - REORDER","OUT - ON ORDER"),IF(O75<T75,"REORDER",IF(H75<T75,"LOW - ON ORDER",IF(AND(S75<>"",N(S75)>Settings!$B$5),"SLOW MOVER","OK")))))) -> SLOW MOVER | X75: =IF(OR(D75="End of range",U75=""),0,IF(N(U75)>0,U75+ROW()/1000000,0)) -> 0
A76: BWO004 | B76: FORRESTER CHARCOAL | C76: Hide | D76: Active | E76: =SUMIFS('CPT Count'!$D:$D,'CPT Count'!$A:$A,$A76)-SUMIFS('Weekly Sales'!$F:$F,'Weekly Sales'!$H:$H,$A76,'Weekly Sales'!$I:$I,"CPT")+SUMIFS(Transfers!$F:$F,Transfers!$C:$C,$A76,Transfers!$J:$J,"CPT")-SUMIFS(Transfers!$F:$F,Transfers!$C:$C,$A76,Transfers!$I:$I,"CPT",Transfers!$H:$H,"<>Y")+SUMIFS('Stock Received'!$I:$I,'Stock Received'!$E:$E,$A76,'Stock Received'!$L:$L,"CPT") -> 1323.77 | F76: =SUMIFS('JHB Count'!$E:$E,'JHB Count'!$F:$F,$A76)-SUMIFS('Weekly Sales'!$F:$F,'Weekly Sales'!$H:$H,$A76,'Weekly Sales'!$I:$I,"JHB")+SUMIFS(Transfers!$F:$F,Transfers!$C:$C,$A76,Transfers!$J:$J,"JHB")-SUMIFS(Transfers!$F:$F,Transfers!$C:$C,$A76,Transfers!$I:$I,"JHB",Transfers!$H:$H,"<>Y")+SUMIFS('Stock Received'!$I:$I,'Stock Received'!$E:$E,$A76,'Stock Received'!$L:$L,"JHB") -> 84 | G76: =SUMIFS('DBN Count'!$D:$D,'DBN Count'!$E:$E,$A76)-SUMIFS('Weekly Sales'!$F:$F,'Weekly Sales'!$H:$H,$A76,'Weekly Sales'!$I:$I,"DBN")+SUMIFS(Transfers!$F:$F,Transfers!$C:$C,$A76,Transfers!$J:$J,"DBN")-SUMIFS(Transfers!$F:$F,Transfers!$C:$C,$A76,Transfers!$I:$I,"DBN",Transfers!$H:$H,"<>Y")+SUMIFS('Stock Received'!$I:$I,'Stock Received'!$E:$E,$A76,'Stock Received'!$L:$L,"DBN") -> 0 | H76: =E76+F76+G76 -> 1407.77 | I76: =SUMIFS('Weekly Sales'!$F:$F,'Weekly Sales'!$H:$H,$A76) -> 7.23 | J76: =SUMIFS(Orders!$L:$L,Orders!$D:$D,$A76,Orders!$F:$F,">="&J$4,Orders!$F:$F,"<"&EDATE(J$4,1)) -> 0 | K76: =SUMIFS(Orders!$L:$L,Orders!$D:$D,$A76,Orders!$F:$F,">="&K$4,Orders!$F:$F,"<"&EDATE(K$4,1)) -> 0 | L76: =SUMIFS(Orders!$L:$L,Orders!$D:$D,$A76,Orders!$F:$F,">="&L$4,Orders!$F:$F,"<"&EDATE(L$4,1)) -> 0 | M76: =N76-J76-K76-L76 -> 0 | N76: =SUMIFS(Orders!$L:$L,Orders!$D:$D,$A76) -> 0 | O76: =H76+N76 -> 1407.77 | P76: 40 | Q76: =IF(SUMIFS('Sales History'!$E:$E,'Sales History'!$G:$G,$A76)>0,SUMIFS('Sales History'!$E:$E,'Sales History'!$G:$G,$A76)/Settings!$B$4,N(P76)) -> 40 | R76: =IF(SUMIFS('Sales History'!$E:$E,'Sales History'!$G:$G,$A76)>0,"6-month history",IF(N(P76)>0,"Current sheet","No sales data")) -> Current sheet | S76: =IF(Q76>0,H76/Q76,"") -> 35.19425 | T76: 300 | U76: =IF(T76="","",MAX(0,T76-O76)) -> 0 | V76: =IF(D76="End of range","END OF RANGE",IF(T76="","NO BUFFER SET",IF(H76<=0,IF(O76<T76,"OUT - REORDER","OUT - ON ORDER"),IF(O76<T76,"REORDER",IF(H76<T76,"LOW - ON ORDER",IF(AND(S76<>"",N(S76)>Settings!$B$5),"SLOW MOVER","OK")))))) -> SLOW MOVER | X76: =IF(OR(D76="End of range",U76=""),0,IF(N(U76)>0,U76+ROW()/1000000,0)) -> 0
A77: BWO005 | B77: FORRESTER TAUPE B | C77: Hide | D77: Active | E77: =SUMIFS('CPT Count'!$D:$D,'CPT Count'!$A:$A,$A77)-SUMIFS('Weekly Sales'!$F:$F,'Weekly Sales'!$H:$H,$A77,'Weekly Sales'!$I:$I,"CPT")+SUMIFS(Transfers!$F:$F,Transfers!$C:$C,$A77,Transfers!$J:$J,"CPT")-SUMIFS(Transfers!$F:$F,Transfers!$C:$C,$A77,Transfers!$I:$I,"CPT",Transfers!$H:$H,"<>Y")+SUMIFS('Stock Received'!$I:$I,'Stock Received'!$E:$E,$A77,'Stock Received'!$L:$L,"CPT") -> 380.64 | F77: =SUMIFS('JHB Count'!$E:$E,'JHB Count'!$F:$F,$A77)-SUMIFS('Weekly Sales'!$F:$F,'Weekly Sales'!$H:$H,$A77,'Weekly Sales'!$I:$I,"JHB")+SUMIFS(Transfers!$F:$F,Transfers!$C:$C,$A77,Transfers!$J:$J,"JHB")-SUMIFS(Transfers!$F:$F,Transfers!$C:$C,$A77,Transfers!$I:$I,"JHB",Transfers!$H:$H,"<>Y")+SUMIFS('Stock Received'!$I:$I,'Stock Received'!$E:$E,$A77,'Stock Received'!$L:$L,"JHB") -> 30.5 | G77: =SUMIFS('DBN Count'!$D:$D,'DBN Count'!$E:$E,$A77)-SUMIFS('Weekly Sales'!$F:$F,'Weekly Sales'!$H:$H,$A77,'Weekly Sales'!$I:$I,"DBN")+SUMIFS(Transfers!$F:$F,Transfers!$C:$C,$A77,Transfers!$J:$J,"DBN")-SUMIFS(Transfers!$F:$F,Transfers!$C:$C,$A77,Transfers!$I:$I,"DBN",Transfers!$H:$H,"<>Y")+SUMIFS('Stock Received'!$I:$I,'Stock Received'!$E:$E,$A77,'Stock Received'!$L:$L,"DBN") -> 0 | H77: =E77+F77+G77 -> 411.14 | I77: =SUMIFS('Weekly Sales'!$F:$F,'Weekly Sales'!$H:$H,$A77) -> 29.5 | J77: =SUMIFS(Orders!$L:$L,Orders!$D:$D,$A77,Orders!$F:$F,">="&J$4,Orders!$F:$F,"<"&EDATE(J$4,1)) -> 0 | K77: =SUMIFS(Orders!$L:$L,Orders!$D:$D,$A77,Orders!$F:$F,">="&K$4,Orders!$F:$F,"<"&EDATE(K$4,1)) -> 300 | L77: =SUMIFS(Orders!$L:$L,Orders!$D:$D,$A77,Orders!$F:$F,">="&L$4,Orders!$F:$F,"<"&EDATE(L$4,1)) -> 0 | M77: =N77-J77-K77-L77 -> 0 | N77: =SUMIFS(Orders!$L:$L,Orders!$D:$D,$A77) -> 300 | O77: =H77+N77 -> 711.14 | P77: 200 | Q77: =IF(SUMIFS('Sales History'!$E:$E,'Sales History'!$G:$G,$A77)>0,SUMIFS('Sales History'!$E:$E,'Sales History'!$G:$G,$A77)/Settings!$B$4,N(P77)) -> 200 | R77: =IF(SUMIFS('Sales History'!$E:$E,'Sales History'!$G:$G,$A77)>0,"6-month history",IF(N(P77)>0,"Current sheet","No sales data")) -> Current sheet | S77: =IF(Q77>0,H77/Q77,"") -> 2.0557 | T77: 300 | U77: =IF(T77="","",MAX(0,T77-O77)) -> 0 | V77: =IF(D77="End of range","END OF RANGE",IF(T77="","NO BUFFER SET",IF(H77<=0,IF(O77<T77,"OUT - REORDER","OUT - ON ORDER"),IF(O77<T77,"REORDER",IF(H77<T77,"LOW - ON ORDER",IF(AND(S77<>"",N(S77)>Settings!$B$5),"SLOW MOVER","OK")))))) -> OK | X77: =IF(OR(D77="End of range",U77=""),0,IF(N(U77)>0,U77+ROW()/1000000,0)) -> 0
A78: BWO006 | B78: FORRESTER GRAPHITE | C78: Hide | D78: Active | E78: =SUMIFS('CPT Count'!$D:$D,'CPT Count'!$A:$A,$A78)-SUMIFS('Weekly Sales'!$F:$F,'Weekly Sales'!$H:$H,$A78,'Weekly Sales'!$I:$I,"CPT")+SUMIFS(Transfers!$F:$F,Transfers!$C:$C,$A78,Transfers!$J:$J,"CPT")-SUMIFS(Transfers!$F:$F,Transfers!$C:$C,$A78,Transfers!$I:$I,"CPT",Transfers!$H:$H,"<>Y")+SUMIFS('Stock Received'!$I:$I,'Stock Received'!$E:$E,$A78,'Stock Received'!$L:$L,"CPT") -> 547 | F78: =SUMIFS('JHB Count'!$E:$E,'JHB Count'!$F:$F,$A78)-SUMIFS('Weekly Sales'!$F:$F,'Weekly Sales'!$H:$H,$A78,'Weekly Sales'!$I:$I,"JHB")+SUMIFS(Transfers!$F:$F,Transfers!$C:$C,$A78,Transfers!$J:$J,"JHB")-SUMIFS(Transfers!$F:$F,Transfers!$C:$C,$A78,Transfers!$I:$I,"JHB",Transfers!$H:$H,"<>Y")+SUMIFS('Stock Received'!$I:$I,'Stock Received'!$E:$E,$A78,'Stock Received'!$L:$L,"JHB") -> 205.61 | G78: =SUMIFS('DBN Count'!$D:$D,'DBN Count'!$E:$E,$A78)-SUMIFS('Weekly Sales'!$F:$F,'Weekly Sales'!$H:$H,$A78,'Weekly Sales'!$I:$I,"DBN")+SUMIFS(Transfers!$F:$F,Transfers!$C:$C,$A78,Transfers!$J:$J,"DBN")-SUMIFS(Transfers!$F:$F,Transfers!$C:$C,$A78,Transfers!$I:$I,"DBN",Transfers!$H:$H,"<>Y")+SUMIFS('Stock Received'!$I:$I,'Stock Received'!$E:$E,$A78,'Stock Received'!$L:$L,"DBN") -> 0 | H78: =E78+F78+G78 -> 752.61 | I78: =SUMIFS('Weekly Sales'!$F:$F,'Weekly Sales'!$H:$H,$A78) -> 90.39 | J78: =SUMIFS(Orders!$L:$L,Orders!$D:$D,$A78,Orders!$F:$F,">="&J$4,Orders!$F:$F,"<"&EDATE(J$4,1)) -> 0 | K78: =SUMIFS(Orders!$L:$L,Orders!$D:$D,$A78,Orders!$F:$F,">="&K$4,Orders!$F:$F,"<"&EDATE(K$4,1)) -> 0 | L78: =SUMIFS(Orders!$L:$L,Orders!$D:$D,$A78,Orders!$F:$F,">="&L$4,Orders!$F:$F,"<"&EDATE(L$4,1)) -> 0 | M78: =N78-J78-K78-L78 -> 0 | N78: =SUMIFS(Orders!$L:$L,Orders!$D:$D,$A78) -> 0 | O78: =H78+N78 -> 752.61 | P78: 110 | Q78: =IF(SUMIFS('Sales History'!$E:$E,'Sales History'!$G:$G,$A78)>0,SUMIFS('Sales History'!$E:$E,'Sales History'!$G:$G,$A78)/Settings!$B$4,N(P78)) -> 110 | R78: =IF(SUMIFS('Sales History'!$E:$E,'Sales History'!$G:$G,$A78)>0,"6-month history",IF(N(P78)>0,"Current sheet","No sales data")) -> Current sheet | S78: =IF(Q78>0,H78/Q78,"") -> 6.8419091 | T78: 300 | U78: =IF(T78="","",MAX(0,T78-O78)) -> 0 | V78: =IF(D78="End of range","END OF RANGE",IF(T78="","NO BUFFER SET",IF(H78<=0,IF(O78<T78,"OUT - REORDER","OUT - ON ORDER"),IF(O78<T78,"REORDER",IF(H78<T78,"LOW - ON ORDER",IF(AND(S78<>"",N(S78)>Settings!$B$5),"SLOW MOVER","OK")))))) -> OK | X78: =IF(OR(D78="End of range",U78=""),0,IF(N(U78)>0,U78+ROW()/1000000,0)) -> 0
A79: WLS001 | B79: WOODLAND CHOC (BROWN JHB) | C79: Hide | D79: Active | E79: =SUMIFS('CPT Count'!$D:$D,'CPT Count'!$A:$A,$A79)-SUMIFS('Weekly Sales'!$F:$F,'Weekly Sales'!$H:$H,$A79,'Weekly Sales'!$I:$I,"CPT")+SUMIFS(Transfers!$F:$F,Transfers!$C:$C,$A79,Transfers!$J:$J,"CPT")-SUMIFS(Transfers!$F:$F,Transfers!$C:$C,$A79,Transfers!$I:$I,"CPT",Transfers!$H:$H,"<>Y")+SUMIFS('Stock Received'!$I:$I,'Stock Received'!$E:$E,$A79,'Stock Received'!$L:$L,"CPT") -> 0 | F79: =SUMIFS('JHB Count'!$E:$E,'JHB Count'!$F:$F,$A79)-SUMIFS('Weekly Sales'!$F:$F,'Weekly Sales'!$H:$H,$A79,'Weekly Sales'!$I:$I,"JHB")+SUMIFS(Transfers!$F:$F,Transfers!$C:$C,$A79,Transfers!$J:$J,"JHB")-SUMIFS(Transfers!$F:$F,Transfers!$C:$C,$A79,Transfers!$I:$I,"JHB",Transfers!$H:$H,"<>Y")+SUMIFS('Stock Received'!$I:$I,'Stock Received'!$E:$E,$A79,'Stock Received'!$L:$L,"JHB") -> 0.03 | G79: =SUMIFS('DBN Count'!$D:$D,'DBN Count'!$E:$E,$A79)-SUMIFS('Weekly Sales'!$F:$F,'Weekly Sales'!$H:$H,$A79,'Weekly Sales'!$I:$I,"DBN")+SUMIFS(Transfers!$F:$F,Transfers!$C:$C,$A79,Transfers!$J:$J,"DBN")-SUMIFS(Transfers!$F:$F,Transfers!$C:$C,$A79,Transfers!$I:$I,"DBN",Transfers!$H:$H,"<>Y")+SUMIFS('Stock Received'!$I:$I,'Stock Received'!$E:$E,$A79,'Stock Received'!$L:$L,"DBN") -> 0 | H79: =E79+F79+G79 -> 0.03 | I79: =SUMIFS('Weekly Sales'!$F:$F,'Weekly Sales'!$H:$H,$A79) -> 308.17 | J79: =SUMIFS(Orders!$L:$L,Orders!$D:$D,$A79,Orders!$F:$F,">="&J$4,Orders!$F:$F,"<"&EDATE(J$4,1)) -> 0 | K79: =SUMIFS(Orders!$L:$L,Orders!$D:$D,$A79,Orders!$F:$F,">="&K$4,Orders!$F:$F,"<"&EDATE(K$4,1)) -> 1000 | L79: =SUMIFS(Orders!$L:$L,Orders!$D:$D,$A79,Orders!$F:$F,">="&L$4,Orders!$F:$F,"<"&EDATE(L$4,1)) -> 0 | M79: =N79-J79-K79-L79 -> 0 | N79: =SUMIFS(Orders!$L:$L,Orders!$D:$D,$A79) -> 1000 | O79: =H79+N79 -> 1000.03 | P79: 780 | Q79: =IF(SUMIFS('Sales History'!$E:$E,'Sales History'!$G:$G,$A79)>0,SUMIFS('Sales History'!$E:$E,'Sales History'!$G:$G,$A79)/Settings!$B$4,N(P79)) -> 780 | R79: =IF(SUMIFS('Sales History'!$E:$E,'Sales History'!$G:$G,$A79)>0,"6-month history",IF(N(P79)>0,"Current sheet","No sales data")) -> Current sheet | S79: =IF(Q79>0,H79/Q79,"") -> 3.8461538e-05 | T79: 500 | U79: =IF(T79="","",MAX(0,T79-O79)) -> 0 | V79: =IF(D79="End of range","END OF RANGE",IF(T79="","NO BUFFER SET",IF(H79<=0,IF(O79<T79,"OUT - REORDER","OUT - ON ORDER"),IF(O79<T79,"REORDER",IF(H79<T79,"LOW - ON ORDER",IF(AND(S79<>"",N(S79)>Settings!$B$5),"SLOW MOVER","OK")))))) -> LOW - ON ORDER | X79: =IF(OR(D79="End of range",U79=""),0,IF(N(U79)>0,U79+ROW()/1000000,0)) -> 0
A80: WLS002 | B80: WOODLAND WHISKEY (TAN JHB) | C80: Hide | D80: Active | E80: =SUMIFS('CPT Count'!$D:$D,'CPT Count'!$A:$A,$A80)-SUMIFS('Weekly Sales'!$F:$F,'Weekly Sales'!$H:$H,$A80,'Weekly Sales'!$I:$I,"CPT")+SUMIFS(Transfers!$F:$F,Transfers!$C:$C,$A80,Transfers!$J:$J,"CPT")-SUMIFS(Transfers!$F:$F,Transfers!$C:$C,$A80,Transfers!$I:$I,"CPT",Transfers!$H:$H,"<>Y")+SUMIFS('Stock Received'!$I:$I,'Stock Received'!$E:$E,$A80,'Stock Received'!$L:$L,"CPT") -> 0 | F80: =SUMIFS('JHB Count'!$E:$E,'JHB Count'!$F:$F,$A80)-SUMIFS('Weekly Sales'!$F:$F,'Weekly Sales'!$H:$H,$A80,'Weekly Sales'!$I:$I,"JHB")+SUMIFS(Transfers!$F:$F,Transfers!$C:$C,$A80,Transfers!$J:$J,"JHB")-SUMIFS(Transfers!$F:$F,Transfers!$C:$C,$A80,Transfers!$I:$I,"JHB",Transfers!$H:$H,"<>Y")+SUMIFS('Stock Received'!$I:$I,'Stock Received'!$E:$E,$A80,'Stock Received'!$L:$L,"JHB") -> 613 | G80: =SUMIFS('DBN Count'!$D:$D,'DBN Count'!$E:$E,$A80)-SUMIFS('Weekly Sales'!$F:$F,'Weekly Sales'!$H:$H,$A80,'Weekly Sales'!$I:$I,"DBN")+SUMIFS(Transfers!$F:$F,Transfers!$C:$C,$A80,Transfers!$J:$J,"DBN")-SUMIFS(Transfers!$F:$F,Transfers!$C:$C,$A80,Transfers!$I:$I,"DBN",Transfers!$H:$H,"<>Y")+SUMIFS('Stock Received'!$I:$I,'Stock Received'!$E:$E,$A80,'Stock Received'!$L:$L,"DBN") -> 0 | H80: =E80+F80+G80 -> 613 | I80: =SUMIFS('Weekly Sales'!$F:$F,'Weekly Sales'!$H:$H,$A80) -> 115 | J80: =SUMIFS(Orders!$L:$L,Orders!$D:$D,$A80,Orders!$F:$F,">="&J$4,Orders!$F:$F,"<"&EDATE(J$4,1)) -> 0 | K80: =SUMIFS(Orders!$L:$L,Orders!$D:$D,$A80,Orders!$F:$F,">="&K$4,Orders!$F:$F,"<"&EDATE(K$4,1)) -> 1000 | L80: =SUMIFS(Orders!$L:$L,Orders!$D:$D,$A80,Orders!$F:$F,">="&L$4,Orders!$F:$F,"<"&EDATE(L$4,1)) -> 0 | M80: =N80-J80-K80-L80 -> 0 | N80: =SUMIFS(Orders!$L:$L,Orders!$D:$D,$A80) -> 1000 | O80: =H80+N80 -> 1613 | P80: 650 | Q80: =IF(SUMIFS('Sales History'!$E:$E,'Sales History'!$G:$G,$A80)>0,SUMIFS('Sales History'!$E:$E,'Sales History'!$G:$G,$A80)/Settings!$B$4,N(P80)) -> 650 | R80: =IF(SUMIFS('Sales History'!$E:$E,'Sales History'!$G:$G,$A80)>0,"6-month history",IF(N(P80)>0,"Current sheet","No sales data")) -> Current sheet | S80: =IF(Q80>0,H80/Q80,"") -> 0.94307692 | T80: 500 | U80: =IF(T80="","",MAX(0,T80-O80)) -> 0 | V80: =IF(D80="End of range","END OF RANGE",IF(T80="","NO BUFFER SET",IF(H80<=0,IF(O80<T80,"OUT - REORDER","OUT - ON ORDER"),IF(O80<T80,"REORDER",IF(H80<T80,"LOW - ON ORDER",IF(AND(S80<>"",N(S80)>Settings!$B$5),"SLOW MOVER","OK")))))) -> OK | X80: =IF(OR(D80="End of range",U80=""),0,IF(N(U80)>0,U80+ROW()/1000000,0)) -> 0
A81: WLS003 | B81: WOODLAND NERO (CHARCOAL JHB) | C81: Hide | D81: Active | E81: =SUMIFS('CPT Count'!$D:$D,'CPT Count'!$A:$A,$A81)-SUMIFS('Weekly Sales'!$F:$F,'Weekly Sales'!$H:$H,$A81,'Weekly Sales'!$I:$I,"CPT")+SUMIFS(Transfers!$F:$F,Transfers!$C:$C,$A81,Transfers!$J:$J,"CPT")-SUMIFS(Transfers!$F:$F,Transfers!$C:$C,$A81,Transfers!$I:$I,"CPT",Transfers!$H:$H,"<>Y")+SUMIFS('Stock Received'!$I:$I,'Stock Received'!$E:$E,$A81,'Stock Received'!$L:$L,"CPT") -> 0 | F81: =SUMIFS('JHB Count'!$E:$E,'JHB Count'!$F:$F,$A81)-SUMIFS('Weekly Sales'!$F:$F,'Weekly Sales'!$H:$H,$A81,'Weekly Sales'!$I:$I,"JHB")+SUMIFS(Transfers!$F:$F,Transfers!$C:$C,$A81,Transfers!$J:$J,"JHB")-SUMIFS(Transfers!$F:$F,Transfers!$C:$C,$A81,Transfers!$I:$I,"JHB",Transfers!$H:$H,"<>Y")+SUMIFS('Stock Received'!$I:$I,'Stock Received'!$E:$E,$A81,'Stock Received'!$L:$L,"JHB") -> 711.29 | G81: =SUMIFS('DBN Count'!$D:$D,'DBN Count'!$E:$E,$A81)-SUMIFS('Weekly Sales'!$F:$F,'Weekly Sales'!$H:$H,$A81,'Weekly Sales'!$I:$I,"DBN")+SUMIFS(Transfers!$F:$F,Transfers!$C:$C,$A81,Transfers!$J:$J,"DBN")-SUMIFS(Transfers!$F:$F,Transfers!$C:$C,$A81,Transfers!$I:$I,"DBN",Transfers!$H:$H,"<>Y")+SUMIFS('Stock Received'!$I:$I,'Stock Received'!$E:$E,$A81,'Stock Received'!$L:$L,"DBN") -> 0 | H81: =E81+F81+G81 -> 711.29 | I81: =SUMIFS('Weekly Sales'!$F:$F,'Weekly Sales'!$H:$H,$A81) -> 72.71 | J81: =SUMIFS(Orders!$L:$L,Orders!$D:$D,$A81,Orders!$F:$F,">="&J$4,Orders!$F:$F,"<"&EDATE(J$4,1)) -> 0 | K81: =SUMIFS(Orders!$L:$L,Orders!$D:$D,$A81,Orders!$F:$F,">="&K$4,Orders!$F:$F,"<"&EDATE(K$4,1)) -> 0 | L81: =SUMIFS(Orders!$L:$L,Orders!$D:$D,$A81,Orders!$F:$F,">="&L$4,Orders!$F:$F,"<"&EDATE(L$4,1)) -> 0 | M81: =N81-J81-K81-L81 -> 0 | N81: =SUMIFS(Orders!$L:$L,Orders!$D:$D,$A81) -> 0 | O81: =H81+N81 -> 711.29 | P81: 190 | Q81: =IF(SUMIFS('Sales History'!$E:$E,'Sales History'!$G:$G,$A81)>0,SUMIFS('Sales History'!$E:$E,'Sales History'!$G:$G,$A81)/Settings!$B$4,N(P81)) -> 190 | R81: =IF(SUMIFS('Sales History'!$E:$E,'Sales History'!$G:$G,$A81)>0,"6-month history",IF(N(P81)>0,"Current sheet","No sales data")) -> Current sheet | S81: =IF(Q81>0,H81/Q81,"") -> 3.7436316 | T81: 300 | U81: =IF(T81="","",MAX(0,T81-O81)) -> 0 | V81: =IF(D81="End of range","END OF RANGE",IF(T81="","NO BUFFER SET",IF(H81<=0,IF(O81<T81,"OUT - REORDER","OUT - ON ORDER"),IF(O81<T81,"REORDER",IF(H81<T81,"LOW - ON ORDER",IF(AND(S81<>"",N(S81)>Settings!$B$5),"SLOW MOVER","OK")))))) -> OK | X81: =IF(OR(D81="End of range",U81=""),0,IF(N(U81)>0,U81+ROW()/1000000,0)) -> 0
A82: CAP003 | B82: CAPE BUFFALO BUTTERSCOTCH | C82: Hide | D82: Active | E82: =SUMIFS('CPT Count'!$D:$D,'CPT Count'!$A:$A,$A82)-SUMIFS('Weekly Sales'!$F:$F,'Weekly Sales'!$H:$H,$A82,'Weekly Sales'!$I:$I,"CPT")+SUMIFS(Transfers!$F:$F,Transfers!$C:$C,$A82,Transfers!$J:$J,"CPT")-SUMIFS(Transfers!$F:$F,Transfers!$C:$C,$A82,Transfers!$I:$I,"CPT",Transfers!$H:$H,"<>Y")+SUMIFS('Stock Received'!$I:$I,'Stock Received'!$E:$E,$A82,'Stock Received'!$L:$L,"CPT") -> 439.1 | F82: =SUMIFS('JHB Count'!$E:$E,'JHB Count'!$F:$F,$A82)-SUMIFS('Weekly Sales'!$F:$F,'Weekly Sales'!$H:$H,$A82,'Weekly Sales'!$I:$I,"JHB")+SUMIFS(Transfers!$F:$F,Transfers!$C:$C,$A82,Transfers!$J:$J,"JHB")-SUMIFS(Transfers!$F:$F,Transfers!$C:$C,$A82,Transfers!$I:$I,"JHB",Transfers!$H:$H,"<>Y")+SUMIFS('Stock Received'!$I:$I,'Stock Received'!$E:$E,$A82,'Stock Received'!$L:$L,"JHB") -> 27.79 | G82: =SUMIFS('DBN Count'!$D:$D,'DBN Count'!$E:$E,$A82)-SUMIFS('Weekly Sales'!$F:$F,'Weekly Sales'!$H:$H,$A82,'Weekly Sales'!$I:$I,"DBN")+SUMIFS(Transfers!$F:$F,Transfers!$C:$C,$A82,Transfers!$J:$J,"DBN")-SUMIFS(Transfers!$F:$F,Transfers!$C:$C,$A82,Transfers!$I:$I,"DBN",Transfers!$H:$H,"<>Y")+SUMIFS('Stock Received'!$I:$I,'Stock Received'!$E:$E,$A82,'Stock Received'!$L:$L,"DBN") -> 0 | H82: =E82+F82+G82 -> 466.89 | I82: =SUMIFS('Weekly Sales'!$F:$F,'Weekly Sales'!$H:$H,$A82) -> 102.36 | J82: =SUMIFS(Orders!$L:$L,Orders!$D:$D,$A82,Orders!$F:$F,">="&J$4,Orders!$F:$F,"<"&EDATE(J$4,1)) -> 0 | K82: =SUMIFS(Orders!$L:$L,Orders!$D:$D,$A82,Orders!$F:$F,">="&K$4,Orders!$F:$F,"<"&EDATE(K$4,1)) -> 0 | L82: =SUMIFS(Orders!$L:$L,Orders!$D:$D,$A82,Orders!$F:$F,">="&L$4,Orders!$F:$F,"<"&EDATE(L$4,1)) -> 0 | M82: =N82-J82-K82-L82 -> 0 | N82: =SUMIFS(Orders!$L:$L,Orders!$D:$D,$A82) -> 0 | O82: =H82+N82 -> 466.89 | P82: 100 | Q82: =IF(SUMIFS('Sales History'!$E:$E,'Sales History'!$G:$G,$A82)>0,SUMIFS('Sales History'!$E:$E,'Sales History'!$G:$G,$A82)/Settings!$B$4,N(P82)) -> 100 | R82: =IF(SUMIFS('Sales History'!$E:$E,'Sales History'!$G:$G,$A82)>0,"6-month history",IF(N(P82)>0,"Current sheet","No sales data")) -> Current sheet | S82: =IF(Q82>0,H82/Q82,"") -> 4.6689 | T82: 300 | U82: =IF(T82="","",MAX(0,T82-O82)) -> 0 | V82: =IF(D82="End of range","END OF RANGE",IF(T82="","NO BUFFER SET",IF(H82<=0,IF(O82<T82,"OUT - REORDER","OUT - ON ORDER"),IF(O82<T82,"REORDER",IF(H82<T82,"LOW - ON ORDER",IF(AND(S82<>"",N(S82)>Settings!$B$5),"SLOW MOVER","OK")))))) -> OK | X82: =IF(OR(D82="End of range",U82=""),0,IF(N(U82)>0,U82+ROW()/1000000,0)) -> 0
A83: CAP002 | B83: CAPE BUFFALO COPPER | C83: Hide | D83: Active | E83: =SUMIFS('CPT Count'!$D:$D,'CPT Count'!$A:$A,$A83)-SUMIFS('Weekly Sales'!$F:$F,'Weekly Sales'!$H:$H,$A83,'Weekly Sales'!$I:$I,"CPT")+SUMIFS(Transfers!$F:$F,Transfers!$C:$C,$A83,Transfers!$J:$J,"CPT")-SUMIFS(Transfers!$F:$F,Transfers!$C:$C,$A83,Transfers!$I:$I,"CPT",Transfers!$H:$H,"<>Y")+SUMIFS('Stock Received'!$I:$I,'Stock Received'!$E:$E,$A83,'Stock Received'!$L:$L,"CPT") -> 405.67 | F83: =SUMIFS('JHB Count'!$E:$E,'JHB Count'!$F:$F,$A83)-SUMIFS('Weekly Sales'!$F:$F,'Weekly Sales'!$H:$H,$A83,'Weekly Sales'!$I:$I,"JHB")+SUMIFS(Transfers!$F:$F,Transfers!$C:$C,$A83,Transfers!$J:$J,"JHB")-SUMIFS(Transfers!$F:$F,Transfers!$C:$C,$A83,Transfers!$I:$I,"JHB",Transfers!$H:$H,"<>Y")+SUMIFS('Stock Received'!$I:$I,'Stock Received'!$E:$E,$A83,'Stock Received'!$L:$L,"JHB") -> 104 | G83: =SUMIFS('DBN Count'!$D:$D,'DBN Count'!$E:$E,$A83)-SUMIFS('Weekly Sales'!$F:$F,'Weekly Sales'!$H:$H,$A83,'Weekly Sales'!$I:$I,"DBN")+SUMIFS(Transfers!$F:$F,Transfers!$C:$C,$A83,Transfers!$J:$J,"DBN")-SUMIFS(Transfers!$F:$F,Transfers!$C:$C,$A83,Transfers!$I:$I,"DBN",Transfers!$H:$H,"<>Y")+SUMIFS('Stock Received'!$I:$I,'Stock Received'!$E:$E,$A83,'Stock Received'!$L:$L,"DBN") -> 0 | H83: =E83+F83+G83 -> 509.67 | I83: =SUMIFS('Weekly Sales'!$F:$F,'Weekly Sales'!$H:$H,$A83) -> 0 | J83: =SUMIFS(Orders!$L:$L,Orders!$D:$D,$A83,Orders!$F:$F,">="&J$4,Orders!$F:$F,"<"&EDATE(J$4,1)) -> 0 | K83: =SUMIFS(Orders!$L:$L,Orders!$D:$D,$A83,Orders!$F:$F,">="&K$4,Orders!$F:$F,"<"&EDATE(K$4,1)) -> 0 | L83: =SUMIFS(Orders!$L:$L,Orders!$D:$D,$A83,Orders!$F:$F,">="&L$4,Orders!$F:$F,"<"&EDATE(L$4,1)) -> 0 | M83: =N83-J83-K83-L83 -> 0 | N83: =SUMIFS(Orders!$L:$L,Orders!$D:$D,$A83) -> 0 | O83: =H83+N83 -> 509.67 | P83: 75 | Q83: =IF(SUMIFS('Sales History'!$E:$E,'Sales History'!$G:$G,$A83)>0,SUMIFS('Sales History'!$E:$E,'Sales History'!$G:$G,$A83)/Settings!$B$4,N(P83)) -> 75 | R83: =IF(SUMIFS('Sales History'!$E:$E,'Sales History'!$G:$G,$A83)>0,"6-month history",IF(N(P83)>0,"Current sheet","No sales data")) -> Current sheet | S83: =IF(Q83>0,H83/Q83,"") -> 6.7956 | T83: 300 | U83: =IF(T83="","",MAX(0,T83-O83)) -> 0 | V83: =IF(D83="End of range","END OF RANGE",IF(T83="","NO BUFFER SET",IF(H83<=0,IF(O83<T83,"OUT - REORDER","OUT - ON ORDER"),IF(O83<T83,"REORDER",IF(H83<T83,"LOW - ON ORDER",IF(AND(S83<>"",N(S83)>Settings!$B$5),"SLOW MOVER","OK")))))) -> OK | X83: =IF(OR(D83="End of range",U83=""),0,IF(N(U83)>0,U83+ROW()/1000000,0)) -> 0
A84: CAP009 | B84: CAPE BUFFALO RUST | C84: Hide | D84: Active | E84: =SUMIFS('CPT Count'!$D:$D,'CPT Count'!$A:$A,$A84)-SUMIFS('Weekly Sales'!$F:$F,'Weekly Sales'!$H:$H,$A84,'Weekly Sales'!$I:$I,"CPT")+SUMIFS(Transfers!$F:$F,Transfers!$C:$C,$A84,Transfers!$J:$J,"CPT")-SUMIFS(Transfers!$F:$F,Transfers!$C:$C,$A84,Transfers!$I:$I,"CPT",Transfers!$H:$H,"<>Y")+SUMIFS('Stock Received'!$I:$I,'Stock Received'!$E:$E,$A84,'Stock Received'!$L:$L,"CPT") -> 732.21 | F84: =SUMIFS('JHB Count'!$E:$E,'JHB Count'!$F:$F,$A84)-SUMIFS('Weekly Sales'!$F:$F,'Weekly Sales'!$H:$H,$A84,'Weekly Sales'!$I:$I,"JHB")+SUMIFS(Transfers!$F:$F,Transfers!$C:$C,$A84,Transfers!$J:$J,"JHB")-SUMIFS(Transfers!$F:$F,Transfers!$C:$C,$A84,Transfers!$I:$I,"JHB",Transfers!$H:$H,"<>Y")+SUMIFS('Stock Received'!$I:$I,'Stock Received'!$E:$E,$A84,'Stock Received'!$L:$L,"JHB") -> 23.62 | G84: =SUMIFS('DBN Count'!$D:$D,'DBN Count'!$E:$E,$A84)-SUMIFS('Weekly Sales'!$F:$F,'Weekly Sales'!$H:$H,$A84,'Weekly Sales'!$I:$I,"DBN")+SUMIFS(Transfers!$F:$F,Transfers!$C:$C,$A84,Transfers!$J:$J,"DBN")-SUMIFS(Transfers!$F:$F,Transfers!$C:$C,$A84,Transfers!$I:$I,"DBN",Transfers!$H:$H,"<>Y")+SUMIFS('Stock Received'!$I:$I,'Stock Received'!$E:$E,$A84,'Stock Received'!$L:$L,"DBN") -> 23.67 | H84: =E84+F84+G84 -> 779.5 | I84: =SUMIFS('Weekly Sales'!$F:$F,'Weekly Sales'!$H:$H,$A84) -> 24.17 | J84: =SUMIFS(Orders!$L:$L,Orders!$D:$D,$A84,Orders!$F:$F,">="&J$4,Orders!$F:$F,"<"&EDATE(J$4,1)) -> 0 | K84: =SUMIFS(Orders!$L:$L,Orders!$D:$D,$A84,Orders!$F:$F,">="&K$4,Orders!$F:$F,"<"&EDATE(K$4,1)) -> 0 | L84: =SUMIFS(Orders!$L:$L,Orders!$D:$D,$A84,Orders!$F:$F,">="&L$4,Orders!$F:$F,"<"&EDATE(L$4,1)) -> 0 | M84: =N84-J84-K84-L84 -> 0 | N84: =SUMIFS(Orders!$L:$L,Orders!$D:$D,$A84) -> 0 | O84: =H84+N84 -> 779.5 | P84: 90 | Q84: =IF(SUMIFS('Sales History'!$E:$E,'Sales History'!$G:$G,$A84)>0,SUMIFS('Sales History'!$E:$E,'Sales History'!$G:$G,$A84)/Settings!$B$4,N(P84)) -> 90 | R84: =IF(SUMIFS('Sales History'!$E:$E,'Sales History'!$G:$G,$A84)>0,"6-month history",IF(N(P84)>0,"Current sheet","No sales data")) -> Current sheet | S84: =IF(Q84>0,H84/Q84,"") -> 8.6611111 | T84: 300 | U84: =IF(T84="","",MAX(0,T84-O84)) -> 0 | V84: =IF(D84="End of range","END OF RANGE",IF(T84="","NO BUFFER SET",IF(H84<=0,IF(O84<T84,"OUT - REORDER","OUT - ON ORDER"),IF(O84<T84,"REORDER",IF(H84<T84,"LOW - ON ORDER",IF(AND(S84<>"",N(S84)>Settings!$B$5),"SLOW MOVER","OK")))))) -> OK | X84: =IF(OR(D84="End of range",U84=""),0,IF(N(U84)>0,U84+ROW()/1000000,0)) -> 0
A85: CAP004 | B85: CAPE BUFFALO BAOBAB | C85: Hide | D85: Active | E85: =SUMIFS('CPT Count'!$D:$D,'CPT Count'!$A:$A,$A85)-SUMIFS('Weekly Sales'!$F:$F,'Weekly Sales'!$H:$H,$A85,'Weekly Sales'!$I:$I,"CPT")+SUMIFS(Transfers!$F:$F,Transfers!$C:$C,$A85,Transfers!$J:$J,"CPT")-SUMIFS(Transfers!$F:$F,Transfers!$C:$C,$A85,Transfers!$I:$I,"CPT",Transfers!$H:$H,"<>Y")+SUMIFS('Stock Received'!$I:$I,'Stock Received'!$E:$E,$A85,'Stock Received'!$L:$L,"CPT") -> 280.23 | F85: =SUMIFS('JHB Count'!$E:$E,'JHB Count'!$F:$F,$A85)-SUMIFS('Weekly Sales'!$F:$F,'Weekly Sales'!$H:$H,$A85,'Weekly Sales'!$I:$I,"JHB")+SUMIFS(Transfers!$F:$F,Transfers!$C:$C,$A85,Transfers!$J:$J,"JHB")-SUMIFS(Transfers!$F:$F,Transfers!$C:$C,$A85,Transfers!$I:$I,"JHB",Transfers!$H:$H,"<>Y")+SUMIFS('Stock Received'!$I:$I,'Stock Received'!$E:$E,$A85,'Stock Received'!$L:$L,"JHB") -> 64 | G85: =SUMIFS('DBN Count'!$D:$D,'DBN Count'!$E:$E,$A85)-SUMIFS('Weekly Sales'!$F:$F,'Weekly Sales'!$H:$H,$A85,'Weekly Sales'!$I:$I,"DBN")+SUMIFS(Transfers!$F:$F,Transfers!$C:$C,$A85,Transfers!$J:$J,"DBN")-SUMIFS(Transfers!$F:$F,Transfers!$C:$C,$A85,Transfers!$I:$I,"DBN",Transfers!$H:$H,"<>Y")+SUMIFS('Stock Received'!$I:$I,'Stock Received'!$E:$E,$A85,'Stock Received'!$L:$L,"DBN") -> 0 | H85: =E85+F85+G85 -> 344.23 | I85: =SUMIFS('Weekly Sales'!$F:$F,'Weekly Sales'!$H:$H,$A85) -> 23.77 | J85: =SUMIFS(Orders!$L:$L,Orders!$D:$D,$A85,Orders!$F:$F,">="&J$4,Orders!$F:$F,"<"&EDATE(J$4,1)) -> 0 | K85: =SUMIFS(Orders!$L:$L,Orders!$D:$D,$A85,Orders!$F:$F,">="&K$4,Orders!$F:$F,"<"&EDATE(K$4,1)) -> 0 | L85: =SUMIFS(Orders!$L:$L,Orders!$D:$D,$A85,Orders!$F:$F,">="&L$4,Orders!$F:$F,"<"&EDATE(L$4,1)) -> 0 | M85: =N85-J85-K85-L85 -> 0 | N85: =SUMIFS(Orders!$L:$L,Orders!$D:$D,$A85) -> 0 | O85: =H85+N85 -> 344.23 | P85: 15 | Q85: =IF(SUMIFS('Sales History'!$E:$E,'Sales History'!$G:$G,$A85)>0,SUMIFS('Sales History'!$E:$E,'Sales History'!$G:$G,$A85)/Settings!$B$4,N(P85)) -> 15 | R85: =IF(SUMIFS('Sales History'!$E:$E,'Sales History'!$G:$G,$A85)>0,"6-month history",IF(N(P85)>0,"Current sheet","No sales data")) -> Current sheet | S85: =IF(Q85>0,H85/Q85,"") -> 22.948667 | T85: 200 | U85: =IF(T85="","",MAX(0,T85-O85)) -> 0 | V85: =IF(D85="End of range","END OF RANGE",IF(T85="","NO BUFFER SET",IF(H85<=0,IF(O85<T85,"OUT - REORDER","OUT - ON ORDER"),IF(O85<T85,"REORDER",IF(H85<T85,"LOW - ON ORDER",IF(AND(S85<>"",N(S85)>Settings!$B$5),"SLOW MOVER","OK")))))) -> SLOW MOVER | X85: =IF(OR(D85="End of range",U85=""),0,IF(N(U85)>0,U85+ROW()/1000000,0)) -> 0
... A90: ANT004 | B90: ANTIQUE TOBACCO | C90: Hide | D90: Active | E90: =SUMIFS('CPT Count'!$D:$D,'CPT Count'!$A:$A,$A90)-SUMIFS('Weekly Sales'!$F:$F,'Weekly Sales'!$H:$H,$A90,'Weekly Sales'!$I:$I,"CPT")+SUMIFS(Transfers!$F:$F,Transfers!$C:$C,$A90,Transfers!$J:$J,"CPT")-SUMIFS(Transfers!$F:$F,Transfers!$C:$C,$A90,Transfers!$I:$I,"CPT",Transfers!$H:$H,"<>Y")+SUMIFS('Stock Received'!$I:$I,'Stock Received'!$E:$E,$A90,'Stock Received'!$L:$L,"CPT") -> 0 | F90: =SUMIFS('JHB Count'!$E:$E,'JHB Count'!$F:$F,$A90)-SUMIFS('Weekly Sales'!$F:$F,'Weekly Sales'!$H:$H,$A90,'Weekly Sales'!$I:$I,"JHB")+SUMIFS(Transfers!$F:$F,Transfers!$C:$C,$A90,Transfers!$J:$J,"JHB")-SUMIFS(Transfers!$F:$F,Transfers!$C:$C,$A90,Transfers!$I:$I,"JHB",Transfers!$H:$H,"<>Y")+SUMIFS('Stock Received'!$I:$I,'Stock Received'!$E:$E,$A90,'Stock Received'!$L:$L,"JHB") -> 668 | G90: =SUMIFS('DBN Count'!$D:$D,'DBN Count'!$E:$E,$A90)-SUMIFS('Weekly Sales'!$F:$F,'Weekly Sales'!$H:$H,$A90,'Weekly Sales'!$I:$I,"DBN")+SUMIFS(Transfers!$F:$F,Transfers!$C:$C,$A90,Transfers!$J:$J,"DBN")-SUMIFS(Transfers!$F:$F,Transfers!$C:$C,$A90,Transfers!$I:$I,"DBN",Transfers!$H:$H,"<>Y")+SUMIFS('Stock Received'!$I:$I,'Stock Received'!$E:$E,$A90,'Stock Received'!$L:$L,"DBN") -> 0 | H90: =E90+F90+G90 -> 668 | I90: =SUMIFS('Weekly Sales'!$F:$F,'Weekly Sales'!$H:$H,$A90) -> 0 | J90: =SUMIFS(Orders!$L:$L,Orders!$D:$D,$A90,Orders!$F:$F,">="&J$4,Orders!$F:$F,"<"&EDATE(J$4,1)) -> 300 | K90: =SUMIFS(Orders!$L:$L,Orders!$D:$D,$A90,Orders!$F:$F,">="&K$4,Orders!$F:$F,"<"&EDATE(K$4,1)) -> 300 | L90: =SUMIFS(Orders!$L:$L,Orders!$D:$D,$A90,Orders!$F:$F,">="&L$4,Orders!$F:$F,"<"&EDATE(L$4,1)) -> 0 | M90: =N90-J90-K90-L90 -> 0 | N90: =SUMIFS(Orders!$L:$L,Orders!$D:$D,$A90) -> 600 | O90: =H90+N90 -> 1268 | P90: 120 | Q90: =IF(SUMIFS('Sales History'!$E:$E,'Sales History'!$G:$G,$A90)>0,SUMIFS('Sales History'!$E:$E,'Sales History'!$G:$G,$A90)/Settings!$B$4,N(P90)) -> 120 | R90: =IF(SUMIFS('Sales History'!$E:$E,'Sales History'!$G:$G,$A90)>0,"6-month history",IF(N(P90)>0,"Current sheet","No sales data")) -> Current sheet | S90: =IF(Q90>0,H90/Q90,"") -> 5.5666667 | T90: 200 | U90: =IF(T90="","",MAX(0,T90-O90)) -> 0 | V90: =IF(D90="End of range","END OF RANGE",IF(T90="","NO BUFFER SET",IF(H90<=0,IF(O90<T90,"OUT - REORDER","OUT - ON ORDER"),IF(O90<T90,"REORDER",IF(H90<T90,"LOW - ON ORDER",IF(AND(S90<>"",N(S90)>Settings!$B$5),"SLOW MOVER","OK")))))) -> OK | X90: =IF(OR(D90="End of range",U90=""),0,IF(N(U90)>0,U90+ROW()/1000000,0)) -> 0
A91: OXF005 | B91: OXFORD GOLD | C91: Hide | D91: End of range | E91: =SUMIFS('CPT Count'!$D:$D,'CPT Count'!$A:$A,$A91)-SUMIFS('Weekly Sales'!$F:$F,'Weekly Sales'!$H:$H,$A91,'Weekly Sales'!$I:$I,"CPT")+SUMIFS(Transfers!$F:$F,Transfers!$C:$C,$A91,Transfers!$J:$J,"CPT")-SUMIFS(Transfers!$F:$F,Transfers!$C:$C,$A91,Transfers!$I:$I,"CPT",Transfers!$H:$H,"<>Y")+SUMIFS('Stock Received'!$I:$I,'Stock Received'!$E:$E,$A91,'Stock Received'!$L:$L,"CPT") -> 220 | F91: =SUMIFS('JHB Count'!$E:$E,'JHB Count'!$F:$F,$A91)-SUMIFS('Weekly Sales'!$F:$F,'Weekly Sales'!$H:$H,$A91,'Weekly Sales'!$I:$I,"JHB")+SUMIFS(Transfers!$F:$F,Transfers!$C:$C,$A91,Transfers!$J:$J,"JHB")-SUMIFS(Transfers!$F:$F,Transfers!$C:$C,$A91,Transfers!$I:$I,"JHB",Transfers!$H:$H,"<>Y")+SUMIFS('Stock Received'!$I:$I,'Stock Received'!$E:$E,$A91,'Stock Received'!$L:$L,"JHB") -> 0 | G91: =SUMIFS('DBN Count'!$D:$D,'DBN Count'!$E:$E,$A91)-SUMIFS('Weekly Sales'!$F:$F,'Weekly Sales'!$H:$H,$A91,'Weekly Sales'!$I:$I,"DBN")+SUMIFS(Transfers!$F:$F,Transfers!$C:$C,$A91,Transfers!$J:$J,"DBN")-SUMIFS(Transfers!$F:$F,Transfers!$C:$C,$A91,Transfers!$I:$I,"DBN",Transfers!$H:$H,"<>Y")+SUMIFS('Stock Received'!$I:$I,'Stock Received'!$E:$E,$A91,'Stock Received'!$L:$L,"DBN") -> 0 | H91: =E91+F91+G91 -> 220 | I91: =SUMIFS('Weekly Sales'!$F:$F,'Weekly Sales'!$H:$H,$A91) -> 0 | J91: =SUMIFS(Orders!$L:$L,Orders!$D:$D,$A91,Orders!$F:$F,">="&J$4,Orders!$F:$F,"<"&EDATE(J$4,1)) -> 0 | K91: =SUMIFS(Orders!$L:$L,Orders!$D:$D,$A91,Orders!$F:$F,">="&K$4,Orders!$F:$F,"<"&EDATE(K$4,1)) -> 0 | L91: =SUMIFS(Orders!$L:$L,Orders!$D:$D,$A91,Orders!$F:$F,">="&L$4,Orders!$F:$F,"<"&EDATE(L$4,1)) -> 0 | M91: =N91-J91-K91-L91 -> 0 | N91: =SUMIFS(Orders!$L:$L,Orders!$D:$D,$A91) -> 0 | O91: =H91+N91 -> 220 | Q91: =IF(SUMIFS('Sales History'!$E:$E,'Sales History'!$G:$G,$A91)>0,SUMIFS('Sales History'!$E:$E,'Sales History'!$G:$G,$A91)/Settings!$B$4,N(P91)) -> 0 | R91: =IF(SUMIFS('Sales History'!$E:$E,'Sales History'!$G:$G,$A91)>0,"6-month history",IF(N(P91)>0,"Current sheet","No sales data")) -> No sales data | S91: =IF(Q91>0,H91/Q91,"") | U91: =IF(T91="","",MAX(0,T91-O91)) | V91: =IF(D91="End of range","END OF RANGE",IF(T91="","NO BUFFER SET",IF(H91<=0,IF(O91<T91,"OUT - REORDER","OUT - ON ORDER"),IF(O91<T91,"REORDER",IF(H91<T91,"LOW - ON ORDER",IF(AND(S91<>"",N(S91)>Settings!$B$5),"SLOW MOVER","OK")))))) -> END OF RANGE | X91: =IF(OR(D91="End of range",U91=""),0,IF(N(U91)>0,U91+ROW()/1000000,0)) -> 0
A92: MOU001 | B92: MOUNTAIN DARK BROWN | C92: Hide | D92: Active | E92: =SUMIFS('CPT Count'!$D:$D,'CPT Count'!$A:$A,$A92)-SUMIFS('Weekly Sales'!$F:$F,'Weekly Sales'!$H:$H,$A92,'Weekly Sales'!$I:$I,"CPT")+SUMIFS(Transfers!$F:$F,Transfers!$C:$C,$A92,Transfers!$J:$J,"CPT")-SUMIFS(Transfers!$F:$F,Transfers!$C:$C,$A92,Transfers!$I:$I,"CPT",Transfers!$H:$H,"<>Y")+SUMIFS('Stock Received'!$I:$I,'Stock Received'!$E:$E,$A92,'Stock Received'!$L:$L,"CPT") -> 326.54 | F92: =SUMIFS('JHB Count'!$E:$E,'JHB Count'!$F:$F,$A92)-SUMIFS('Weekly Sales'!$F:$F,'Weekly Sales'!$H:$H,$A92,'Weekly Sales'!$I:$I,"JHB")+SUMIFS(Transfers!$F:$F,Transfers!$C:$C,$A92,Transfers!$J:$J,"JHB")-SUMIFS(Transfers!$F:$F,Transfers!$C:$C,$A92,Transfers!$I:$I,"JHB",Transfers!$H:$H,"<>Y")+SUMIFS('Stock Received'!$I:$I,'Stock Received'!$E:$E,$A92,'Stock Received'!$L:$L,"JHB") -> 20 | G92: =SUMIFS('DBN Count'!$D:$D,'DBN Count'!$E:$E,$A92)-SUMIFS('Weekly Sales'!$F:$F,'Weekly Sales'!$H:$H,$A92,'Weekly Sales'!$I:$I,"DBN")+SUMIFS(Transfers!$F:$F,Transfers!$C:$C,$A92,Transfers!$J:$J,"DBN")-SUMIFS(Transfers!$F:$F,Transfers!$C:$C,$A92,Transfers!$I:$I,"DBN",Transfers!$H:$H,"<>Y")+SUMIFS('Stock Received'!$I:$I,'Stock Received'!$E:$E,$A92,'Stock Received'!$L:$L,"DBN") -> 0 | H92: =E92+F92+G92 -> 346.54 | I92: =SUMIFS('Weekly Sales'!$F:$F,'Weekly Sales'!$H:$H,$A92) -> 0 | J92: =SUMIFS(Orders!$L:$L,Orders!$D:$D,$A92,Orders!$F:$F,">="&J$4,Orders!$F:$F,"<"&EDATE(J$4,1)) -> 0 | K92: =SUMIFS(Orders!$L:$L,Orders!$D:$D,$A92,Orders!$F:$F,">="&K$4,Orders!$F:$F,"<"&EDATE(K$4,1)) -> 0 | L92: =SUMIFS(Orders!$L:$L,Orders!$D:$D,$A92,Orders!$F:$F,">="&L$4,Orders!$F:$F,"<"&EDATE(L$4,1)) -> 0 | M92: =N92-J92-K92-L92 -> 0 | N92: =SUMIFS(Orders!$L:$L,Orders!$D:$D,$A92) -> 0 | O92: =H92+N92 -> 346.54 | Q92: =IF(SUMIFS('Sales History'!$E:$E,'Sales History'!$G:$G,$A92)>0,SUMIFS('Sales History'!$E:$E,'Sales History'!$G:$G,$A92)/Settings!$B$4,N(P92)) -> 0 | R92: =IF(SUMIFS('Sales History'!$E:$E,'Sales History'!$G:$G,$A92)>0,"6-month history",IF(N(P92)>0,"Current sheet","No sales data")) -> No sales data | S92: =IF(Q92>0,H92/Q92,"") | T92: 200 | U92: =IF(T92="","",MAX(0,T92-O92)) -> 0 | V92: =IF(D92="End of range","END OF RANGE",IF(T92="","NO BUFFER SET",IF(H92<=0,IF(O92<T92,"OUT - REORDER","OUT - ON ORDER"),IF(O92<T92,"REORDER",IF(H92<T92,"LOW - ON ORDER",IF(AND(S92<>"",N(S92)>Settings!$B$5),"SLOW MOVER","OK")))))) -> OK | X92: =IF(OR(D92="End of range",U92=""),0,IF(N(U92)>0,U92+ROW()/1000000,0)) -> 0
A93: MOU002 | B93: MOUNTAIN LIGHT BROWN | C93: Hide | D93: Active | E93: =SUMIFS('CPT Count'!$D:$D,'CPT Count'!$A:$A,$A93)-SUMIFS('Weekly Sales'!$F:$F,'Weekly Sales'!$H:$H,$A93,'Weekly Sales'!$I:$I,"CPT")+SUMIFS(Transfers!$F:$F,Transfers!$C:$C,$A93,Transfers!$J:$J,"CPT")-SUMIFS(Transfers!$F:$F,Transfers!$C:$C,$A93,Transfers!$I:$I,"CPT",Transfers!$H:$H,"<>Y")+SUMIFS('Stock Received'!$I:$I,'Stock Received'!$E:$E,$A93,'Stock Received'!$L:$L,"CPT") -> 432 | F93: =SUMIFS('JHB Count'!$E:$E,'JHB Count'!$F:$F,$A93)-SUMIFS('Weekly Sales'!$F:$F,'Weekly Sales'!$H:$H,$A93,'Weekly Sales'!$I:$I,"JHB")+SUMIFS(Transfers!$F:$F,Transfers!$C:$C,$A93,Transfers!$J:$J,"JHB")-SUMIFS(Transfers!$F:$F,Transfers!$C:$C,$A93,Transfers!$I:$I,"JHB",Transfers!$H:$H,"<>Y")+SUMIFS('Stock Received'!$I:$I,'Stock Received'!$E:$E,$A93,'Stock Received'!$L:$L,"JHB") -> 20 | G93: =SUMIFS('DBN Count'!$D:$D,'DBN Count'!$E:$E,$A93)-SUMIFS('Weekly Sales'!$F:$F,'Weekly Sales'!$H:$H,$A93,'Weekly Sales'!$I:$I,"DBN")+SUMIFS(Transfers!$F:$F,Transfers!$C:$C,$A93,Transfers!$J:$J,"DBN")-SUMIFS(Transfers!$F:$F,Transfers!$C:$C,$A93,Transfers!$I:$I,"DBN",Transfers!$H:$H,"<>Y")+SUMIFS('Stock Received'!$I:$I,'Stock Received'!$E:$E,$A93,'Stock Received'!$L:$L,"DBN") -> 0 | H93: =E93+F93+G93 -> 452 | I93: =SUMIFS('Weekly Sales'!$F:$F,'Weekly Sales'!$H:$H,$A93) -> 0 | J93: =SUMIFS(Orders!$L:$L,Orders!$D:$D,$A93,Orders!$F:$F,">="&J$4,Orders!$F:$F,"<"&EDATE(J$4,1)) -> 0 | K93: =SUMIFS(Orders!$L:$L,Orders!$D:$D,$A93,Orders!$F:$F,">="&K$4,Orders!$F:$F,"<"&EDATE(K$4,1)) -> 0 | L93: =SUMIFS(Orders!$L:$L,Orders!$D:$D,$A93,Orders!$F:$F,">="&L$4,Orders!$F:$F,"<"&EDATE(L$4,1)) -> 0 | M93: =N93-J93-K93-L93 -> 0 | N93: =SUMIFS(Orders!$L:$L,Orders!$D:$D,$A93) -> 0 | O93: =H93+N93 -> 452 | Q93: =IF(SUMIFS('Sales History'!$E:$E,'Sales History'!$G:$G,$A93)>0,SUMIFS('Sales History'!$E:$E,'Sales History'!$G:$G,$A93)/Settings!$B$4,N(P93)) -> 0 | R93: =IF(SUMIFS('Sales History'!$E:$E,'Sales History'!$G:$G,$A93)>0,"6-month history",IF(N(P93)>0,"Current sheet","No sales data")) -> No sales data | S93: =IF(Q93>0,H93/Q93,"") | T93: 200 | U93: =IF(T93="","",MAX(0,T93-O93)) -> 0 | V93: =IF(D93="End of range","END OF RANGE",IF(T93="","NO BUFFER SET",IF(H93<=0,IF(O93<T93,"OUT - REORDER","OUT - ON ORDER"),IF(O93<T93,"REORDER",IF(H93<T93,"LOW - ON ORDER",IF(AND(S93<>"",N(S93)>Settings!$B$5),"SLOW MOVER","OK")))))) -> OK | X93: =IF(OR(D93="End of range",U93=""),0,IF(N(U93)>0,U93+ROW()/1000000,0)) -> 0
A94: AMA001 | B94: AMANI CANYON | C94: Hide | D94: Active | E94: =SUMIFS('CPT Count'!$D:$D,'CPT Count'!$A:$A,$A94)-SUMIFS('Weekly Sales'!$F:$F,'Weekly Sales'!$H:$H,$A94,'Weekly Sales'!$I:$I,"CPT")+SUMIFS(Transfers!$F:$F,Transfers!$C:$C,$A94,Transfers!$J:$J,"CPT")-SUMIFS(Transfers!$F:$F,Transfers!$C:$C,$A94,Transfers!$I:$I,"CPT",Transfers!$H:$H,"<>Y")+SUMIFS('Stock Received'!$I:$I,'Stock Received'!$E:$E,$A94,'Stock Received'!$L:$L,"CPT") -> 0 | F94: =SUMIFS('JHB Count'!$E:$E,'JHB Count'!$F:$F,$A94)-SUMIFS('Weekly Sales'!$F:$F,'Weekly Sales'!$H:$H,$A94,'Weekly Sales'!$I:$I,"JHB")+SUMIFS(Transfers!$F:$F,Transfers!$C:$C,$A94,Transfers!$J:$J,"JHB")-SUMIFS(Transfers!$F:$F,Transfers!$C:$C,$A94,Transfers!$I:$I,"JHB",Transfers!$H:$H,"<>Y")+SUMIFS('Stock Received'!$I:$I,'Stock Received'!$E:$E,$A94,'Stock Received'!$L:$L,"JHB") -> 0 | G94: =SUMIFS('DBN Count'!$D:$D,'DBN Count'!$E:$E,$A94)-SUMIFS('Weekly Sales'!$F:$F,'Weekly Sales'!$H:$H,$A94,'Weekly Sales'!$I:$I,"DBN")+SUMIFS(Transfers!$F:$F,Transfers!$C:$C,$A94,Transfers!$J:$J,"DBN")-SUMIFS(Transfers!$F:$F,Transfers!$C:$C,$A94,Transfers!$I:$I,"DBN",Transfers!$H:$H,"<>Y")+SUMIFS('Stock Received'!$I:$I,'Stock Received'!$E:$E,$A94,'Stock Received'!$L:$L,"DBN") -> 0 | H94: =E94+F94+G94 -> 0 | I94: =SUMIFS('Weekly Sales'!$F:$F,'Weekly Sales'!$H:$H,$A94) -> 0 | J94: =SUMIFS(Orders!$L:$L,Orders!$D:$D,$A94,Orders!$F:$F,">="&J$4,Orders!$F:$F,"<"&EDATE(J$4,1)) -> 200 | K94: =SUMIFS(Orders!$L:$L,Orders!$D:$D,$A94,Orders!$F:$F,">="&K$4,Orders!$F:$F,"<"&EDATE(K$4,1)) -> 0 | L94: =SUMIFS(Orders!$L:$L,Orders!$D:$D,$A94,Orders!$F:$F,">="&L$4,Orders!$F:$F,"<"&EDATE(L$4,1)) -> 0 | M94: =N94-J94-K94-L94 -> 0 | N94: =SUMIFS(Orders!$L:$L,Orders!$D:$D,$A94) -> 200 | O94: =H94+N94 -> 200 | Q94: =IF(SUMIFS('Sales History'!$E:$E,'Sales History'!$G:$G,$A94)>0,SUMIFS('Sales History'!$E:$E,'Sales History'!$G:$G,$A94)/Settings!$B$4,N(P94)) -> 0 | R94: =IF(SUMIFS('Sales History'!$E:$E,'Sales History'!$G:$G,$A94)>0,"6-month history",IF(N(P94)>0,"Current sheet","No sales data")) -> No sales data | S94: =IF(Q94>0,H94/Q94,"") | T94: 50 | U94: =IF(T94="","",MAX(0,T94-O94)) -> 0 | V94: =IF(D94="End of range","END OF RANGE",IF(T94="","NO BUFFER SET",IF(H94<=0,IF(O94<T94,"OUT - REORDER","OUT - ON ORDER"),IF(O94<T94,"REORDER",IF(H94<T94,"LOW - ON ORDER",IF(AND(S94<>"",N(S94)>Settings!$B$5),"SLOW MOVER","OK")))))) -> OUT - ON ORDER | X94: =IF(OR(D94="End of range",U94=""),0,IF(N(U94)>0,U94+ROW()/1000000,0)) -> 0
